Workbook

Sheet メモ
A1: 45954 | B1: キックオフ＆共有フォルダルール決め
A2: 45969 | B2: 物理サーバ更新
A3: 45970 | B3: 物理サーバ更新
A4: 45971 | B4: 物理サーバ更新完了
B5: 物理サーバ更新中に、SSC社内で 部署毎・業務毎に
B6: 共有フォルダの運用ルール・管理担当 一次案を決める
A7: 46006 | B7: 進捗確認
B8: ↓共有フォルダ運用体制、MS365、セキュリティ対策 ⇄ IT基本勉強会、MS365勉強会 等 実施予定
A10: 46063 | B10: ①共有フォルダ：整備状況を報告､年月日フォルダの階層軽減効率化にあたって更新日時をファイル名に自動で付与するツールについてご相談。認識レベルによって漏れる可能性もあるが実効性は高いためインフィニティ様で検討いただく。
B11: ②クラウドバックアップ整備：現実的な選択肢についてご相談。「MS365OneDrive」手動にはなるがOffice込みなのでアプリ環境がなくてもデータを開くことができる「専用サービス」アプリ環境にダウンロードしないと開けないが必要なものだけ厳選すれば作業効率･費用面で候補となる。当課題は①③の状況を見ながら追って方向性を決めていく。
B12: ③事務作業自動化(AI化)：本日のメイン課題､具体的な取り組みについてご相談。今は生成AIのみならずAIエージェントも機能性や精度が充実してきており代表的なサービスを説明いただいた。いきなり広範囲･高負荷作業で検討するよりも身近な課題を前向きなメンバーでやりながらテンプレ化して共有する方が定着しやすいとのことで先ず社内ヒアリングで気軽な意見を収集してから具体的な考察に入ることとした。ミーティング終了後参加メンバーでヒアリング項目案を出し今週配布～来週半ばに回収～とりまとめ～次回2/24提出する。
B13: ④Q美レンタルサーバ移設検討報告(迷惑メールフィルター脆弱)
A15: 46073 | B15: 先日実施した業務改善ヒアリング（回答数：27名）の結果を踏まえ、DX推進に関してインフィニティ様へ相談したい内容を整理しましたので共有いたします。今回のヒアリングでは、主に以下の課題が確認されました。
B16: ・Excelへの手入力や転記、集計などの手作業が多い
B17: ・紙帳票での運用が残っており、作成・保管・検索に工数がかかっている
B18: ・定型業務が自動化されておらず、日常業務に時間を要している
B19: ・業務フローが属人化しており、確認や照合作業に時間がかかっている
B20: 上記課題を踏まえ、インフィニティ様へは主に以下の内容を相談予定です。
B21: ① 紙帳票の電子化の進め方：製造記録や各種帳票の電子化にあたり、最適な手法・ツール・導入方法について相談
B22: ② Excel業務の効率化・自動化：集計・転記・資料作成などの定型業務について、自動化の進め方および優先順位の整理
B23: ③ 業務フローの整理およびDX推進の進め方：現状業務の可視化、DX推進の優先順位、段階的な導入ロードマップの策定
B24: ④ AIツールの業務活用に関する導入方針：AIを活用可能な業務領域の整理および、社内での安全な活用環境の構築方法
B25: 今回の相談では、いきなりシステム導入を決定するのではなく、「どの業務からDXを進めるべきか」「どのような進め方が現実的か」といった全体方針を整理することを目的としています。
A27: 46077 | B27: 中土主任にて社内ヒアリング配布-回収-要約していただいた内容に基づいて社内業務効率化の進め方(どの業務から/どうすれば現実的か)､全体方針の整理について打合せ。
B28: インフィニティ様の支援実績では数時間かかるような大きな業務から着手するよりも数分程度の業務で日々多数の人が関わるものから実施した方が定着率が良いとのことで先ずExcel業務の効率化(収集/転記/集計/作成など定型業務)から着手しその状況を見ながら紙帳票の電子化､業務フロー整理､AIツール導入､業務フロー再構築へと進めていく形で検討することとなった。
B29: 今回のヒアリングでは業務内容が多岐に渡り社内で実務を確認するのも時間がかかるため3月はプレDXを中断していただくことし4/14再開を目標として3月中旬に進捗状況を共有することとした。
A31: 46077 | B31: ② Excel業務の効率化・自動化：集計・転記・資料作成などの定型業務について、自動化の進め方および優先順位の整理
B32: ∟初動はここから着手し、小さな範囲で小さな成果を出し、社内に「前向きな空気」を広げていく。
B33: ∟先ず、ヒアリング内容の中で、初動計画で着手したら良さそうな候補を共有したいです。
B34: ∟その後、具体的にどんなツール/業務フローで実行していけそうか、草案を共有したいです。 ▶具体的な日程を相談したいです。
B35: ① 紙帳票の電子化の進め方：製造記録や各種帳票の電子化にあたり、最適な手法・ツール・導入方法について相談
B36: ∟ペーパーレス化/DX推進の本旨に基づいて、②の進捗を圧迫しない範囲で並行して検討を進める。
B37: ∟作成内容/業務フローを鑑みて、ヒアリング内容の中から社内で相談しやすそうな候補を共有したいです。
B38: ∟その後、具体的にどんなツール/業務フローで実行していけそうか、草案を共有したいです。
B39: ③ 業務フローの整理およびDX推進の進め方：現状業務の可視化、DX推進の優先順位、段階的な導入ロードマップの策定
B40: ④ AIツールの業務活用に関する導入方針：AIを活用可能な業務領域の整理および、社内での安全な活用環境の構築方法
B41: AIを活用可能な業務領域の整理および、社内での安全な活用環境の構築方法
B42: ∟②①を実施していく中で社内の実情や温度感も踏まえて考察を深めていき、中盤以降に具体化する。
B43: Ⓐ MS365
... B46: ∟②①Ⓐを踏まえ、インフィニティ様おすすめツールの活用方法、それ以外でも検討したいツールなど、率直な意見を共有したいです。▶具体的な日程を相談したいです。
A48: 2026/03/10(火) | B48: 社内ミーティング
B49: 社内AI環境構築▶中村さんより概要を共有。初期段階では 中村さんにて検証しながら構築となるため東京営業所内 ローカル端末で稼働する予定。ネットワークセキュリティは インフィニティ様に相談しながら整備する。
B50: 計画概案▶前回までの社内ヒアリングとインフィニティ様プレDXの内容に基づいて 意見をすり合わせ。実務に関係する整備に入るため 各々の担当業務に近しい領域で分担していく予定。
B51: ∟中土主任：ツールを使う整備、議事録AI化、社内アンケート
B52: ∟鳥山主任：データ構造が明確なExcelファイルの作業効率化
B53: ∟中島さん：AI活用による業務マニュアル制作・属人化解消
B54: ∟中村さん：AI活用業務モデル制作、ツールを使う整備の支援 ▶共有フォルダ ▶3/11構造可視化ツール作成,利便性向上対策考察 ▶3/12検索ツール開発中～3/19営業課試験運用 ▶3/18検索ツール概要書提出-3/19決裁 ▶3/23構造可視化&データコピーツール完成
B55: ∟髙野：全ヒアリング項目の仕分け、領域別・時期別 計画案作成
A57: 2026/03/24(火) | B57: 社内ミーティング
A62: 46126
A63: 46136
A64: 46154
A65: 46168
A66: 46182
A67: 46197

Sheet 全体
A1: 開始 | B1: 完了(目標) | C1: 1区分 | D1: 2区分 | E1: 3区分 | F1: 46204 | G1: データベース： キーワード 課題/提案 意識/姿勢 候補者 埋める
A2: 46106 | B2: 46142 | C2: 1.サーバ環境 | D2: ▶サーバリプレイス後の動作改善確認
A3: 46106 | B3: 46142 | C3: 1.サーバ環境 | D3: ▶サーバリプレイス後の動作改善確認 | E3: ログイン・接続：時間帯、切断、フリーズ、速さ
A4: 46106 | B4: 46142 | C4: 1.サーバ環境 | D4: ▶サーバリプレイス後の動作改善確認 | E4: アプリ動作：Outlook（メール検索、迷惑メール） | G4: リアルタイム共有 | I4: 46126
A5: 46106 | B5: 46142 | C5: 1.サーバ環境 | D5: ▶サーバリプレイス後の動作改善確認 | E5: アプリ動作：Excel、PDF、Word、ブラウザ | G5: ワークフロー | I5: 46136
A6: 46106 | B6: 46142 | C6: 1.サーバ環境 | D6: ▶サーバリプレイス後の動作改善確認 | E6: その他1：デスクトップアイコン位置・既定プリンタの固定 | G6: 案件タスク管理 | I6: 46154
A7: 46106 | B7: 46142 | C7: 1.サーバ環境 | D7: ▶サーバリプレイス後の動作改善確認 | E7: その他2：テプラ | G7: 履歴管理 | I7: 46168
A8: 46106 | B8: 46173 | C8: 1.サーバ環境 | D8: ▶サーバリプレイス後の動作改善確認 | E8: Wi-Fi接続：製造エリア、自動⇄手動 | G8: 自動通知 | I8: 46182
A9: 46106 | B9: 46173 | C9: 1.サーバ環境 | D9: ▶サーバリプレイス後の動作改善確認 | E9: TPiCS・PI-navi：現品票発行、タブレット、ハンディターミナル | G9: 拠点外作業 | I9: 46197
A10: 46106 | B10: 46356 | C10: 2.クラウド環境 | D10: ▶MS365
A11: 46106 | B11: 46142 | C11: 2.クラウド環境 | D11: ▶MS365 | E11: 奉行クラウド主担当･TPiCS主担当・営業担当 アカウント導入
A12: 46204 | B12: 46295 | C12: 2.クラウド環境 | D12: ▶MS365 | E12: 部署別・業務別アカウント 導入
A13: 46266 | B13: 46356 | C13: 2.クラウド環境 | D13: ▶クラウドバックアップ整備
A14: 46266 | B14: 46326 | C14: 2.クラウド環境 | D14: ▶クラウドバックアップ整備 | E14: 部署別OneDrive
A15: 46266 | B15: 46326 | C15: 2.クラウド環境 | D15: ▶クラウドバックアップ整備 | E15: 専用サービス導入 有無判断➡一次整備完了
A16: 46106 | B16: 46203 | C16: 3.業務データ | D16: ▶共有フォルダ整備
A17: 46113 | B17: 46142 | C17: 3.業務データ | D17: ▶共有フォルダ整備 | E17: 共有フォルダ：可視化ツール➡削除範囲特定
A18: 46127 | B18: 46173 | C18: 3.業務データ | D18: ▶共有フォルダ整備 | E18: 共有フォルダ：コピー移行ツール➡バックアップ・削除
A19: 46113 | B19: 46203 | C19: 3.業務データ | D19: ▶共有フォルダ整備 | E19: 共有フォルダ：検索ツール➡使用頻度順位付け
A20: 46204 | B20: 46254 | C20: 3.業務データ | D20: ▶共有フォルダ整備 | E20: 共有フォルダ：データリンク集➡Excelハイパーリンク
A21: 46204 | B21: 46265 | C21: 3.業務データ | D21: ▶共有フォルダ整備 | E21: 共有フォルダ：定期メンテナンス方法確定
A22: 46106 | B22: 46326 | C22: 3.業務データ | D22: ▶事務作業自動化(AI化)
A23: 46106 | B23: 46173 | C23: 3.業務データ | D23: ▶事務作業自動化(AI化) | E23: 議事録
A24: 46106 | B24: 46173 | C24: 3.業務データ | D24: ▶事務作業自動化(AI化) | E24: Excel-製造関連
A25: 46174 | B25: 46234 | C25: 3.業務データ | D25: ▶事務作業自動化(AI化) | E25: 日報 改善
A26: 46174 | B26: 46356 | C26: 3.業務データ | D26: ▶データ形式標準化
A27: 46174 | B27: 46356 | C27: 3.業務データ | D27: ▶データ形式標準化 | E27: (▶事務作業自動化(AI化)、▶共有フォルダ整備 進捗に応じて検討開始）
A28: 46143 | B28: 46356 | C28: 3.業務データ | D28: ▶PDM・PLM環境整備
A29: 46143 | B29: 46356 | C29: 3.業務データ | D29: ▶PDM・PLM環境整備 | E29: サービス調査～開発・品管ヒアリング～具体化～
A30: 46174 | B30: 46326 | C30: 3.業務データ | D30: ▶ペーパーレス化・データ化
A31: 46174 | B31: 46326 | C31: 3.業務データ | D31: ▶ペーパーレス化・データ化 | E31: (▶事務作業自動化(AI化)、▶共有フォルダ整備 進捗に応じて検討開始）
A32: 46143 | B32: 46326 | C32: 4.ナレッジ共有 | D32: ▶ナレッジ共有（平準化）
A33: 46113 | B33: 46326 | C33: 4.ナレッジ | D33: ▶ナレッジ共有（平準化） | E33: マニュアル作成（属人化回避）
A34: 46235 | B34: 46326 | C34: 4.ナレッジ | D34: ▶ナレッジ共有（平準化） | E34: 日報 活用
A35: 46143 | B35: 46203 | C35: 5.リテラシー向上 | D35: ▶セキュリティ対策・IT基礎知識勉強会
A36: =B36-7*3 -> 46133 | B36: 46154 | C36: 5.リテラシー向上 | D36: ▶セキュリティ対策・IT基礎知識勉強会 | E36: セキュリティ対策・IT基礎知識勉強会①【？？？】
A37: =B37-7*3 -> 46147 | B37: 46168 | C37: 5.リテラシー向上 | D37: ▶セキュリティ対策・IT基礎知識勉強会 | E37: セキュリティ対策・IT基礎知識勉強会②【？？？】
A38: =B38-7*3 -> 46161 | B38: 46182 | C38: 5.リテラシー向上 | D38: ▶セキュリティ対策・IT基礎知識勉強会 | E38: セキュリティ対策・IT基礎知識勉強会③【？？？】
A39: 46054 | B39: 46387 | C39: - | D39: -

Sheet 予定P
J1: 全選択→更新→「-」「(空白)」非表示 | K1: 全選択→更新→「(空白)」非表示
A2: 年 (開始) | B2: 月 (開始) | C2: 個数 / 3区分 | D2: 個数 / 2区分 | E2: 個数 / 1区分 | G2: 年 (開始) | H2: 月 (開始) | I2: 1区分 | J2: 2区分 | K2: 3区分 | L2: 年 (完了(目標)) | M2: 月 (完了(目標))
A3: <2026/2/1 | B3: <2026/2/1 | G3: 2026年 | H3: 3月 | I3: 1.サーバ環境 | J3: ▶サーバリプレイス後の動作改善確認 | K3: ログイン・接続：時間帯、切断、フリーズ、速さ | L3: 2026年 | M3: 4月
A4: 2026年 | B4: 2月 | D4: 1 | E4: 1 | K4: アプリ動作：Outlook（メール検索、迷惑メール） | L4: 2026年 | M4: 4月
B5: 3月 | C5: 10 | D5: 14 | E5: 14 | K5: アプリ動作：Excel、PDF、Word、ブラウザ | L5: 2026年 | M5: 4月
B6: 4月 | C6: 5 | D6: 5 | E6: 5 | K6: その他1：デスクトップアイコン位置・既定プリンタの固定 | L6: 2026年 | M6: 4月
B7: 5月 | C7: 3 | D7: 6 | E7: 6 | K7: その他2：テプラ | L7: 2026年 | M7: 4月
B8: 6月 | C8: 3 | D8: 5 | E8: 5 | K8: Wi-Fi接続：製造エリア、自動⇄手動 | L8: 2026年 | M8: 5月
B9: 7月 | C9: 3 | D9: 3 | E9: 3 | K9: TPiCS・PI-navi：現品票発行、タブレット、ハンディターミナル | L9: 2026年 | M9: 5月
B10: 8月 | C10: 1 | D10: 1 | E10: 1 | I10: 2.クラウド環境 | J10: ▶MS365 | K10: 奉行クラウド主担当･TPiCS主担当・営業担当 アカウント導入 | L10: 2026年 | M10: 4月
B11: 9月 | C11: 2 | D11: 3 | E11: 3 | I11: 3.業務データ | J11: ▶事務作業自動化(AI化) | K11: Excel-製造関連 | L11: 2026年 | M11: 5月
A12: 総計 | C12: 27 | D12: 38 | E12: 38 | K12: 議事録 | L12: 2026年 | M12: 5月
H13: 4月 | I13: 3.業務データ | J13: ▶共有フォルダ整備 | K13: 共有フォルダ：可視化ツール➡削除範囲特定 | L13: 2026年 | M13: 4月
K14: 共有フォルダ：コピー移行ツール➡バックアップ・削除 | L14: 2026年 | M14: 5月
K15: 共有フォルダ：検索ツール➡使用頻度順位付け | L15: 2026年 | M15: 6月
I16: 4.ナレッジ | J16: ▶ナレッジ共有（平準化） | K16: マニュアル作成（属人化回避） | L16: 2026年 | M16: 10月
I17: 5.リテラシー向上 | J17: ▶セキュリティ対策・IT基礎知識勉強会 | K17: セキュリティ対策・IT基礎知識勉強会①【？？？】 | L17: 2026年 | M17: 5月
H18: 5月 | I18: 3.業務データ | J18: ▶PDM・PLM環境整備 | K18: サービス調査～開発・品管ヒアリング～具体化～ | L18: 2026年 | M18: 11月
I19: 5.リテラシー向上 | J19: ▶セキュリティ対策・IT基礎知識勉強会 | K19: セキュリティ対策・IT基礎知識勉強会②【？？？】 | L19: 2026年 | M19: 5月
K20: セキュリティ対策・IT基礎知識勉強会③【？？？】 | L20: 2026年 | M20: 6月
H21: 6月 | I21: 3.業務データ | J21: ▶事務作業自動化(AI化) | K21: 日報 改善 | L21: 2026年 | M21: 7月
A22: 年 (完了(目標)) | B22: 月 (完了(目標)) | C22: 個数 / 3区分 | D22: 個数 / 2区分 | E22: 個数 / 1区分 | J22: ▶データ形式標準化 | K22: (▶事務作業自動化(AI化)、▶共有フォルダ整備 進捗に応じて検討開始） | L22: 2026年 | M22: 11月
A23: <2026/4/30 | B23: <2026/4/30 | J23: ▶ペーパーレス化・データ化 | K23: (▶事務作業自動化(AI化)、▶共有フォルダ整備 進捗に応じて検討開始） | L23: 2026年 | M23: 10月
A24: 2026年 | B24: 4月 | C24: 7 | D24: 8 | E24: 8 | H24: 7月 | I24: 2.クラウド環境 | J24: ▶MS365 | K24: 部署別・業務別アカウント 導入 | L24: 2026年 | M24: 9月
B25: 5月 | C25: 7 | D25: 7 | E25: 7 | I25: 3.業務データ | J25: ▶共有フォルダ整備 | K25: 共有フォルダ：データリンク集➡Excelハイパーリンク | L25: 2026年 | M25: 8月
B26: 6月 | C26: 2 | D26: 4 | E26: 4 | K26: 共有フォルダ：定期メンテナンス方法確定 | L26: 2026年 | M26: 8月
B27: 7月 | C27: 1 | D27: 1 | E27: 1 | H27: 8月 | I27: 4.ナレッジ | J27: ▶ナレッジ共有（平準化） | K27: 日報 活用 | L27: 2026年 | M27: 10月
B28: 8月 | C28: 2 | D28: 2 | E28: 2 | H28: 9月 | I28: 2.クラウド環境 | J28: ▶クラウドバックアップ整備 | K28: 専用サービス導入 有無判断➡一次整備完了 | L28: 2026年 | M28: 10月
B29: 9月 | C29: 1 | D29: 1 | E29: 1 | K29: 部署別OneDrive | L29: 2026年 | M29: 10月
B30: 10月 | C30: 5 | D30: 8 | E30: 8
B31: 11月 | C31: 2 | D31: 6 | E31: 6
B32: 12月 | D32: 1 | E32: 1
A33: 総計 | C33: 27 | D33: 38 | E33: 38

Sheet 動作P-
A1: 接続/動作 | B1: アプリ/操作 | C1: 体制/管理 | D1: 勤務拠点 | E1: 部 | F1: 課 | G1: 係 | H1: 年 (回答時期) | I1: 月 (回答時期) | J1: キーワード | K1: No | L1: 原文 | M1: 氏名 | N1: ヒアリング項目 | O1: 対象 | R1: 1 | S1: 以下に、サーバ動作に関する意見を**勤務拠点ごとに整理（要約）**しました。（重複・類似意見は統合しています） | AA1: 2025年9月から、OS・CPUのサポートが終了するパソコンを入れ替え、本社のサーバ本体の設置環境や床下配線の整備、11月10日にシンクライアントサーバをリプレイスしました。
A2: 1 | B2: 1 | C2: 1 | D2: コスメラボラトリー | E2: 技術製造部 | F2: 製造課 | G2: バルク・顆粒 | H2: 2025年 | I2: 3月 | J2: 現品票発行 | K2: 28 | L2: ・ネットの環境か分からないが、現品票の発行（印刷）に時間がかかる。 | M2: 小田晶彦 | N2: (空白) | R2: 2 | S2: ■ 全拠点共通の構造課題（重要） | AA2: 約4ヵ月経過し、リプレイスの前に発生していた不具合・不便な事象に変化があったか否か、お聞かせください。
A3: 1 | B3: 1 | C3: (空白) | D3: 本社 | E3: 技術製造部 | F3: 生産管理課 | G3: 生産管理 | H3: 2025年 | I3: 3月 | J3: ハイパーリンク | K3: 17 | L3: ・エクセルのハイパーリンクはバグりやすいです | M3: 馬場阿弥子 | N3: (空白) | R3: 3 | S3: 各拠点を横断すると、問題は大きく5つに整理できます：
A4: 1 | B4: 1 | C4: (空白) | D4: 本社 | E4: 技術製造部 | F4: 生産管理課 | G4: 生産管理 | H4: 2025年 | I4: 3月 | J4: (空白) | K4: 12 | L4: ・ローカルのブラウザやSkypeの起動が遅い(1～3分くらい掛かる) | M4: 中島和哉 | N4: (空白) | R4: 4 | S4: ① サーバ負荷集中 | AA4: 氏名（フルネーム） | AF4: ↓(ローカル側からコピペしてください。※Windowsスタートメニュー→設定→システム→バージョン情報)
A5: 1 | B5: 1 | C5: (空白) | D5: 本社 | E5: 技術製造部 | F5: 生産管理課 | G5: 生産管理 | H5: 2025年 | I5: 3月 | J5: (空白) | K5: 20 | L5: ・Rグループが重いのとSkypeも終わるタイミングで、チャットやweb会議、スケジュール管理を、 Microsoft系かGoogle系にまとめられたら、各自予定の登録や確認がしやすいかなと思います。 | M5: 馬場阿弥子 | N5: (空白) | R5: 5 | S5: 9時・18時に遅延集中 | AA5: 所属部署 | AB5: 取締役・執行役員 | AF5: ◆デバイスの仕様
A6: 1 | B6: 1 | C6: (空白) | D6: 本社 | E6: 技術製造部 | F6: 生産管理課 | G6: 生産管理事務 | H6: 2025年 | I6: 3月 | J6: PDF | K6: 5 | L6: ・PDFの文字化け(最近落ち着いた気がしますが…) | M6: 東香里 | N6: (空白) | R6: 6 | S6: → リソース不足 or 負荷分散設計不足 | AB6: 研究開発部 研究開発課 | AF6: デバイス名
A7: 1 | B7: 1 | C7: (空白) | D7: 本社 | E7: 技術製造部 | F7: 生産管理課 | G7: 生産管理事務 | H7: 2025年 | I7: 3月 | J7: PDF | K7: 6 | L7: ・概ねPDFが重い気がします | M7: 東香里 | N7: (空白) | R7: 7 | S7: ② シンクライアント依存 | AB7: 品質保証部 品質管理課 | AF7: プロセッサ
A8: 1 | B8: 1 | C8: (空白) | D8: 本社 | E8: 技術製造部 | F8: 生産管理課 | G8: 生産管理事務 | H8: 2025年 | I8: 3月 | J8: ハイパーリンク | K8: 2 | L8: ・定期的にハイパーリンクがリンクしなくなる。 | M8: 徳永彩花 | N8: (空白) | R8: 8 | S8: 全拠点で遅延・切断・フリーズ | AB8: 技術製造部 製造課 液体 | AF8: 実装 RAM
A9: 1 | B9: 1 | C9: (空白) | D9: 本社 | E9: 技術製造部 | F9: 生産管理課 | G9: 生産管理事務 | H9: 2025年 | I9: 3月 | J9: ハイパーリンク | K9: 4 | L9: ・たまにハイパーリンクが死亡する(どういった場合かは不明。突然発生する) | M9: 東香里 | N9: (空白) | R9: 9 | S9: → 基盤構造のボトルネック | AB9: 技術製造部 製造課 粉体 | AF9: デバイス ID
A10: 1 | B10: 1 | C10: (空白) | D10: 本社 | E10: 技術製造部 | F10: 生産管理課 | G10: 生産管理事務 | H10: 2025年 | I10: 3月 | J10: (空白) | K10: 1 | L10: ・サーバーのフリーズが多い、ローカルのSkype立ち上がりなど少し遅い印象 | M10: 徳永彩花 | N10: (空白) | R10: 10 | S10: ③ ネットワーク品質 | AB10: 技術製造部 製造課 バルク・顆粒 | AF10: プロダクト ID
A11: 1 | B11: 1 | C11: (空白) | D11: コスメラボラトリー | E11: 研究開発部 | F11: 研究開発課 | G11: - | H11: 2025年 | I11: 3月 | J11: Excel | K11: 62 | L11: ・一定の手順で必ずエクセルとワードが落ちることがある。 | M11: 近藤雅人 | N11: (空白) | R11: 11 | S11: 回線遅延・切断 | AB11: 技術製造部 製造課 充填包装 | AF11: システムの種類
A12: 1 | B12: 1 | C12: (空白) | D12: コスメラボラトリー | E12: 研究開発部 | F12: 研究開発課 | G12: - | H12: 2025年 | I12: 3月 | J12: Excel | K12: 90 | L12: ・Excelの動きが遅い、フリーズして消えることがある | M12: 橋口千聖 | N12: (空白) | R12: 12 | S12: → 拠点間帯域 or WAN問題 | AB12: 技術製造部 生産管理課 生産管理 | AF12: ペンとタッチ
A13: 1 | B13: 1 | C13: (空白) | D13: コスメラボラトリー | E13: 研究開発部 | F13: 研究開発課 | G13: - | H13: 2025年 | I13: 3月 | J13: Excel・PDF | K13: 73 | L13: ・エクセル、PDF使用時は遅くなりやすい。 | M13: 直木美佐子 | N13: (空白) | R13: 13 | S13: ④ 端末性能差 | AB13: 技術製造部 生産管理課 生産管理事務 | AF13: ◆OSの仕様
A14: 1 | B14: 1 | C14: (空白) | D14: コスメラボラトリー | E14: 研究開発部 | F14: 研究開発課 | G14: - | H14: 2025年 | I14: 3月 | J14: Excel・Word | K14: 60 | L14: ・エクセル・ワードにて、タイピングした内容が反映されるまでのタイムラグがかなりある時がある。 | M14: 近藤雅人 | N14: (空白) | R14: 14 | S14: 古いPC・タブレット | AB14: 技術製造部 生産管理課 物流 | AF14: エディション
A15: 1 | B15: 1 | C15: (空白) | D15: コスメラボラトリー | E15: 研究開発部 | F15: 研究開発課 | G15: - | H15: 2025年 | I15: 3月 | J15: Excel・Word | K15: 68 | L15: ・Word、EXcel使用時に急に落ちる。 | M15: 山下基宏 | N15: (空白) | R15: 15 | S15: → クライアント側処理不足 | AB15: 技術製造部 製造課 パート事務 | AF15: バージョン
A16: 1 | B16: 1 | C16: (空白) | D16: コスメラボラトリー | E16: 研究開発部 | F16: 研究開発課 | G16: - | H16: 2025年 | I16: 3月 | J16: Outlook | K16: 59 | L16: ・朝立ち上げ時、アウトルックの起動に5分程かかる | M16: 近藤雅人 | N16: (空白) | R16: 16 | S16: ⑤ アプリ・データ肥大化 | AB16: 管理部 管理課 | AF16: インストール日
A17: 1 | B17: 1 | C17: (空白) | D17: コスメラボラトリー | E17: 研究開発部 | F17: 研究開発課 | G17: - | H17: 2025年 | I17: 3月 | J17: Outlook | K17: 67 | L17: ・Outlook使用時に急に落ちる。 | M17: 山下基宏 | N17: (空白) | R17: 17 | S17: Excel／PDF／Outlook遅延 | AB17: EC事業部 EC事業課 | AF17: OS ビルド
A18: 1 | B18: 1 | C18: (空白) | D18: コスメラボラトリー | E18: 研究開発部 | F18: 研究開発課 | G18: - | H18: 2025年 | I18: 3月 | J18: Outlook | K18: 89 | L18: ・Outlookの動きが遅い、フリーズする | M18: 橋口千聖 | N18: (空白) | R18: 18 | S18: → データ量増加＋最適化不足 | AB18: 企画営業部 営業課 | AF18: シリアル番号
A19: 1 | B19: 1 | C19: (空白) | D19: コスメラボラトリー | E19: 研究開発部 | F19: 研究開発課 | G19: - | H19: 2025年 | I19: 3月 | J19: PDF | K19: 82 | L19: ・最近PDFの立ち上がりが遅い | M19: 矢野恵 | N19: (空白) | R19: 19 | AB19: 企画営業部 企画課 | AF19: エクスペリエンス
A20: 1 | B20: 1 | C20: (空白) | D20: コスメラボラトリー | E20: 研究開発部 | F20: 研究開発課 | G20: - | H20: 2025年 | I20: 3月 | J20: ブラウザ | K20: 91 | L20: ・インターネット検索に時間がかかる、サーバー外でも時間がかかる | M20: 橋口千聖 | N20: (空白) | R20: 20 | S20: ■ まとめ（経営視点） | AA20: 常勤拠点 | AB20: 本社
A21: 1 | B21: 1 | C21: (空白) | D21: コスメラボラトリー | E21: 研究開発部 | F21: 研究開発課 | G21: - | H21: 2025年 | I21: 3月 | J21: メール検索 | K21: 83 | L21: ・outlookのメールの検索が遅い | M21: 矢野恵 | N21: (空白) | R21: 21 | S21: 最重度：コスメラボラトリー（研究開発） | AB21: ラボラトリー | AF21: ◆無線接続先
A22: 1 | B22: 1 | C22: (空白) | D22: コスメラボラトリー | E22: 品質保証部 | F22: 品質管理課 | G22: - | H22: 2025年 | I22: 3月 | J22: Explorer | K22: 86 | L22: ・サーバーに関係あるか分かりませんが、開いている全てのエクスプローラーが勝手に閉じる | M22: 西村穂乃果 | N22: (空白) | R22: 22 | S22: 次点：本社・コスメファクトリー | AB22: ファクトリー | AF22: Wi-Fi接続 SSID (メイン)
A23: 1 | B23: 1 | C23: (空白) | D23: コスメラボラトリー | E23: 技術製造部 | F23: 製造課 | G23: バルク・顆粒 | H23: 2025年 | I23: 3月 | J23: TPiCS・PI-navi | K23: 29 | L23: ・朝の９時以外でもメールやTPiCS・PI-naviが遅い時がある。時間は見てないです。あきらめて製造に戻る時もあります。 | M23: 小田晶彦 | N23: (空白) | R23: 23 | S23: 構造問題：インフラ設計全体（サーバ＋回線＋シンクラ） | AB23: 第一倉庫 | AF23: Wi-Fi接続 SSID (サブ1)
A24: 1 | B24: 1 | C24: (空白) | D24: コスメラボラトリー | E24: EC事業部 | F24: EC事業課 | G24: - | H24: 2025年 | I24: 3月 | J24: Excel | K24: 57 | L24: エクセルの操作が固まりやすい | M24: 大前道仁 | N24: (空白) | R24: 24 | S24: 👉 単なる「PCが遅い」ではなく | AB24: 東京営業所 | AF24: Wi-Fi接続 SSID (サブ2)
A25: 1 | B25: 1 | C25: (空白) | D25: コスメラボラトリー | E25: EC事業部 | F25: EC事業課 | G25: - | H25: 2025年 | I25: 3月 | J25: ブラウザ | K25: 50 | L25: ブラウザ処理の負荷に耐えれていない | M25: 中土陽介 | N25: (空白) | R25: 25 | S25: “インフラ設計の限界に到達している状態” | AA25: 仮想サーバ | AB25: A | AF25: Wi-Fi接続 SSID (サブ3)
A26: 1 | B26: 1 | C26: (空白) | D26: コスメラボラトリー | E26: EC事業部 | F26: EC事業課 | G26: - | H26: 2025年 | I26: 3月 | J26: ブラウザ | K26: 56 | L26: 受注が多い日に受注管理システム（ブラウザ）からデータをDLすると重たい | M26: 大前道仁 | N26: (空白) | R26: 26 | AB26: B | AF26: Wi-Fi接続 SSID (サブ4)
A27: 1 | B27: 1 | C27: (空白) | D27: コスメラボラトリー | E27: EC事業部 | F27: EC事業課 | G27: - | H27: 2025年 | I27: 3月 | J27: ブラウザ | K27: 58 | L27: ブラウザ上の業務が多い中、固まることで遅延してしまう。 | M27: 酒井絢音 | N27: (空白) | R27: 27 | S27: ■ 勤務拠点別まとめ（サーバ動作） | AB27: C | AF27: Wi-Fi接続 SSID (サブ5)
A28: 1 | B28: (空白) | C28: 1 | D28: 本社 | E28: 技術製造部 | F28: 製造課 | G28: 粉体 | H28: 2025年 | I28: 7月 | J28: 迷惑メール | K28: 376 | L28: 迷惑メールが増えている。今でもフリーズすることがある。 | M28: 内藤恭介 | N28: ⑥その他(自由意見) | R28: 28 | S28: ① 本社
A29: 1 | B29: (空白) | C29: 1 | D29: 第一倉庫 | E29: 技術製造部 | F29: 生産管理課 | G29: 物流 | H29: 2025年 | I29: 3月 | J29: ハンディターミナル | K29: 15 | L29: ・ハンディの動作反応が年々遅くなっている→データ蓄積されているため？ | M29: 池田悦彰 | N29: (空白) | R29: 29 | S29: ● 主な課題 | AA29: シンクライアントサーバについて
A30: 1 | B30: (空白) | C30: (空白) | D30: 本社 | E30: 管理部 | F30: 管理課 | G30: - | H30: 2025年 | I30: 3月 | J30: デスクトップアイコン | K30: 39 | L30: ・会計処理をする際、管理部用のノートＰＣでサーバー接続しCSVデータを取り込んでいますが、デスクトップPCに戻りログインするとデスクトップ上のアイコンの配列がバラバラになり少しストレスです | M30: 図書杏子 | N30: (空白) | R30: 30 | S30: サーバーフリーズ・不安定 | AA30: ログインの時刻+接続時間について | AD30: 1 不具合・不便を全く感じない
A31: 1 | B31: (空白) | C31: (空白) | D31: 本社 | E31: 管理部 | F31: 管理課 | G31: - | H31: 2025年 | I31: 3月 | J31: ブラウザ | K31: 47 | L31: ･アマゾンサイトなどへ接続している時、サイト内の動きがとても遅いです。 | M31: 丸中都 | N31: (空白) | R31: 31 | S31: フリーズが多い／突然切断／再ログイン頻発 | AA31: 9時・18時 | AD31: 2 殆ど感じない
A32: 1 | B32: (空白) | C32: (空白) | D32: 本社 | E32: 管理部 | F32: 管理課 | G32: - | H32: 2025年 | I32: 3月 | J32: プリンタ既定 | K32: 38 | L32: ・一定期間作業していない時（昼休みなど）ログイン画面が表示され入るとプリンター指定が解除されて毎回ＰＤＦ指定になる | M32: 図書杏子 | N32: (空白) | R32: 32 | S32: 起動・接続遅延 | AA32: 昼休み | AD32: 3 たまに感じる
A33: 1 | B33: (空白) | C33: (空白) | D33: 本社 | E33: 管理部 | F33: 管理課 | G33: - | H33: 2025年 | I33: 3月 | J33: 共有フォルダ | K33: 41 | L33: ・毎日最初の一回共有フォルダにはじかれる | M33: 越智絵美子 | N33: (空白) | R33: 33 | S33: PC起動・シンクラ接続に時間（約3〜6分） | AA33: それ以外の時間帯 | AD33: 4 週に1～2回はある／2～3分以上かかる
A34: 1 | B34: (空白) | C34: (空白) | D34: 本社 | E34: 管理部 | F34: 管理課 | G34: - | H34: 2025年 | I34: 3月 | J34: (空白) | K34: 45 | L34: ・昔よりは改善されてますがPCが固まったり遅かったりする | M34: 越智絵美子 | N34: (空白) | R34: 34 | S34: 共有フォルダ接続不良 | AA34: 常勤拠点での接続の状態について | AD34: 5 リプレイス前と変わっていない／5分以上かかる
A35: 1 | B35: (空白) | C35: (空白) | D35: 本社 | E35: 管理部 | F35: 管理課 | G35: - | H35: 2025年 | I35: 3月 | J35: (空白) | K35: 46 | L35: ・事務長がサーバーになかなか入れないときがある | M35: 越智絵美子 | N35: (空白) | R35: 35 | S35: 初回アクセスで弾かれる／ログインできない | AA35: ログインできない
A36: 1 | B36: (空白) | C36: (空白) | D36: 本社 | E36: 管理部 | F36: 管理課 | G36: - | H36: 2025年 | I36: 3月 | J36: (空白) | K36: 48 | L36: ･突然サーバーからはじき出される。ログインしなおすと作業途中の画面には戻れます。 | M36: 丸中都 | N36: (空白) | R36: 36 | S36: ブラウザ・アプリ遅延 | AA36: 突然切断される・再ログインする
A37: 1 | B37: (空白) | C37: (空白) | D37: 本社 | E37: 技術製造部 | F37: 生産管理課 | G37: 生産管理 | H37: 2025年 | I37: 3月 | J37: (空白) | K37: 10 | L37: ・ローカル、サーバー共にフリーズが多い | M37: 中島和哉 | N37: (空白) | R37: 37 | S37: Skype・ブラウザ起動遅い（1〜3分） | AA37: 画面が真っ暗になる
A38: 1 | B38: (空白) | C38: (空白) | D38: 本社 | E38: 技術製造部 | F38: 生産管理課 | G38: 生産管理 | H38: 2025年 | I38: 3月 | J38: (空白) | K38: 11 | L38: ・パソコンの起動が遅く、シンクラの接続にも時間が掛かる、電源入～デスクトップの画面表示まで約3分30秒、Aサーバー接続アイコン選択～シンクラ画面まで約2分30秒 | M38: 中島和哉 | N38: (空白) | R38: 38 | S38: リンク・ファイル不具合 | AA38: フリーズする
A39: 1 | B39: (空白) | C39: (空白) | D39: 本社 | E39: 技術製造部 | F39: 生産管理課 | G39: 生産管理 | H39: 2025年 | I39: 3月 | J39: (空白) | K39: 19 | L39: ・サーバーのフリーズが多い | M39: 馬場阿弥子 | N39: (空白) | R39: 39 | S39: ハイパーリンク切れ／PDF重い・文字化け | AA39: 動作が重い
A40: 1 | B40: (空白) | C40: (空白) | D40: 本社 | E40: 技術製造部 | F40: 生産管理課 | G40: 生産管理 | H40: 2025年 | I40: 3月 | J40: (空白) | K40: 22 | L40: ・ローカルのブラウザやSkypeの起動が遅い(1～3分くらい掛かる) | M40: 島田智章 | N40: (空白) | R40: 40 | S40: ● 特徴 | AA40: 製造エリアでの接続の状態について（製造課メンバーのみ）
A41: 1 | B41: (空白) | C41: (空白) | D41: 本社 | E41: 技術製造部 | F41: 生産管理課 | G41: 生産管理 | H41: 2025年 | I41: 3月 | J41: (空白) | K41: 23 | L41: ・パソコンの起動が遅く、シンクラの接続にも時間が掛かる(中島くんと同等の所要時間) ※島田主任と中島くんのPCスペックは同等です | M41: 島田智章 | N41: (空白) | R41: 41 | S41: 業務全般に影響（管理・生産管理中心） | AA41: ログインできない
A42: 1 | B42: (空白) | C42: (空白) | D42: 本社 | E42: 技術製造部 | F42: 生産管理課 | G42: 生産管理事務 | H42: 2025年 | I42: 3月 | J42: (空白) | K42: 3 | L42: ・定期的にデスクトップのアイコン位置シャッフルされる | M42: 徳永彩花 | N42: (空白) | R42: 42 | S42: シンクライアント環境依存の問題が顕著 | AA42: 突然切断される・再ログインする
A43: 1 | B43: (空白) | C43: (空白) | D43: 本社 | E43: 技術製造部 | F43: 生産管理課 | G43: 生産管理事務 | H43: 2025年 | I43: 3月 | J43: (空白) | K43: 7 | L43: ・天気が悪いとPCの動きが鈍い | M43: 東香里 | N43: (空白) | R43: 43 | AA43: 画面が真っ暗になる
A44: 1 | B44: (空白) | C44: (空白) | D44: 本社 | E44: 技術製造部 | F44: 生産管理課 | G44: 生産管理事務 | H44: 2025年 | I44: 7月 | J44: (空白) | K44: 374 | L44: 定期的にパソコンのフリーズがあるので安定してほしい。工程が複雑にならず、ダブった作業は増えないでほしい。簡易になれば嬉しい。 | M44: 徳永彩花 | N44: ⑥その他(自由意見) | R44: 44 | S44: ② コスメラボラトリー（研究開発・品質・製造） | AA44: フリーズする
A45: 1 | B45: (空白) | C45: (空白) | D45: 本社 | E45: 技術製造部 | F45: 製造課 | G45: 粉体 | H45: 2025年 | I45: 3月 | J45: (空白) | K45: 31 | L45: 私的には以前に容量削減の対策をやってからフリーズすることがかなり改善したように思います。ただ大川リーダー、伊澤Ｌは今でも動作が重たくなる時はあるとのことです。 | M45: 内藤恭介 | N45: (空白) | R45: 45 | S45: ● 主な課題 | AA45: 動作が重い
A46: 1 | B46: (空白) | C46: (空白) | D46: コスメファクトリー | E46: 技術製造部 | F46: 生産管理課 | G46: 物流 | H46: 2025年 | I46: 3月 | J46: (空白) | K46: 25 | L46: ・シンクラサーバーの動作が全体的に重い。（シンクラが原因なのか、PC自体が古いからなのかは分からないです） | M46: 北村優樹 | N46: (空白) | R46: 46 | S46: 慢性的なサーバー遅延・フリーズ
A47: 1 | B47: (空白) | C47: (空白) | D47: コスメファクトリー | E47: 技術製造部 | F47: 生産管理課 | G47: 物流 | H47: 2025年 | I47: 3月 | J47: (空白) | K47: 26 | L47: ・フリーズが頻発する。社員のパソコン使用が集中する時間帯（主に9時頃、18時頃）は特に多く、長くフリーズする。 | M47: 北村優樹 | N47: (空白) | R47: 47 | S47: 「常に重い」「毎日発生」レベル | AA47: アプリ動作について
A48: 1 | B48: (空白) | C48: (空白) | D48: コスメファクトリー | E48: 技術製造部 | F48: 製造課 | G48: バルク・顆粒 | H48: 2025年 | I48: 7月 | J48: (空白) | K48: 361 | L48: 軽いフリーズをすることが結構あるので回線がもっといい環境になれば嬉しいです。 | M48: 外間裕貴人 | N48: ⑥その他(自由意見) | R48: 48 | S48: 時間帯依存（特に9時・18時） | AA48: Outlook
A49: 1 | B49: (空白) | C49: (空白) | D49: コスメファクトリー | E49: 技術製造部 | F49: 製造課 | G49: バルク・顆粒 | H49: 2025年 | I49: 7月 | J49: (空白) | K49: 364 | L49: 回線が遅い（フリーズが多い）気がするので少しでもスムーズになってほしいと思います。 | M49: 松下賢 | N49: ⑥その他(自由意見) | R49: 49 | S49: 高負荷時に必ず遅延・接続困難 | AA49: 起動が遅い
A50: 1 | B50: (空白) | C50: (空白) | D50: コスメファクトリー | E50: 技術製造部 | F50: 製造課 | G50: 充填包装 | H50: 2025年 | I50: 3月 | J50: タブレット | K50: 36 | L50: ネット環境が関係あるか分かりませんが以前からタブレットの動作は常に重いのでそちらも改善できればと思います。 | M50: 東口智一 | N50: (空白) | R50: 50 | S50: アプリ全般の不安定 | AA50: 強制終了する
A51: 1 | B51: (空白) | C51: (空白) | D51: コスメファクトリー | E51: 技術製造部 | F51: 製造課 | G51: 充填包装 | H51: 2025年 | I51: 3月 | J51: (空白) | K51: 35 | L51: サーバーの動作が遅く、切断されがち | M51: 東口智一 | N51: (空白) | R51: 51 | S51: Excel・Word・Outlookのフリーズ／強制終了 | AA51: フリーズする
A52: 1 | B52: (空白) | C52: (空白) | D52: コスメファクトリー | E52: 技術製造部 | F52: 製造課 | G52: 充填包装 | H52: 2025年 | I52: 7月 | J52: (空白) | K52: 354 | L52: パソコン本体が重たい。 | M52: 藤本洸平 | N52: ⑥その他(自由意見) | R52: 52 | S52: 入力遅延・誤入力リスク | AA52: 文字入力が遅れる
A53: 1 | B53: (空白) | C53: (空白) | D53: コスメラボラトリー | E53: 研究開発部 | F53: 研究開発課 | G53: - | H53: 2025年 | I53: 3月 | J53: (空白) | K53: 61 | L53: ・重すぎて、文字が明瞭ではない時がある。ボケてる。 | M53: 近藤雅人 | N53: (空白) | R53: 53 | S53: タイピング遅延・画面停止で業務ミス増加 | AA53: メール検索できない
A54: 1 | B54: (空白) | C54: (空白) | D54: コスメラボラトリー | E54: 研究開発部 | F54: 研究開発課 | G54: - | H54: 2025年 | I54: 3月 | J54: (空白) | K54: 64 | L54: ・慢性的に動作が遅くてフリーズします。書類（処方、提案書、報告書、成績書、指図書など）作成、メール対応、調査など、本社で作業していた時と比べ、完了するまでの時間が長くなっています。 | M54: 宗近倶枝 | N54: (空白) | R54: 54 | S54: 接続障害 | AA54: Excel
A55: 1 | B55: (空白) | C55: (空白) | D55: コスメラボラトリー | E55: 研究開発部 | F55: 研究開発課 | G55: - | H55: 2025年 | I55: 3月 | J55: (空白) | K55: 65 | L55: ・コスメは本社に比べ不具合の時間が多いです。 | M55: 宗近倶枝 | N55: (空白) | R55: 55 | S55: ログイン不可／強制切断／画面ブラックアウト | AA55: 起動が遅い
A56: 1 | B56: (空白) | C56: (空白) | D56: コスメラボラトリー | E56: 研究開発部 | F56: 研究開発課 | G56: - | H56: 2025年 | I56: 3月 | J56: (空白) | K56: 66 | L56: ・急に切れる。 | M56: 山下基宏 | N56: (空白) | R56: 56 | S56: ● 特徴 | AA56: 強制終了する
A57: 1 | B57: (空白) | C57: (空白) | D57: コスメラボラトリー | E57: 研究開発部 | F57: 研究開発課 | G57: - | H57: 2025年 | I57: 3月 | J57: (空白) | K57: 69 | L57: ・急に止まる。 | M57: 山下基宏 | N57: (空白) | R57: 57 | S57: 最も影響が深刻 | AA57: フリーズする
A58: 1 | B58: (空白) | C58: (空白) | D58: コスメラボラトリー | E58: 研究開発部 | F58: 研究開発課 | G58: - | H58: 2025年 | I58: 3月 | J58: (空白) | K58: 70 | L58: ・タイピングが遅れて反応。 | M58: 山下基宏 | N58: (空白) | R58: 58 | S58: 研究・文書作成業務に直接ダメージ（効率低下・品質リスク） | AA58: 文字入力が遅れる
A59: 1 | B59: (空白) | C59: (空白) | D59: コスメラボラトリー | E59: 研究開発部 | F59: 研究開発課 | G59: - | H59: 2025年 | I59: 3月 | J59: (空白) | K59: 71 | L59: ・ログインできない。 | M59: 山下基宏 | N59: (空白) | R59: 59 | S59: 「本社より不具合多い」との声あり | AA59: ハイパーリンクが切れる
A60: 1 | B60: (空白) | C60: (空白) | D60: コスメラボラトリー | E60: 研究開発部 | F60: 研究開発課 | G60: - | H60: 2025年 | I60: 3月 | J60: (空白) | K60: 72 | L60: ・サーバーが重い、遅い。毎日午前9時と午後6時前後は必ず発生。その他の時間帯も突発的に発生。 | M60: 直木美佐子 | N60: (空白) | R60: 60 | AA60: Word
A61: 1 | B61: (空白) | C61: (空白) | D61: コスメラボラトリー | E61: 研究開発部 | F61: 研究開発課 | G61: - | H61: 2025年 | I61: 3月 | J61: (空白) | K61: 74 | L61: ・サーバーが止まることで打ち損じや誤入力が発生しやすくなっている。電子管理が増える中で、この現象は致命的だと思う。 | M61: 直木美佐子 | N61: (空白) | R61: 61 | S61: ③ コスメファクトリー | AA61: 起動が遅い
A62: 1 | B62: (空白) | C62: (空白) | D62: コスメラボラトリー | E62: 研究開発部 | F62: 研究開発課 | G62: - | H62: 2025年 | I62: 3月 | J62: (空白) | K62: 75 | L62: ・パソコンが止まることで、進行中の作業が一旦止まる。再開時に誤入力していないか確認することからスタートするので、作業効率が低下。 | M62: 直木美佐子 | N62: (空白) | R62: 62 | S62: ● 主な課題 | AA62: 強制終了する
A63: 1 | B63: (空白) | C63: (空白) | D63: コスメラボラトリー | E63: 研究開発部 | F63: 研究開発課 | G63: - | H63: 2025年 | I63: 3月 | J63: (空白) | K63: 77 | L63: ・サーバーの動作が重い。 | M63: 津田宝加 | N63: (空白) | R63: 63 | S63: シンクラ全体の動作遅延 | AA63: フリーズする
A64: 1 | B64: (空白) | C64: (空白) | D64: コスメラボラトリー | E64: 研究開発部 | F64: 研究開発課 | G64: - | H64: 2025年 | I64: 3月 | J64: (空白) | K64: 78 | L64: ・Ｂサーバーから突然はじき出される。ログインしなおすと作業途中の画面には戻れる。 | M64: 津田宝加 | N64: (空白) | R64: 64 | S64: 常に重い／原因不明（サーバ or PC） | AA64: 文字入力が遅れる
A65: 1 | B65: (空白) | C65: (空白) | D65: コスメラボラトリー | E65: 研究開発部 | F65: 研究開発課 | G65: - | H65: 2025年 | I65: 3月 | J65: (空白) | K65: 79 | L65: ・シンクライアントサーバーの動きが悪く、何度もフリーズする日がある | M65: 矢野恵 | N65: (空白) | R65: 65 | S65: フリーズ頻発（特に集中時間） | AA65: PDF
A66: 1 | B66: (空白) | C66: (空白) | D66: コスメラボラトリー | E66: 研究開発部 | F66: 研究開発課 | G66: - | H66: 2025年 | I66: 3月 | J66: (空白) | K66: 80 | L66: ・動きが悪い日はその状態が一日中続くことが多く、仕事の作業効率が悪くなる（以前に比べると頻度は落ち着いているように感じます…） | M66: 矢野恵 | N66: (空白) | R66: 66 | S66: 9時・18時に顕著 | AA66: 起動が遅い
A67: 1 | B67: (空白) | C67: (空白) | D67: コスメラボラトリー | E67: 研究開発部 | F67: 研究開発課 | G67: - | H67: 2025年 | I67: 3月 | J67: (空白) | K67: 81 | L67: ・シンクライアントからはじき出されることが数日おきにある | M67: 矢野恵 | N67: (空白) | R67: 67 | S67: 回線・ネットワーク問題 | AA67: 強制終了する
A68: 1 | B68: (空白) | C68: (空白) | D68: コスメラボラトリー | E68: 研究開発部 | F68: 研究開発課 | G68: - | H68: 2025年 | I68: 3月 | J68: (空白) | K68: 87 | L68: ・サーバーへ入るのに時間がかかる | M68: 橋口千聖 | N68: (空白) | R68: 68 | S68: 通信遅延・切断が多い | AA68: フリーズする
A69: 1 | B69: (空白) | C69: (空白) | D69: コスメラボラトリー | E69: 研究開発部 | F69: 研究開発課 | G69: - | H69: 2025年 | I69: 3月 | J69: (空白) | K69: 88 | L69: ・サーバー内で作業中、画面が真っ暗になり強制終了せざるを得ない | M69: 橋口千聖 | N69: (空白) | R69: 69 | S69: 現場端末の性能不足 | AA69: 文字化けする
A70: 1 | B70: (空白) | C70: (空白) | D70: コスメラボラトリー | E70: 品質保証部 | F70: 品質管理課 | G70: - | H70: 2025年 | I70: 3月 | J70: (空白) | K70: 84 | L70: ・サーバーが重く、フリーズが多い | M70: 西村穂乃果 | N70: (空白) | R70: 70 | S70: PC・タブレットが重い | AA70: 編集操作が重い
A71: 1 | B71: (空白) | C71: (空白) | D71: コスメラボラトリー | E71: 品質保証部 | F71: 品質管理課 | G71: - | H71: 2025年 | I71: 3月 | J71: (空白) | K71: 85 | L71: ・ログイン情報が合っているのにサーバーに入れない。（4,5回ログインし直すと入れる） | M71: 西村穂乃果 | N71: (空白) | R71: 71 | S71: ● 特徴 | AA71: ブラウザ（Edge・Chrome・Firefox）
A72: 1 | B72: (空白) | C72: (空白) | D72: コスメラボラトリー | E72: 技術製造部 | F72: 製造課 | G72: バルク・顆粒 | H72: 2025年 | I72: 3月 | J72: (空白) | K72: 27 | L72: ・サーバーにつながりにくい（特に朝９時ぐらい） | M72: 小田晶彦 | N72: (空白) | R72: 72 | S72: ネットワーク＋端末性能の複合問題 | AA72: 起動が遅い
A73: 1 | B73: (空白) | C73: (空白) | D73: コスメラボラトリー | E73: 技術製造部 | F73: 製造課 | G73: バルク・顆粒 | H73: 2025年 | I73: 3月 | J73: (空白) | K73: 30 | L73: ・要望はパソコンはスムーズに使いたい。 製造してる合間に打ち込んだりメール見ることがあるので、ネットがつながらないとかあると、作業効率が悪いです。 | M73: 小田晶彦 | N73: (空白) | R73: 73 | S73: 製造現場でのリアルタイム性に影響 | AA73: 強制終了する
A74: 1 | B74: (空白) | C74: (空白) | D74: コスメラボラトリー | E74: 技術製造部 | F74: 製造課 | G74: 充填包装 | H74: 2025年 | I74: 3月 | J74: 時間帯 | K74: 33 | L74: サーバーの動作が遅く、すぐ切断される。開発、BeGardenの出勤時刻9時頃が最もサーバーにつながりにくい。 | M74: 小田勇雄 | N74: (空白) | R74: 74 | AA74: フリーズする
A75: 1 | B75: (空白) | C75: (空白) | D75: コスメラボラトリー | E75: 技術製造部 | F75: 製造課 | G75: 充填包装 | H75: 2025年 | I75: 7月 | J75: (空白) | K75: 352 | L75: 現場で使用しているパソコンのスペックが良くないので固まったり再接続の回数が多く作業に時間を要している。 | M75: 松山丈弘 | N75: ⑥その他(自由意見) | R75: 75 | S75: ④ 第一倉庫（物流） | AA75: 文字入力が遅れる
A76: 1 | B76: (空白) | C76: (空白) | D76: コスメラボラトリー | E76: EC事業部 | F76: EC事業課 | G76: - | H76: 2025年 | I76: 3月 | J76: 時間帯 | K76: 55 | L76: 昼頃・夕方に遅延がする | M76: 大前道仁 | N76: (空白) | R76: 76 | S76: ● 主な課題
A77: 1 | B77: (空白) | C77: (空白) | D77: 第一倉庫 | E77: 技術製造部 | F77: 生産管理課 | G77: 物流 | H77: 2025年 | I77: 3月 | J77: (空白) | K77: 14 | L77: ・Bサーバー基本的に重い | M77: 池田悦彰 | N77: (空白) | R77: 77 | S77: サーバー（B系）常時重い | AA77: 上記以外の不具合報告について
A78: 1 | B78: (空白) | C78: (空白) | D78: 東京営業所 | E78: 企画営業部 | F78: 営業課 | G78: - | H78: 2025年 | I78: 6月 | J78: (空白) | K78: 107 | L78: サーバーや回線等による作業待ち時間を減らしたい | M78: 橋本悠司 | N78: MS365(基礎) | R78: 78 | S78: ハンディ端末の動作遅延（年々悪化） | AA78: 迷惑メールが多い
A79: 1 | B79: (空白) | C79: (空白) | D79: 東京営業所 | E79: 企画営業部 | F79: 営業課 | G79: - | H79: 2025年 | I79: 6月 | J79: マニュアル・ナレッジ | K79: 119 | L79: サーバーやアプリに繋がらないなどの時の簡易トラブル対処マニュアル作成 | M79: 橋本悠司 | N79: セキュリティ | R79: 79 | S79: ● 特徴 | AA79: 既定プリンタがリセットされる
A80: (空白) | B80: 1 | C80: 1 | D80: 本社 | E80: 技術製造部 | F80: 生産管理課 | G80: 生産管理 | H80: 2025年 | I80: 6月 | J80: 迷惑メール | K80: 103 | L80: 各ユーザーレベルで必要な知識はマニュアルが欲しいですが、 OJTはお願したいです。特にセキュリティはハードルが高いと感じてます・・・ 個人的には、メールは迷惑メールが来てるのと、SPAM認識されてるメールも多く、 何かしら各個人で対応ができるのか等、教えて頂きたいです。 | M80: 馬場阿弥子 | N80: セキュリティ | R80: 80 | S80: データ蓄積による性能劣化の可能性 | AA80: デスクトップアイコンの位置が変わる
A81: (空白) | B81: (空白) | C81: 1 | D81: 本社 | E81: 品質保証部 | F81: 品質管理課 | G81: - | H81: 2025年 | I81: 7月 | J81: 迷惑メール | K81: 291 | L81: 迷惑メールが多量に届くためブロックする方法や対策について相談を行いたい | M81: 野村秀太朗 | N81: ④セキュリティ | R81: 81 | S81: 物流オペレーションに直接影響
A82: (空白) | B82: (空白) | C82: 1 | D82: 本社 | E82: 技術製造部 | F82: 生産管理課 | G82: 生産管理 | H82: 2025年 | I82: 3月 | J82: デュアルモニター | K82: 13 | L82: ・複数のデータを見ながら処理を進めることが多いので、デュアルモニターだと作業効率が上がりそうです | M82: 中島和哉 | N82: (空白) | R82: 82 | AA82: Wi-Fi設定
A83: (空白) | B83: (空白) | C83: 1 | D83: 本社 | E83: 技術製造部 | F83: 生産管理課 | G83: 生産管理 | H83: 2025年 | I83: 3月 | J83: デュアルモニター | K83: 18 | L83: ・デュアルモニターの対応ができてデータを並べられたら、効率は上がる可能性あります。 例えば、製造予定とTPCIS等を並べて確認や、充填バルクの製造予定並べて見れたら、画面が広分確認はしやすいです。 | M83: 馬場阿弥子 | N83: (空白) | R83: 83 | S83: ⑤ 東京営業所 | AA83: TPiCS・PI-navi
A84: (空白) | B84: (空白) | C84: 1 | D84: 本社 | E84: 技術製造部 | F84: 生産管理課 | G84: 生産管理 | H84: 2025年 | I84: 7月 | J84: 迷惑メール | K84: 281 | L84: 迷惑メールが一定数あったり、必要なメールがSPAM認定されてるので、エラーとかで届かない等にならないかは気になる | M84: 馬場阿弥子 | N84: ④セキュリティ | R84: 84 | S84: ● 主な課題 | AA84: 現品票発行
A85: (空白) | B85: (空白) | C85: 1 | D85: 本社 | E85: 技術製造部 | F85: 生産管理課 | G85: 生産管理 | H85: 2025年 | I85: 7月 | J85: 迷惑メール | K85: 287 | L85: ウイルス対策と迷惑メールはなくしてほしい | M85: 島田智章 | N85: ④セキュリティ | R85: 85 | S85: 回線・サーバ由来の待ち時間 | AA85: タブレット
A86: (空白) | B86: (空白) | C86: 1 | D86: 本社 | E86: 技術製造部 | F86: 生産管理課 | G86: 生産管理事務 | H86: 2025年 | I86: 7月 | J86: 迷惑メール | K86: 284 | L86: 最近迷惑メールが来る頻度が増えている。 | M86: 徳永彩花 | N86: ④セキュリティ | R86: 86 | S86: トラブル対応ナレッジ不足 | AA86: ハンディターミナル
A87: (空白) | B87: (空白) | C87: 1 | D87: 本社 | E87: 技術製造部 | F87: 生産管理課 | G87: 生産管理事務 | H87: 2025年 | I87: 7月 | J87: 迷惑メール | K87: 288 | L87: 毎日迷惑メールが来る。(2～3件) | M87: 東香里 | N87: ④セキュリティ | R87: 87 | S87: ● 特徴 | AA87: テプラ
A88: (空白) | B88: (空白) | C88: 1 | D88: 本社 | E88: 技術製造部 | F88: 製造課 | G88: 液体 | H88: 2025年 | I88: 7月 | J88: 迷惑メール | K88: 297 | L88: 迷惑メール(野村證券、アマゾン等)よく来ます。 | M88: 伊澤浩司 | N88: ④セキュリティ | R88: 88 | S88: 業務停止まではいかないが効率ロス
A89: (空白) | B89: (空白) | C89: 1 | D89: コスメファクトリー | E89: 技術製造部 | F89: 製造課 | G89: バルク・顆粒 | H89: 2025年 | I89: 7月 | J89: 迷惑メール | K89: 271 | L89: 最近迷惑メールが来るようになっているので出来ればなくしたいです。 | M89: 外間裕貴人 | N89: ④セキュリティ | R89: 89 | S89: ITサポート体制課題が顕在化
A90: (空白) | B90: (空白) | C90: 1 | D90: コスメファクトリー | E90: 技術製造部 | F90: 製造課 | G90: 充填包装 | H90: 2025年 | I90: 7月 | J90: 迷惑メール | K90: 266 | L90: ここ最近AppleやＳＢＩ証券を名乗る迷惑メールがくることがあり、無視しているが来ないように出来ないか。 | M90: 東口智一 | N90: ④セキュリティ
A91: (空白) | B91: (空白) | C91: 1 | D91: コスメラボラトリー | E91: 技術製造部 | F91: 製造課 | G91: バルク・顆粒 | H91: 2025年 | I91: 7月 | J91: 迷惑メール | K91: 268 | L91: 迷惑メールがよく来るので来ないようにしてほしい。削除がめんどくさい。 | M91: 小田晶彦 | N91: ④セキュリティ

Sheet MS365
D1: 46087 | E1: 鳥山主任 | K1: 46079 | L1: 髙野
B2: 奉行担当関連 | K2: 【管理/共有】
C3: ①Q美ワールド側の生産管理課アカウントの有無 | K3: 図書杏子 SSC/Q美(売り) E
D4: 東さんのアカウントのみあり | K4: 越智絵美子 SSC/Q美(買い,棚卸) E
C5: ②管理部がExcelを必要としない場合の作業環境(サーバーorローカル) | K5: 丸中都 SSC？/Q美 E
D6: サーバーで作業を行っている | K6: ∟3+鳥山
C7: ③シンコーサイエンス側の「売る」「買う」の処理分担
D8: 「売る」は図書主任、「買う」は越智リーダー | K8: 【生産管理1/共有】
C9: ④丸中さんがシンコーサイエンス側を触るか否か | K9: 馬場阿弥子 SSC EE
D10: 森下産業の原料受注に対する発注処理を行うことがある | K10: 東香里 SSC EE
C11: ⑤Q美ワールドの原価登録担当 | K11: 徳永彩花 SSC EE
D12: 丸中さん | K12: ∟3+鳥山
C13: ⑥受注～売りの登録での2重登録
D14: 奉行クラウドにおいては、売価が変更となった場合 | K14: 【生産管理2/共有】
D15: 売りの処理時に売価を変更する | K15: 鳥山一洋 SSC EE
D16: 受注側にも反映されるので、2重登録とはなっていない | K16: 中島和哉 SSC E
C17: ⑦Q美、シンコーの受注～売りの登録の流れ | K17: 島田智章 SSC E
D18: Q美受注～売りまでの登録を丸中さんが行い | K18: +物流?
D19: 一か月分まとめたQ美原価とシンコー原価を図書主任に提示
D20: その情報をもとに図書主任がシンコーからQ美に | K20: 【WEB/共有】
D21: 請求処理を行う | K21: 中土陽介
K22: 髙野愛子
B23: 生産管理課のMS365導入関連 | K23: 中村剛
C24: ・MS365の2アカウントに対する振り分け
D25: ①島田主任、馬場リーダー、中島くん、鳥山 | K25: 【営業/個別】
D26: ②東さん、徳永さん、池田リーダー(タブレット)、鳥山 | K26: 吉村善成
D27: ※池田リーダーについてはMS365導入後、実運用でどのように生かせるのか検証を進める | K27: 南光彦
K28: 橋本悠司
K31: サーバ奉行 システム側の動作保証の問題だけなので、残しておく方向
K33: 仕入発注 奉行→TPiCS CSV又はExcel吐き出してO→マクロ加工してT→取り込む＠生管
K34: 受注登録 TPiCS→奉行 出荷先-注意事項(追加項目⇄1項目でテンプレ化) →取り込む＠管理
K35: 原価 TPiCS→原価表→奉行 マクロ加工してO→取り込む＠生管？管理？
K36: 出荷/出庫 TPiCS→奉行 検討(預かり在庫の識別) →取り込む＠生管？管理？

Sheet 抜粋P
A3: キーワード | B3: 合計 / 意識/姿勢 | C3: 個数 / 原文
A4: AI・自動化 | B4: 5 | C4: 1
A5: Excel | C5: 3
A6: Excel・PDF | C6: 1
A7: Excel・Word | C7: 2
A8: Excel-製造関連 | B8: 30 | C8: 7
A9: Explorer | C9: 1
A10: Lanscope | B10: 5 | C10: 1
A11: Outlook | B11: 4 | C11: 4
A12: PDF | C12: 3
A13: TPiCS・PI-navi | C13: 1
A14: Wi-Fi設定 | C14: 1
A15: タブレット | C15: 1
A16: データ化 | B16: 4 | C16: 1
A17: デスクトップアイコン | C17: 1
A18: テプラ | C18: 1
A19: デュアルモニター | C19: 2
A20: ハイパーリンク | C20: 3
A21: バックアップ | C21: 1
A22: ハンディターミナル | C22: 1
A23: ブラウザ | C23: 5
A24: プリンタ既定 | C24: 3
A25: マニュアル・ナレッジ | B25: 92 | C25: 21
A26: マニュアル作成 | B26: 5 | C26: 1
A27: メール検索 | C27: 4
A28: メール振分 | C28: 2
A29: リアルタイム共有 | B29: 5 | C29: 1
A30: ワークフロー | B30: 9 | C30: 2
A31: 案件タスク管理 | B31: 5 | C31: 1
A32: 議事録 | B32: 16 | C32: 4
A33: 拠点外作業 | B33: 13 | C33: 3
A34: 共有フォルダ | B34: 35 | C34: 9
A35: 現品票発行 | C35: 1
A36: 最適化・高速化 | C36: 1
A37: 参照先整備 | B37: 5 | C37: 1
A38: 時間帯 | B38: 3 | C38: 3
A39: 自動通知 | B39: 8 | C39: 2
A40: 日報改善 | B40: 5 | C40: 1
A41: 日報活用 | B41: 5 | C41: 1
A42: 迷惑メール | B42: 43 | C42: 11
A43: 履歴管理 | B43: 4 | C43: 1
A44: (空白) | B44: 1169 | C44: 351
A45: 総計 | B45: 1470 | C45: 465

Sheet 完了CP
A2: サーバ/端末 | B2: 1
A3: 完了 | B3: (空白)
A5: 接続/動作 | B5: アプリ/操作 | C5: 体制/管理 | D5: 勤務拠点 | E5: 部 | F5: 課 | G5: 係 | H5: 年 (回答時期) | I5: 月 (回答時期) | J5: キーワード | K5: No | L5: 原文 | M5: 氏名 | N5: ヒアリング項目
A6: 1 | B6: 1 | C6: 1 | D6: コスメラボラトリー | E6: 技術製造部 | F6: 製造課 | G6: バルク・顆粒 | H6: 2025年 | I6: 3月 | J6: 現品票発行 | K6: 28 | L6: ・ネットの環境か分からないが、現品票の発行（印刷）に時間がかかる。 | M6: 小田晶彦 | N6: (空白)
A7: 1 | B7: 1 | C7: (空白) | D7: 本社 | E7: 技術製造部 | F7: 生産管理課 | G7: 生産管理 | H7: 2025年 | I7: 3月 | J7: ハイパーリンク | K7: 17 | L7: ・エクセルのハイパーリンクはバグりやすいです | M7: 馬場阿弥子 | N7: (空白)
A8: 1 | B8: 1 | C8: (空白) | D8: 本社 | E8: 技術製造部 | F8: 生産管理課 | G8: 生産管理 | H8: 2025年 | I8: 3月 | J8: (空白) | K8: 12 | L8: ・ローカルのブラウザやSkypeの起動が遅い(1～3分くらい掛かる) | M8: 中島和哉 | N8: (空白)
A9: 1 | B9: 1 | C9: (空白) | D9: 本社 | E9: 技術製造部 | F9: 生産管理課 | G9: 生産管理 | H9: 2025年 | I9: 3月 | J9: (空白) | K9: 20 | L9: ・Rグループが重いのとSkypeも終わるタイミングで、チャットやweb会議、スケジュール管理を、 Microsoft系かGoogle系にまとめられたら、各自予定の登録や確認がしやすいかなと思います。 | M9: 馬場阿弥子 | N9: (空白)
A10: 1 | B10: 1 | C10: (空白) | D10: 本社 | E10: 技術製造部 | F10: 生産管理課 | G10: 生産管理事務 | H10: 2025年 | I10: 3月 | J10: PDF | K10: 5 | L10: ・PDFの文字化け(最近落ち着いた気がしますが…) | M10: 東香里 | N10: (空白)
A11: 1 | B11: 1 | C11: (空白) | D11: 本社 | E11: 技術製造部 | F11: 生産管理課 | G11: 生産管理事務 | H11: 2025年 | I11: 3月 | J11: PDF | K11: 6 | L11: ・概ねPDFが重い気がします | M11: 東香里 | N11: (空白)
A12: 1 | B12: 1 | C12: (空白) | D12: 本社 | E12: 技術製造部 | F12: 生産管理課 | G12: 生産管理事務 | H12: 2025年 | I12: 3月 | J12: ハイパーリンク | K12: 2 | L12: ・定期的にハイパーリンクがリンクしなくなる。 | M12: 徳永彩花 | N12: (空白)
A13: 1 | B13: 1 | C13: (空白) | D13: 本社 | E13: 技術製造部 | F13: 生産管理課 | G13: 生産管理事務 | H13: 2025年 | I13: 3月 | J13: ハイパーリンク | K13: 4 | L13: ・たまにハイパーリンクが死亡する(どういった場合かは不明。突然発生する) | M13: 東香里 | N13: (空白)
A14: 1 | B14: 1 | C14: (空白) | D14: 本社 | E14: 技術製造部 | F14: 生産管理課 | G14: 生産管理事務 | H14: 2025年 | I14: 3月 | J14: (空白) | K14: 1 | L14: ・サーバーのフリーズが多い、ローカルのSkype立ち上がりなど少し遅い印象 | M14: 徳永彩花 | N14: (空白)
A15: 1 | B15: 1 | C15: (空白) | D15: コスメラボラトリー | E15: 研究開発部 | F15: 研究開発課 | G15: - | H15: 2025年 | I15: 3月 | J15: Excel | K15: 62 | L15: ・一定の手順で必ずエクセルとワードが落ちることがある。 | M15: 近藤雅人 | N15: (空白)
A16: 1 | B16: 1 | C16: (空白) | D16: コスメラボラトリー | E16: 研究開発部 | F16: 研究開発課 | G16: - | H16: 2025年 | I16: 3月 | J16: Excel | K16: 90 | L16: ・Excelの動きが遅い、フリーズして消えることがある | M16: 橋口千聖 | N16: (空白)
A17: 1 | B17: 1 | C17: (空白) | D17: コスメラボラトリー | E17: 研究開発部 | F17: 研究開発課 | G17: - | H17: 2025年 | I17: 3月 | J17: Excel・PDF | K17: 73 | L17: ・エクセル、PDF使用時は遅くなりやすい。 | M17: 直木美佐子 | N17: (空白)
A18: 1 | B18: 1 | C18: (空白) | D18: コスメラボラトリー | E18: 研究開発部 | F18: 研究開発課 | G18: - | H18: 2025年 | I18: 3月 | J18: Excel・Word | K18: 60 | L18: ・エクセル・ワードにて、タイピングした内容が反映されるまでのタイムラグがかなりある時がある。 | M18: 近藤雅人 | N18: (空白)
... A31: 1 | B31: 1 | C31: (空白) | D31: コスメラボラトリー | E31: EC事業部 | F31: EC事業課 | G31: - | H31: 2025年 | I31: 3月 | J31: ブラウザ | K31: 58 | L31: ブラウザ上の業務が多い中、固まることで遅延してしまう。 | M31: 酒井絢音 | N31: (空白)
A32: 1 | B32: (空白) | C32: 1 | D32: 本社 | E32: 技術製造部 | F32: 製造課 | G32: 粉体 | H32: 2025年 | I32: 7月 | J32: 迷惑メール | K32: 376 | L32: 迷惑メールが増えている。今でもフリーズすることがある。 | M32: 内藤恭介 | N32: ⑥その他(自由意見)
A33: 1 | B33: (空白) | C33: 1 | D33: 第一倉庫 | E33: 技術製造部 | F33: 生産管理課 | G33: 物流 | H33: 2025年 | I33: 3月 | J33: ハンディターミナル | K33: 15 | L33: ・ハンディの動作反応が年々遅くなっている→データ蓄積されているため？ | M33: 池田悦彰 | N33: (空白)
A34: 1 | B34: (空白) | C34: (空白) | D34: 本社 | E34: 管理部 | F34: 管理課 | G34: - | H34: 2025年 | I34: 3月 | J34: デスクトップアイコン | K34: 39 | L34: ・会計処理をする際、管理部用のノートＰＣでサーバー接続しCSVデータを取り込んでいますが、デスクトップPCに戻りログインするとデスクトップ上のアイコンの配列がバラバラになり少しストレスです | M34: 図書杏子 | N34: (空白)
A35: 1 | B35: (空白) | C35: (空白) | D35: 本社 | E35: 管理部 | F35: 管理課 | G35: - | H35: 2025年 | I35: 3月 | J35: ブラウザ | K35: 47 | L35: ･アマゾンサイトなどへ接続している時、サイト内の動きがとても遅いです。 | M35: 丸中都 | N35: (空白)
A36: 1 | B36: (空白) | C36: (空白) | D36: 本社 | E36: 管理部 | F36: 管理課 | G36: - | H36: 2025年 | I36: 3月 | J36: プリンタ既定 | K36: 38 | L36: ・一定期間作業していない時（昼休みなど）ログイン画面が表示され入るとプリンター指定が解除されて毎回ＰＤＦ指定になる | M36: 図書杏子 | N36: (空白)
A37: 1 | B37: (空白) | C37: (空白) | D37: 本社 | E37: 管理部 | F37: 管理課 | G37: - | H37: 2025年 | I37: 3月 | J37: 共有フォルダ | K37: 41 | L37: ・毎日最初の一回共有フォルダにはじかれる | M37: 越智絵美子 | N37: (空白)
A38: 1 | B38: (空白) | C38: (空白) | D38: 本社 | E38: 管理部 | F38: 管理課 | G38: - | H38: 2025年 | I38: 3月 | J38: (空白) | K38: 45 | L38: ・昔よりは改善されてますがPCが固まったり遅かったりする | M38: 越智絵美子 | N38: (空白)
A39: 1 | B39: (空白) | C39: (空白) | D39: 本社 | E39: 管理部 | F39: 管理課 | G39: - | H39: 2025年 | I39: 3月 | J39: (空白) | K39: 46 | L39: ・事務長がサーバーになかなか入れないときがある | M39: 越智絵美子 | N39: (空白)
A40: 1 | B40: (空白) | C40: (空白) | D40: 本社 | E40: 管理部 | F40: 管理課 | G40: - | H40: 2025年 | I40: 3月 | J40: (空白) | K40: 48 | L40: ･突然サーバーからはじき出される。ログインしなおすと作業途中の画面には戻れます。 | M40: 丸中都 | N40: (空白)
A41: 1 | B41: (空白) | C41: (空白) | D41: 本社 | E41: 技術製造部 | F41: 生産管理課 | G41: 生産管理 | H41: 2025年 | I41: 3月 | J41: (空白) | K41: 10 | L41: ・ローカル、サーバー共にフリーズが多い | M41: 中島和哉 | N41: (空白)
A42: 1 | B42: (空白) | C42: (空白) | D42: 本社 | E42: 技術製造部 | F42: 生産管理課 | G42: 生産管理 | H42: 2025年 | I42: 3月 | J42: (空白) | K42: 11 | L42: ・パソコンの起動が遅く、シンクラの接続にも時間が掛かる、電源入～デスクトップの画面表示まで約3分30秒、Aサーバー接続アイコン選択～シンクラ画面まで約2分30秒 | M42: 中島和哉 | N42: (空白)
A43: 1 | B43: (空白) | C43: (空白) | D43: 本社 | E43: 技術製造部 | F43: 生産管理課 | G43: 生産管理 | H43: 2025年 | I43: 3月 | J43: (空白) | K43: 19 | L43: ・サーバーのフリーズが多い | M43: 馬場阿弥子 | N43: (空白)
A44: 1 | B44: (空白) | C44: (空白) | D44: 本社 | E44: 技術製造部 | F44: 生産管理課 | G44: 生産管理 | H44: 2025年 | I44: 3月 | J44: (空白) | K44: 22 | L44: ・ローカルのブラウザやSkypeの起動が遅い(1～3分くらい掛かる) | M44: 島田智章 | N44: (空白)
A45: 1 | B45: (空白) | C45: (空白) | D45: 本社 | E45: 技術製造部 | F45: 生産管理課 | G45: 生産管理 | H45: 2025年 | I45: 3月 | J45: (空白) | K45: 23 | L45: ・パソコンの起動が遅く、シンクラの接続にも時間が掛かる(中島くんと同等の所要時間) ※島田主任と中島くんのPCスペックは同等です | M45: 島田智章 | N45: (空白)
... A83: 1 | B83: (空白) | C83: (空白) | D83: 東京営業所 | E83: 企画営業部 | F83: 営業課 | G83: - | H83: 2025年 | I83: 6月 | J83: マニュアル・ナレッジ | K83: 119 | L83: サーバーやアプリに繋がらないなどの時の簡易トラブル対処マニュアル作成 | M83: 橋本悠司 | N83: セキュリティ
A84: (空白) | B84: 1 | C84: 1 | D84: 本社 | E84: 技術製造部 | F84: 生産管理課 | G84: 生産管理 | H84: 2025年 | I84: 6月 | J84: 迷惑メール | K84: 103 | L84: 各ユーザーレベルで必要な知識はマニュアルが欲しいですが、 OJTはお願したいです。特にセキュリティはハードルが高いと感じてます・・・ 個人的には、メールは迷惑メールが来てるのと、SPAM認識されてるメールも多く、 何かしら各個人で対応ができるのか等、教えて頂きたいです。 | M84: 馬場阿弥子 | N84: セキュリティ
A85: (空白) | B85: (空白) | C85: 1 | D85: 本社 | E85: 品質保証部 | F85: 品質管理課 | G85: - | H85: 2025年 | I85: 7月 | J85: 迷惑メール | K85: 291 | L85: 迷惑メールが多量に届くためブロックする方法や対策について相談を行いたい | M85: 野村秀太朗 | N85: ④セキュリティ
A86: (空白) | B86: (空白) | C86: 1 | D86: 本社 | E86: 技術製造部 | F86: 生産管理課 | G86: 生産管理 | H86: 2025年 | I86: 3月 | J86: デュアルモニター | K86: 13 | L86: ・複数のデータを見ながら処理を進めることが多いので、デュアルモニターだと作業効率が上がりそうです | M86: 中島和哉 | N86: (空白)
A87: (空白) | B87: (空白) | C87: 1 | D87: 本社 | E87: 技術製造部 | F87: 生産管理課 | G87: 生産管理 | H87: 2025年 | I87: 3月 | J87: デュアルモニター | K87: 18 | L87: ・デュアルモニターの対応ができてデータを並べられたら、効率は上がる可能性あります。 例えば、製造予定とTPCIS等を並べて確認や、充填バルクの製造予定並べて見れたら、画面が広分確認はしやすいです。 | M87: 馬場阿弥子 | N87: (空白)
A88: (空白) | B88: (空白) | C88: 1 | D88: 本社 | E88: 技術製造部 | F88: 生産管理課 | G88: 生産管理 | H88: 2025年 | I88: 7月 | J88: 迷惑メール | K88: 281 | L88: 迷惑メールが一定数あったり、必要なメールがSPAM認定されてるので、エラーとかで届かない等にならないかは気になる | M88: 馬場阿弥子 | N88: ④セキュリティ
A89: (空白) | B89: (空白) | C89: 1 | D89: 本社 | E89: 技術製造部 | F89: 生産管理課 | G89: 生産管理 | H89: 2025年 | I89: 7月 | J89: 迷惑メール | K89: 287 | L89: ウイルス対策と迷惑メールはなくしてほしい | M89: 島田智章 | N89: ④セキュリティ
A90: (空白) | B90: (空白) | C90: 1 | D90: 本社 | E90: 技術製造部 | F90: 生産管理課 | G90: 生産管理事務 | H90: 2025年 | I90: 7月 | J90: 迷惑メール | K90: 284 | L90: 最近迷惑メールが来る頻度が増えている。 | M90: 徳永彩花 | N90: ④セキュリティ
A91: (空白) | B91: (空白) | C91: 1 | D91: 本社 | E91: 技術製造部 | F91: 生産管理課 | G91: 生産管理事務 | H91: 2025年 | I91: 7月 | J91: 迷惑メール | K91: 288 | L91: 毎日迷惑メールが来る。(2～3件) | M91: 東香里 | N91: ④セキュリティ
A92: (空白) | B92: (空白) | C92: 1 | D92: 本社 | E92: 技術製造部 | F92: 製造課 | G92: 液体 | H92: 2025年 | I92: 7月 | J92: 迷惑メール | K92: 297 | L92: 迷惑メール(野村證券、アマゾン等)よく来ます。 | M92: 伊澤浩司 | N92: ④セキュリティ
A93: (空白) | B93: (空白) | C93: 1 | D93: コスメファクトリー | E93: 技術製造部 | F93: 製造課 | G93: バルク・顆粒 | H93: 2025年 | I93: 7月 | J93: 迷惑メール | K93: 271 | L93: 最近迷惑メールが来るようになっているので出来ればなくしたいです。 | M93: 外間裕貴人 | N93: ④セキュリティ
A94: (空白) | B94: (空白) | C94: 1 | D94: コスメファクトリー | E94: 技術製造部 | F94: 製造課 | G94: 充填包装 | H94: 2025年 | I94: 7月 | J94: 迷惑メール | K94: 266 | L94: ここ最近AppleやＳＢＩ証券を名乗る迷惑メールがくることがあり、無視しているが来ないように出来ないか。 | M94: 東口智一 | N94: ④セキュリティ
A95: (空白) | B95: (空白) | C95: 1 | D95: コスメラボラトリー | E95: 技術製造部 | F95: 製造課 | G95: バルク・顆粒 | H95: 2025年 | I95: 7月 | J95: 迷惑メール | K95: 268 | L95: 迷惑メールがよく来るので来ないようにしてほしい。削除がめんどくさい。 | M95: 小田晶彦 | N95: ④セキュリティ

Sheet データベース
E1: 1短期：すぐできる | P1: 1無し | R1: 561
E2: 2中期：現状からできる | P2: 2低い
E3: 3長期：環境整備から | P3: 3普通
P4: 4有り | R4: 受動的、限定的
P5: 5高い | R5: 能動的、広範囲
A6: No | B6: 回答時期 | C6: 計画No | D6: 計画着手 | E6: 期間 | F6: ヒアリング項目 | G6: キーワード | H6: サーバ/端末 | I6: 接続/動作 | J6: アプリ/操作 | K6: 体制/管理 | L6: 基礎向上 | M6: マニュアル/ナレッジ | N6: AI/DB化 | O6: 課題/提案 | P6: 意識/姿勢 | Q6: 候補者 | R6: 原文 | S6: 主担当 | T6: 対策/解決 | U6: 完了 | V6: 氏名 | W6: 部 | X6: 課 | Y6: 係 | Z6: 勤務拠点 | AA6: 接続エリア
A7: 1 | B7: 45746 | H7: 1 | I7: 1 | J7: 1 | R7: ・サーバーのフリーズが多い、ローカルのSkype立ち上がりなど少し遅い印象 | V7: 徳永彩花 | W7: =VLOOKUP(V7,名簿!A:L,3,FALSE) -> 技術製造部 | X7: =VLOOKUP(V7,名簿!A:L,4,FALSE) -> 生産管理課 | Y7: =VLOOKUP(V7,名簿!A:L,5,FALSE) -> 生産管理事務 | Z7: =VLOOKUP(V7,名簿!A:L,11,FALSE) -> 本社 | AA7: =VLOOKUP(V7,名簿!A:L,12,FALSE) -> 3F/シンク前
A8: 2 | B8: 45746 | G8: ハイパーリンク | H8: 1 | I8: 1 | J8: 1 | R8: ・定期的にハイパーリンクがリンクしなくなる。 | V8: 徳永彩花 | W8: =VLOOKUP(V8,名簿!A:L,3,FALSE) -> 技術製造部 | X8: =VLOOKUP(V8,名簿!A:L,4,FALSE) -> 生産管理課 | Y8: =VLOOKUP(V8,名簿!A:L,5,FALSE) -> 生産管理事務 | Z8: =VLOOKUP(V8,名簿!A:L,11,FALSE) -> 本社 | AA8: =VLOOKUP(V8,名簿!A:L,12,FALSE) -> 3F/シンク前
A9: 3 | B9: 45746 | H9: 1 | I9: 1 | R9: ・定期的にデスクトップのアイコン位置シャッフルされる | V9: 徳永彩花 | W9: =VLOOKUP(V9,名簿!A:L,3,FALSE) -> 技術製造部 | X9: =VLOOKUP(V9,名簿!A:L,4,FALSE) -> 生産管理課 | Y9: =VLOOKUP(V9,名簿!A:L,5,FALSE) -> 生産管理事務 | Z9: =VLOOKUP(V9,名簿!A:L,11,FALSE) -> 本社 | AA9: =VLOOKUP(V9,名簿!A:L,12,FALSE) -> 3F/シンク前
A10: 4 | B10: 45746 | G10: ハイパーリンク | H10: 1 | I10: 1 | J10: 1 | R10: ・たまにハイパーリンクが死亡する(どういった場合かは不明。突然発生する) | V10: 東香里 | W10: =VLOOKUP(V10,名簿!A:L,3,FALSE) -> 技術製造部 | X10: =VLOOKUP(V10,名簿!A:L,4,FALSE) -> 生産管理課 | Y10: =VLOOKUP(V10,名簿!A:L,5,FALSE) -> 生産管理事務 | Z10: =VLOOKUP(V10,名簿!A:L,11,FALSE) -> 本社 | AA10: =VLOOKUP(V10,名簿!A:L,12,FALSE) -> 3F/シンク前
A11: 5 | B11: 45746 | G11: PDF | H11: 1 | I11: 1 | J11: 1 | R11: ・PDFの文字化け(最近落ち着いた気がしますが…) | V11: 東香里 | W11: =VLOOKUP(V11,名簿!A:L,3,FALSE) -> 技術製造部 | X11: =VLOOKUP(V11,名簿!A:L,4,FALSE) -> 生産管理課 | Y11: =VLOOKUP(V11,名簿!A:L,5,FALSE) -> 生産管理事務 | Z11: =VLOOKUP(V11,名簿!A:L,11,FALSE) -> 本社 | AA11: =VLOOKUP(V11,名簿!A:L,12,FALSE) -> 3F/シンク前
A12: 6 | B12: 45746 | G12: PDF | H12: 1 | I12: 1 | J12: 1 | R12: ・概ねPDFが重い気がします | V12: 東香里 | W12: =VLOOKUP(V12,名簿!A:L,3,FALSE) -> 技術製造部 | X12: =VLOOKUP(V12,名簿!A:L,4,FALSE) -> 生産管理課 | Y12: =VLOOKUP(V12,名簿!A:L,5,FALSE) -> 生産管理事務 | Z12: =VLOOKUP(V12,名簿!A:L,11,FALSE) -> 本社 | AA12: =VLOOKUP(V12,名簿!A:L,12,FALSE) -> 3F/シンク前
A13: 7 | B13: 45746 | H13: 1 | I13: 1 | R13: ・天気が悪いとPCの動きが鈍い | V13: 東香里 | W13: =VLOOKUP(V13,名簿!A:L,3,FALSE) -> 技術製造部 | X13: =VLOOKUP(V13,名簿!A:L,4,FALSE) -> 生産管理課 | Y13: =VLOOKUP(V13,名簿!A:L,5,FALSE) -> 生産管理事務 | Z13: =VLOOKUP(V13,名簿!A:L,11,FALSE) -> 本社 | AA13: =VLOOKUP(V13,名簿!A:L,12,FALSE) -> 3F/シンク前
A14: 8 | B14: 45746 | K14: 1 | R14: ・受注時に「クライアント名」「製品名」に読み仮名をつけるようにして欲しい。様々の物をフォルダ分けする際に名前が不明な事が多く困る為。 | V14: 徳永彩花 | W14: =VLOOKUP(V14,名簿!A:L,3,FALSE) -> 技術製造部 | X14: =VLOOKUP(V14,名簿!A:L,4,FALSE) -> 生産管理課 | Y14: =VLOOKUP(V14,名簿!A:L,5,FALSE) -> 生産管理事務 | Z14: =VLOOKUP(V14,名簿!A:L,11,FALSE) -> 本社 | AA14: =VLOOKUP(V14,名簿!A:L,12,FALSE) -> 3F/シンク前
A15: 9 | B15: 45746 | K15: 1 | R15: ・受注時に「クライアント名」「製品名」に読み仮名をつけるようにして欲しい。様々の物をフォルダ分けする際に名前が不明な事が多く困る為。 | V15: 東香里 | W15: =VLOOKUP(V15,名簿!A:L,3,FALSE) -> 技術製造部 | X15: =VLOOKUP(V15,名簿!A:L,4,FALSE) -> 生産管理課 | Y15: =VLOOKUP(V15,名簿!A:L,5,FALSE) -> 生産管理事務 | Z15: =VLOOKUP(V15,名簿!A:L,11,FALSE) -> 本社 | AA15: =VLOOKUP(V15,名簿!A:L,12,FALSE) -> 3F/シンク前
A16: 10 | B16: 45746 | H16: 1 | I16: 1 | R16: ・ローカル、サーバー共にフリーズが多い | V16: 中島和哉 | W16: =VLOOKUP(V16,名簿!A:L,3,FALSE) -> 技術製造部 | X16: =VLOOKUP(V16,名簿!A:L,4,FALSE) -> 生産管理課 | Y16: =VLOOKUP(V16,名簿!A:L,5,FALSE) -> 生産管理 | Z16: =VLOOKUP(V16,名簿!A:L,11,FALSE) -> 本社 | AA16: =VLOOKUP(V16,名簿!A:L,12,FALSE) -> 3F/シンク前
A17: 11 | B17: 45746 | H17: 1 | I17: 1 | R17: ・パソコンの起動が遅く、シンクラの接続にも時間が掛かる、電源入～デスクトップの画面表示まで約3分30秒、Aサーバー接続アイコン選択～シンクラ画面まで約2分30秒 | V17: 中島和哉 | W17: =VLOOKUP(V17,名簿!A:L,3,FALSE) -> 技術製造部 | X17: =VLOOKUP(V17,名簿!A:L,4,FALSE) -> 生産管理課 | Y17: =VLOOKUP(V17,名簿!A:L,5,FALSE) -> 生産管理 | Z17: =VLOOKUP(V17,名簿!A:L,11,FALSE) -> 本社 | AA17: =VLOOKUP(V17,名簿!A:L,12,FALSE) -> 3F/シンク前
A18: 12 | B18: 45746 | H18: 1 | I18: 1 | J18: 1 | R18: ・ローカルのブラウザやSkypeの起動が遅い(1～3分くらい掛かる) | V18: 中島和哉 | W18: =VLOOKUP(V18,名簿!A:L,3,FALSE) -> 技術製造部 | X18: =VLOOKUP(V18,名簿!A:L,4,FALSE) -> 生産管理課 | Y18: =VLOOKUP(V18,名簿!A:L,5,FALSE) -> 生産管理 | Z18: =VLOOKUP(V18,名簿!A:L,11,FALSE) -> 本社 | AA18: =VLOOKUP(V18,名簿!A:L,12,FALSE) -> 3F/シンク前
A19: 13 | B19: 45746 | G19: デュアルモニター | H19: 1 | K19: 1 | O19: 1 | R19: ・複数のデータを見ながら処理を進めることが多いので、デュアルモニターだと作業効率が上がりそうです | V19: 中島和哉 | W19: =VLOOKUP(V19,名簿!A:L,3,FALSE) -> 技術製造部 | X19: =VLOOKUP(V19,名簿!A:L,4,FALSE) -> 生産管理課 | Y19: =VLOOKUP(V19,名簿!A:L,5,FALSE) -> 生産管理 | Z19: =VLOOKUP(V19,名簿!A:L,11,FALSE) -> 本社 | AA19: =VLOOKUP(V19,名簿!A:L,12,FALSE) -> 3F/シンク前
A20: 14 | B20: 45746 | H20: 1 | I20: 1 | R20: ・Bサーバー基本的に重い | V20: 池田悦彰 | W20: =VLOOKUP(V20,名簿!A:L,3,FALSE) -> 技術製造部 | X20: =VLOOKUP(V20,名簿!A:L,4,FALSE) -> 生産管理課 | Y20: =VLOOKUP(V20,名簿!A:L,5,FALSE) -> 物流 | Z20: =VLOOKUP(V20,名簿!A:L,11,FALSE) -> 第一倉庫 | AA20: =VLOOKUP(V20,名簿!A:L,12,FALSE) -> 1F/南西角
A21: 15 | B21: 45746 | G21: ハンディターミナル | H21: 1 | I21: 1 | K21: 1 | R21: ・ハンディの動作反応が年々遅くなっている→データ蓄積されているため？ | V21: 池田悦彰 | W21: =VLOOKUP(V21,名簿!A:L,3,FALSE) -> 技術製造部 | X21: =VLOOKUP(V21,名簿!A:L,4,FALSE) -> 生産管理課 | Y21: =VLOOKUP(V21,名簿!A:L,5,FALSE) -> 物流 | Z21: =VLOOKUP(V21,名簿!A:L,11,FALSE) -> 第一倉庫 | AA21: =VLOOKUP(V21,名簿!A:L,12,FALSE) -> 1F/南西角
A22: 16 | B22: 45746 | G22: メール検索 | I22: 1 | J22: 1 | R22: ・メールの検索がしにくく困ってます。これはOutlookだからなのか、Gmailだと変わるのはわかりません。 | V22: 馬場阿弥子 | W22: =VLOOKUP(V22,名簿!A:L,3,FALSE) -> 技術製造部 | X22: =VLOOKUP(V22,名簿!A:L,4,FALSE) -> 生産管理課 | Y22: =VLOOKUP(V22,名簿!A:L,5,FALSE) -> 生産管理 | Z22: =VLOOKUP(V22,名簿!A:L,11,FALSE) -> 本社 | AA22: =VLOOKUP(V22,名簿!A:L,12,FALSE) -> 3F/シンク前
A23: 17 | B23: 45746 | G23: ハイパーリンク | H23: 1 | I23: 1 | J23: 1 | R23: ・エクセルのハイパーリンクはバグりやすいです | V23: 馬場阿弥子 | W23: =VLOOKUP(V23,名簿!A:L,3,FALSE) -> 技術製造部 | X23: =VLOOKUP(V23,名簿!A:L,4,FALSE) -> 生産管理課 | Y23: =VLOOKUP(V23,名簿!A:L,5,FALSE) -> 生産管理 | Z23: =VLOOKUP(V23,名簿!A:L,11,FALSE) -> 本社 | AA23: =VLOOKUP(V23,名簿!A:L,12,FALSE) -> 3F/シンク前
A24: 18 | B24: 45746 | G24: デュアルモニター | H24: 1 | K24: 1 | O24: 1 | R24: ・デュアルモニターの対応ができてデータを並べられたら、効率は上がる可能性あります。 例えば、製造予定とTPCIS等を並べて確認や、充填バルクの製造予定並べて見れたら、画面が広分確認はしやすいです。 | V24: 馬場阿弥子 | W24: =VLOOKUP(V24,名簿!A:L,3,FALSE) -> 技術製造部 | X24: =VLOOKUP(V24,名簿!A:L,4,FALSE) -> 生産管理課 | Y24: =VLOOKUP(V24,名簿!A:L,5,FALSE) -> 生産管理 | Z24: =VLOOKUP(V24,名簿!A:L,11,FALSE) -> 本社 | AA24: =VLOOKUP(V24,名簿!A:L,12,FALSE) -> 3F/シンク前
A25: 19 | B25: 45746 | H25: 1 | I25: 1 | R25: ・サーバーのフリーズが多い | V25: 馬場阿弥子 | W25: =VLOOKUP(V25,名簿!A:L,3,FALSE) -> 技術製造部 | X25: =VLOOKUP(V25,名簿!A:L,4,FALSE) -> 生産管理課 | Y25: =VLOOKUP(V25,名簿!A:L,5,FALSE) -> 生産管理 | Z25: =VLOOKUP(V25,名簿!A:L,11,FALSE) -> 本社 | AA25: =VLOOKUP(V25,名簿!A:L,12,FALSE) -> 3F/シンク前
A26: 20 | B26: 45746 | H26: 1 | I26: 1 | J26: 1 | R26: ・Rグループが重いのとSkypeも終わるタイミングで、チャットやweb会議、スケジュール管理を、 Microsoft系かGoogle系にまとめられたら、各自予定の登録や確認がしやすいかなと思います。 | V26: 馬場阿弥子 | W26: =VLOOKUP(V26,名簿!A:L,3,FALSE) -> 技術製造部 | X26: =VLOOKUP(V26,名簿!A:L,4,FALSE) -> 生産管理課 | Y26: =VLOOKUP(V26,名簿!A:L,5,FALSE) -> 生産管理 | Z26: =VLOOKUP(V26,名簿!A:L,11,FALSE) -> 本社 | AA26: =VLOOKUP(V26,名簿!A:L,12,FALSE) -> 3F/シンク前
A27: 21 | B27: 45746 | G27: メール検索 | I27: 1 | J27: 1 | R27: ・メールの検索がしにくく困る。 | V27: 島田智章 | W27: =VLOOKUP(V27,名簿!A:L,3,FALSE) -> 技術製造部 | X27: =VLOOKUP(V27,名簿!A:L,4,FALSE) -> 生産管理課 | Y27: =VLOOKUP(V27,名簿!A:L,5,FALSE) -> 生産管理 | Z27: =VLOOKUP(V27,名簿!A:L,11,FALSE) -> 本社 | AA27: =VLOOKUP(V27,名簿!A:L,12,FALSE) -> 3F/シンク前
A28: 22 | B28: 45746 | H28: 1 | I28: 1 | R28: ・ローカルのブラウザやSkypeの起動が遅い(1～3分くらい掛かる) | V28: 島田智章 | W28: =VLOOKUP(V28,名簿!A:L,3,FALSE) -> 技術製造部 | X28: =VLOOKUP(V28,名簿!A:L,4,FALSE) -> 生産管理課 | Y28: =VLOOKUP(V28,名簿!A:L,5,FALSE) -> 生産管理 | Z28: =VLOOKUP(V28,名簿!A:L,11,FALSE) -> 本社 | AA28: =VLOOKUP(V28,名簿!A:L,12,FALSE) -> 3F/シンク前
A29: 23 | B29: 45746 | H29: 1 | I29: 1 | R29: ・パソコンの起動が遅く、シンクラの接続にも時間が掛かる(中島くんと同等の所要時間) ※島田主任と中島くんのPCスペックは同等です | V29: 島田智章 | W29: =VLOOKUP(V29,名簿!A:L,3,FALSE) -> 技術製造部 | X29: =VLOOKUP(V29,名簿!A:L,4,FALSE) -> 生産管理課 | Y29: =VLOOKUP(V29,名簿!A:L,5,FALSE) -> 生産管理 | Z29: =VLOOKUP(V29,名簿!A:L,11,FALSE) -> 本社 | AA29: =VLOOKUP(V29,名簿!A:L,12,FALSE) -> 3F/シンク前
A30: 24 | B30: 45746 | G30: メール振分 | I30: 1 | J30: 1 | R30: ・メーリングリストで受信したbouncesのせい？でメールの振り分けが僕には対応できなくなってます。 | V30: 島田智章 | W30: =VLOOKUP(V30,名簿!A:L,3,FALSE) -> 技術製造部 | X30: =VLOOKUP(V30,名簿!A:L,4,FALSE) -> 生産管理課 | Y30: =VLOOKUP(V30,名簿!A:L,5,FALSE) -> 生産管理 | Z30: =VLOOKUP(V30,名簿!A:L,11,FALSE) -> 本社 | AA30: =VLOOKUP(V30,名簿!A:L,12,FALSE) -> 3F/シンク前
A31: 25 | B31: 45746 | H31: 1 | I31: 1 | R31: ・シンクラサーバーの動作が全体的に重い。（シンクラが原因なのか、PC自体が古いからなのかは分からないです） | V31: 北村優樹 | W31: =VLOOKUP(V31,名簿!A:L,3,FALSE) -> 技術製造部 | X31: =VLOOKUP(V31,名簿!A:L,4,FALSE) -> 生産管理課 | Y31: =VLOOKUP(V31,名簿!A:L,5,FALSE) -> 物流 | Z31: =VLOOKUP(V31,名簿!A:L,11,FALSE) -> コスメファクトリー | AA31: =VLOOKUP(V31,名簿!A:L,12,FALSE) -> 1F/事務所
A32: 26 | B32: 45746 | H32: 1 | I32: 1 | R32: ・フリーズが頻発する。社員のパソコン使用が集中する時間帯（主に9時頃、18時頃）は特に多く、長くフリーズする。 | V32: 北村優樹 | W32: =VLOOKUP(V32,名簿!A:L,3,FALSE) -> 技術製造部 | X32: =VLOOKUP(V32,名簿!A:L,4,FALSE) -> 生産管理課 | Y32: =VLOOKUP(V32,名簿!A:L,5,FALSE) -> 物流 | Z32: =VLOOKUP(V32,名簿!A:L,11,FALSE) -> コスメファクトリー | AA32: =VLOOKUP(V32,名簿!A:L,12,FALSE) -> 1F/事務所
A33: 27 | B33: 45746 | H33: 1 | I33: 1 | R33: ・サーバーにつながりにくい（特に朝９時ぐらい） | V33: 小田晶彦 | W33: =VLOOKUP(V33,名簿!A:L,3,FALSE) -> 技術製造部 | X33: =VLOOKUP(V33,名簿!A:L,4,FALSE) -> 製造課 | Y33: =VLOOKUP(V33,名簿!A:L,5,FALSE) -> バルク・顆粒 | Z33: =VLOOKUP(V33,名簿!A:L,11,FALSE) -> コスメラボラトリー | AA33: =VLOOKUP(V33,名簿!A:L,12,FALSE) -> 2F/事務所
A34: 28 | B34: 45746 | G34: 現品票発行 | H34: 1 | I34: 1 | J34: 1 | K34: 1 | R34: ・ネットの環境か分からないが、現品票の発行（印刷）に時間がかかる。 | V34: 小田晶彦 | W34: =VLOOKUP(V34,名簿!A:L,3,FALSE) -> 技術製造部 | X34: =VLOOKUP(V34,名簿!A:L,4,FALSE) -> 製造課 | Y34: =VLOOKUP(V34,名簿!A:L,5,FALSE) -> バルク・顆粒 | Z34: =VLOOKUP(V34,名簿!A:L,11,FALSE) -> コスメラボラトリー | AA34: =VLOOKUP(V34,名簿!A:L,12,FALSE) -> 2F/事務所
A35: 29 | B35: 45746 | D35: 46098 | G35: TPiCS・PI-navi | H35: 1 | I35: 1 | J35: 1 | R35: ・朝の９時以外でもメールやTPiCS・PI-naviが遅い時がある。時間は見てないです。あきらめて製造に戻る時もあります。 | S35: 鳥山 | T35: 3/17PI-navi完了操作遅滞-TA調査依頼 3/18最大限チューニング済 | V35: 小田晶彦 | W35: =VLOOKUP(V35,名簿!A:L,3,FALSE) -> 技術製造部 | X35: =VLOOKUP(V35,名簿!A:L,4,FALSE) -> 製造課 | Y35: =VLOOKUP(V35,名簿!A:L,5,FALSE) -> バルク・顆粒 | Z35: =VLOOKUP(V35,名簿!A:L,11,FALSE) -> コスメラボラトリー | AA35: =VLOOKUP(V35,名簿!A:L,12,FALSE) -> 2F/事務所
A36: 30 | B36: 45746 | H36: 1 | I36: 1 | R36: ・要望はパソコンはスムーズに使いたい。 製造してる合間に打ち込んだりメール見ることがあるので、ネットがつながらないとかあると、作業効率が悪いです。 | V36: 小田晶彦 | W36: =VLOOKUP(V36,名簿!A:L,3,FALSE) -> 技術製造部 | X36: =VLOOKUP(V36,名簿!A:L,4,FALSE) -> 製造課 | Y36: =VLOOKUP(V36,名簿!A:L,5,FALSE) -> バルク・顆粒 | Z36: =VLOOKUP(V36,名簿!A:L,11,FALSE) -> コスメラボラトリー | AA36: =VLOOKUP(V36,名簿!A:L,12,FALSE) -> 2F/事務所
A37: 31 | B37: 45746 | H37: 1 | I37: 1 | R37: 私的には以前に容量削減の対策をやってからフリーズすることがかなり改善したように思います。ただ大川リーダー、伊澤Ｌは今でも動作が重たくなる時はあるとのことです。 | V37: 内藤恭介 | W37: =VLOOKUP(V37,名簿!A:L,3,FALSE) -> 技術製造部 | X37: =VLOOKUP(V37,名簿!A:L,4,FALSE) -> 製造課 | Y37: =VLOOKUP(V37,名簿!A:L,5,FALSE) -> 粉体 | Z37: =VLOOKUP(V37,名簿!A:L,11,FALSE) -> 本社 | AA37: =VLOOKUP(V37,名簿!A:L,12,FALSE) -> 3F/シンク前
A38: 32 | B38: 45746 | G38: 共有フォルダ | K38: 1 | P38: 4 | R38: 製造フォルダの中はかなりフォルダ数多く複雑です。「製造用」とか「元製造」とか「製造用１」がありあまり分別もできていないと思います。探すのが大変なので自分の必要なものはショートカットを作成しまとめていますが大昔のデータも多く処分していいかわからないので皆さん放置状態になっているのかと思います。 | S38: 中村 | T38: 3/11～構造可視化ツール/検索ツール/データコピーツール作成中 3/23完成 | V38: 内藤恭介 | W38: =VLOOKUP(V38,名簿!A:L,3,FALSE) -> 技術製造部 | X38: =VLOOKUP(V38,名簿!A:L,4,FALSE) -> 製造課 | Y38: =VLOOKUP(V38,名簿!A:L,5,FALSE) -> 粉体 | Z38: =VLOOKUP(V38,名簿!A:L,11,FALSE) -> 本社 | AA38: =VLOOKUP(V38,名簿!A:L,12,FALSE) -> 3F/シンク前
A39: 33 | B39: 45746 | G39: 時間帯 | H39: 1 | I39: 1 | R39: サーバーの動作が遅く、すぐ切断される。開発、BeGardenの出勤時刻9時頃が最もサーバーにつながりにくい。 | V39: 小田勇雄 | W39: =VLOOKUP(V39,名簿!A:L,3,FALSE) -> 技術製造部 | X39: =VLOOKUP(V39,名簿!A:L,4,FALSE) -> 製造課 | Y39: =VLOOKUP(V39,名簿!A:L,5,FALSE) -> 充填包装 | Z39: =VLOOKUP(V39,名簿!A:L,11,FALSE) -> コスメラボラトリー | AA39: =VLOOKUP(V39,名簿!A:L,12,FALSE) -> 2F/事務所
A40: 34 | B40: 45746 | G40: Wi-Fi設定 | I40: 1 | R40: 移動していないのにWi-fiが途切れ、他のWi-fiにつながってしまう。 | V40: 小田勇雄 | W40: =VLOOKUP(V40,名簿!A:L,3,FALSE) -> 技術製造部 | X40: =VLOOKUP(V40,名簿!A:L,4,FALSE) -> 製造課 | Y40: =VLOOKUP(V40,名簿!A:L,5,FALSE) -> 充填包装 | Z40: =VLOOKUP(V40,名簿!A:L,11,FALSE) -> コスメラボラトリー | AA40: =VLOOKUP(V40,名簿!A:L,12,FALSE) -> 2F/事務所
A41: 35 | B41: 45746 | H41: 1 | I41: 1 | R41: サーバーの動作が遅く、切断されがち | V41: 東口智一 | W41: =VLOOKUP(V41,名簿!A:L,3,FALSE) -> 技術製造部 | X41: =VLOOKUP(V41,名簿!A:L,4,FALSE) -> 製造課 | Y41: =VLOOKUP(V41,名簿!A:L,5,FALSE) -> 充填包装 | Z41: =VLOOKUP(V41,名簿!A:L,11,FALSE) -> コスメファクトリー | AA41: =VLOOKUP(V41,名簿!A:L,12,FALSE) -> 2F/充填ライン南
A42: 36 | B42: 45746 | G42: タブレット | H42: 1 | I42: 1 | R42: ネット環境が関係あるか分かりませんが以前からタブレットの動作は常に重いのでそちらも改善できればと思います。 | V42: 東口智一 | W42: =VLOOKUP(V42,名簿!A:L,3,FALSE) -> 技術製造部 | X42: =VLOOKUP(V42,名簿!A:L,4,FALSE) -> 製造課 | Y42: =VLOOKUP(V42,名簿!A:L,5,FALSE) -> 充填包装 | Z42: =VLOOKUP(V42,名簿!A:L,11,FALSE) -> コスメファクトリー | AA42: =VLOOKUP(V42,名簿!A:L,12,FALSE) -> 2F/充填ライン南
A43: 37 | B43: 45746 | D43: 45818 | E43: 1 | H43: 1 | R43: ・サーバーのファンの音が激しい時と静かな時があり、激しい時は重くなっている気がする | T43: サーバ室設置済 | U43: 45944 | V43: 図書杏子 | W43: =VLOOKUP(V43,名簿!A:L,3,FALSE) -> 管理部 | X43: =VLOOKUP(V43,名簿!A:L,4,FALSE) -> 管理課 | Y43: =VLOOKUP(V43,名簿!A:L,5,FALSE) -> - | Z43: =VLOOKUP(V43,名簿!A:L,11,FALSE) -> 本社 | AA43: =VLOOKUP(V43,名簿!A:L,12,FALSE) -> 3F/シンク前
A44: 38 | B44: 45746 | G44: プリンタ既定 | H44: 1 | I44: 1 | R44: ・一定期間作業していない時（昼休みなど）ログイン画面が表示され入るとプリンター指定が解除されて毎回ＰＤＦ指定になる | V44: 図書杏子 | W44: =VLOOKUP(V44,名簿!A:L,3,FALSE) -> 管理部 | X44: =VLOOKUP(V44,名簿!A:L,4,FALSE) -> 管理課 | Y44: =VLOOKUP(V44,名簿!A:L,5,FALSE) -> - | Z44: =VLOOKUP(V44,名簿!A:L,11,FALSE) -> 本社 | AA44: =VLOOKUP(V44,名簿!A:L,12,FALSE) -> 3F/シンク前
A45: 39 | B45: 45746 | G45: デスクトップアイコン | H45: 1 | I45: 1 | R45: ・会計処理をする際、管理部用のノートＰＣでサーバー接続しCSVデータを取り込んでいますが、デスクトップPCに戻りログインするとデスクトップ上のアイコンの配列がバラバラになり少しストレスです | V45: 図書杏子 | W45: =VLOOKUP(V45,名簿!A:L,3,FALSE) -> 管理部 | X45: =VLOOKUP(V45,名簿!A:L,4,FALSE) -> 管理課 | Y45: =VLOOKUP(V45,名簿!A:L,5,FALSE) -> - | Z45: =VLOOKUP(V45,名簿!A:L,11,FALSE) -> 本社 | AA45: =VLOOKUP(V45,名簿!A:L,12,FALSE) -> 3F/シンク前
A46: 40 | B46: 45746 | D46: 45818 | E46: 1 | H46: 1 | R46: ･サーバーの置いてある場所が暖房の風が直接あたっていて熱くなっているのではないかと思います。 | T46: サーバ室設置済 | U46: 45944 | V46: 図書杏子 | W46: =VLOOKUP(V46,名簿!A:L,3,FALSE) -> 管理部 | X46: =VLOOKUP(V46,名簿!A:L,4,FALSE) -> 管理課 | Y46: =VLOOKUP(V46,名簿!A:L,5,FALSE) -> - | Z46: =VLOOKUP(V46,名簿!A:L,11,FALSE) -> 本社 | AA46: =VLOOKUP(V46,名簿!A:L,12,FALSE) -> 3F/シンク前
A47: 41 | B47: 45746 | G47: 共有フォルダ | H47: 1 | I47: 1 | R47: ・毎日最初の一回共有フォルダにはじかれる | V47: 越智絵美子 | W47: =VLOOKUP(V47,名簿!A:L,3,FALSE) -> 管理部 | X47: =VLOOKUP(V47,名簿!A:L,4,FALSE) -> 管理課 | Y47: =VLOOKUP(V47,名簿!A:L,5,FALSE) -> - | Z47: =VLOOKUP(V47,名簿!A:L,11,FALSE) -> 本社 | AA47: =VLOOKUP(V47,名簿!A:L,12,FALSE) -> 3F/シンク前
A48: 42 | B48: 45746 | G48: プリンタ既定 | I48: 1 | R48: ・毎日プリンターを選択する必要がある →既定にできるのは毎日設定 →既定にできないのは都度プリンター選択 | V48: 越智絵美子 | W48: =VLOOKUP(V48,名簿!A:L,3,FALSE) -> 管理部 | X48: =VLOOKUP(V48,名簿!A:L,4,FALSE) -> 管理課 | Y48: =VLOOKUP(V48,名簿!A:L,5,FALSE) -> - | Z48: =VLOOKUP(V48,名簿!A:L,11,FALSE) -> 本社 | AA48: =VLOOKUP(V48,名簿!A:L,12,FALSE) -> 3F/シンク前
A49: 43 | B49: 45746 | G49: プリンタ既定 | I49: 1 | R49: ・印刷するとき用紙設定がカスタムになってるか毎回確認しないといけない | V49: 越智絵美子 | W49: =VLOOKUP(V49,名簿!A:L,3,FALSE) -> 管理部 | X49: =VLOOKUP(V49,名簿!A:L,4,FALSE) -> 管理課 | Y49: =VLOOKUP(V49,名簿!A:L,5,FALSE) -> - | Z49: =VLOOKUP(V49,名簿!A:L,11,FALSE) -> 本社 | AA49: =VLOOKUP(V49,名簿!A:L,12,FALSE) -> 3F/シンク前
A50: 44 | B50: 45746 | G50: テプラ | I50: 1 | J50: 1 | R50: ・テプラの印刷がサーバーでできない ローカルでアプリ？いれても次の日には消える | V50: 越智絵美子 | W50: =VLOOKUP(V50,名簿!A:L,3,FALSE) -> 管理部 | X50: =VLOOKUP(V50,名簿!A:L,4,FALSE) -> 管理課 | Y50: =VLOOKUP(V50,名簿!A:L,5,FALSE) -> - | Z50: =VLOOKUP(V50,名簿!A:L,11,FALSE) -> 本社 | AA50: =VLOOKUP(V50,名簿!A:L,12,FALSE) -> 3F/シンク前
A51: 45 | B51: 45746 | H51: 1 | I51: 1 | R51: ・昔よりは改善されてますがPCが固まったり遅かったりする | V51: 越智絵美子 | W51: =VLOOKUP(V51,名簿!A:L,3,FALSE) -> 管理部 | X51: =VLOOKUP(V51,名簿!A:L,4,FALSE) -> 管理課 | Y51: =VLOOKUP(V51,名簿!A:L,5,FALSE) -> - | Z51: =VLOOKUP(V51,名簿!A:L,11,FALSE) -> 本社 | AA51: =VLOOKUP(V51,名簿!A:L,12,FALSE) -> 3F/シンク前
A52: 46 | B52: 45746 | H52: 1 | I52: 1 | R52: ・事務長がサーバーになかなか入れないときがある | V52: 越智絵美子 | W52: =VLOOKUP(V52,名簿!A:L,3,FALSE) -> 管理部 | X52: =VLOOKUP(V52,名簿!A:L,4,FALSE) -> 管理課 | Y52: =VLOOKUP(V52,名簿!A:L,5,FALSE) -> - | Z52: =VLOOKUP(V52,名簿!A:L,11,FALSE) -> 本社 | AA52: =VLOOKUP(V52,名簿!A:L,12,FALSE) -> 3F/シンク前
A53: 47 | B53: 45746 | G53: ブラウザ | H53: 1 | I53: 1 | R53: ･アマゾンサイトなどへ接続している時、サイト内の動きがとても遅いです。 | V53: 丸中都 | W53: =VLOOKUP(V53,名簿!A:L,3,FALSE) -> 管理部 | X53: =VLOOKUP(V53,名簿!A:L,4,FALSE) -> 管理課 | Y53: =VLOOKUP(V53,名簿!A:L,5,FALSE) -> - | Z53: =VLOOKUP(V53,名簿!A:L,11,FALSE) -> 本社 | AA53: =VLOOKUP(V53,名簿!A:L,12,FALSE) -> 3F/シンク前
A54: 48 | B54: 45746 | H54: 1 | I54: 1 | R54: ･突然サーバーからはじき出される。ログインしなおすと作業途中の画面には戻れます。 | V54: 丸中都 | W54: =VLOOKUP(V54,名簿!A:L,3,FALSE) -> 管理部 | X54: =VLOOKUP(V54,名簿!A:L,4,FALSE) -> 管理課 | Y54: =VLOOKUP(V54,名簿!A:L,5,FALSE) -> - | Z54: =VLOOKUP(V54,名簿!A:L,11,FALSE) -> 本社 | AA54: =VLOOKUP(V54,名簿!A:L,12,FALSE) -> 3F/シンク前
A55: 49 | B55: 45746 | D55: 45818 | E55: 1 | H55: 1 | R55: サーバ本体の設置環境の改善。電圧・換気・空調の効いた鍵付き個室へ設置したい。 | T55: サーバ室設置済 | U55: 45944 | V55: 中土陽介 | W55: =VLOOKUP(V55,名簿!A:L,3,FALSE) -> EC事業部 | X55: =VLOOKUP(V55,名簿!A:L,4,FALSE) -> EC事業課 | Y55: =VLOOKUP(V55,名簿!A:L,5,FALSE) -> - | Z55: =VLOOKUP(V55,名簿!A:L,11,FALSE) -> コスメラボラトリー | AA55: =VLOOKUP(V55,名簿!A:L,12,FALSE) -> 3F/事務所
A56: 50 | B56: 45746 | G56: ブラウザ | H56: 1 | I56: 1 | J56: 1 | R56: ブラウザ処理の負荷に耐えれていない | V56: 中土陽介 | W56: =VLOOKUP(V56,名簿!A:L,3,FALSE) -> EC事業部 | X56: =VLOOKUP(V56,名簿!A:L,4,FALSE) -> EC事業課 | Y56: =VLOOKUP(V56,名簿!A:L,5,FALSE) -> - | Z56: =VLOOKUP(V56,名簿!A:L,11,FALSE) -> コスメラボラトリー | AA56: =VLOOKUP(V56,名簿!A:L,12,FALSE) -> 3F/事務所
A57: 51 | B57: 45746 | I57: 1 | J57: 1 | R57: 接続・描写遅延 | V57: 中土陽介 | W57: =VLOOKUP(V57,名簿!A:L,3,FALSE) -> EC事業部 | X57: =VLOOKUP(V57,名簿!A:L,4,FALSE) -> EC事業課 | Y57: =VLOOKUP(V57,名簿!A:L,5,FALSE) -> - | Z57: =VLOOKUP(V57,名簿!A:L,11,FALSE) -> コスメラボラトリー | AA57: =VLOOKUP(V57,名簿!A:L,12,FALSE) -> 3F/事務所
A58: 52 | B58: 45746 | G58: 共有フォルダ | K58: 1 | P58: 4 | R58: 共有フォルダが複雑 | S58: 中村 | T58: 3/11～構造可視化ツール/検索ツール/データコピーツール作成中 3/23完成 | V58: 中土陽介 | W58: =VLOOKUP(V58,名簿!A:L,3,FALSE) -> EC事業部 | X58: =VLOOKUP(V58,名簿!A:L,4,FALSE) -> EC事業課 | Y58: =VLOOKUP(V58,名簿!A:L,5,FALSE) -> - | Z58: =VLOOKUP(V58,名簿!A:L,11,FALSE) -> コスメラボラトリー | AA58: =VLOOKUP(V58,名簿!A:L,12,FALSE) -> 3F/事務所
A59: 53 | B59: 45746 | G59: バックアップ | K59: 1 | R59: 各部署ローカルバックアップ強化 | V59: 中土陽介 | W59: =VLOOKUP(V59,名簿!A:L,3,FALSE) -> EC事業部 | X59: =VLOOKUP(V59,名簿!A:L,4,FALSE) -> EC事業課 | Y59: =VLOOKUP(V59,名簿!A:L,5,FALSE) -> - | Z59: =VLOOKUP(V59,名簿!A:L,11,FALSE) -> コスメラボラトリー | AA59: =VLOOKUP(V59,名簿!A:L,12,FALSE) -> 3F/事務所
A60: 54 | B60: 45746 | G60: 最適化・高速化 | I60: 1 | K60: 1 | R60: ストレージの最適化 データアクセスの高速化 | V60: 中土陽介 | W60: =VLOOKUP(V60,名簿!A:L,3,FALSE) -> EC事業部 | X60: =VLOOKUP(V60,名簿!A:L,4,FALSE) -> EC事業課 | Y60: =VLOOKUP(V60,名簿!A:L,5,FALSE) -> - | Z60: =VLOOKUP(V60,名簿!A:L,11,FALSE) -> コスメラボラトリー | AA60: =VLOOKUP(V60,名簿!A:L,12,FALSE) -> 3F/事務所
A61: 55 | B61: 45746 | G61: 時間帯 | H61: 1 | I61: 1 | R61: 昼頃・夕方に遅延がする | V61: 大前道仁 | W61: =VLOOKUP(V61,名簿!A:L,3,FALSE) -> EC事業部 | X61: =VLOOKUP(V61,名簿!A:L,4,FALSE) -> EC事業課 | Y61: =VLOOKUP(V61,名簿!A:L,5,FALSE) -> - | Z61: =VLOOKUP(V61,名簿!A:L,11,FALSE) -> コスメラボラトリー | AA61: =VLOOKUP(V61,名簿!A:L,12,FALSE) -> 3F/事務所
A62: 56 | B62: 45746 | G62: ブラウザ | H62: 1 | I62: 1 | J62: 1 | R62: 受注が多い日に受注管理システム（ブラウザ）からデータをDLすると重たい | V62: 大前道仁 | W62: =VLOOKUP(V62,名簿!A:L,3,FALSE) -> EC事業部 | X62: =VLOOKUP(V62,名簿!A:L,4,FALSE) -> EC事業課 | Y62: =VLOOKUP(V62,名簿!A:L,5,FALSE) -> - | Z62: =VLOOKUP(V62,名簿!A:L,11,FALSE) -> コスメラボラトリー | AA62: =VLOOKUP(V62,名簿!A:L,12,FALSE) -> 3F/事務所
A63: 57 | B63: 45746 | G63: Excel | H63: 1 | I63: 1 | J63: 1 | R63: エクセルの操作が固まりやすい | V63: 大前道仁 | W63: =VLOOKUP(V63,名簿!A:L,3,FALSE) -> EC事業部 | X63: =VLOOKUP(V63,名簿!A:L,4,FALSE) -> EC事業課 | Y63: =VLOOKUP(V63,名簿!A:L,5,FALSE) -> - | Z63: =VLOOKUP(V63,名簿!A:L,11,FALSE) -> コスメラボラトリー | AA63: =VLOOKUP(V63,名簿!A:L,12,FALSE) -> 3F/事務所
A64: 58 | B64: 45746 | G64: ブラウザ | H64: 1 | I64: 1 | J64: 1 | R64: ブラウザ上の業務が多い中、固まることで遅延してしまう。 | V64: 酒井絢音 | W64: =VLOOKUP(V64,名簿!A:L,3,FALSE) -> EC事業部 | X64: =VLOOKUP(V64,名簿!A:L,4,FALSE) -> EC事業課 | Y64: =VLOOKUP(V64,名簿!A:L,5,FALSE) -> - | Z64: =VLOOKUP(V64,名簿!A:L,11,FALSE) -> コスメラボラトリー | AA64: =VLOOKUP(V64,名簿!A:L,12,FALSE) -> 3F/事務所
A65: 59 | B65: 45746 | G65: Outlook | H65: 1 | I65: 1 | J65: 1 | R65: ・朝立ち上げ時、アウトルックの起動に5分程かかる | V65: 近藤雅人 | W65: =VLOOKUP(V65,名簿!A:L,3,FALSE) -> 研究開発部 | X65: =VLOOKUP(V65,名簿!A:L,4,FALSE) -> 研究開発課 | Y65: =VLOOKUP(V65,名簿!A:L,5,FALSE) -> - | Z65: =VLOOKUP(V65,名簿!A:L,11,FALSE) -> コスメラボラトリー | AA65: =VLOOKUP(V65,名簿!A:L,12,FALSE) -> 3F/事務所
A66: 60 | B66: 45746 | G66: Excel・Word | H66: 1 | I66: 1 | J66: 1 | R66: ・エクセル・ワードにて、タイピングした内容が反映されるまでのタイムラグがかなりある時がある。 | V66: 近藤雅人 | W66: =VLOOKUP(V66,名簿!A:L,3,FALSE) -> 研究開発部 | X66: =VLOOKUP(V66,名簿!A:L,4,FALSE) -> 研究開発課 | Y66: =VLOOKUP(V66,名簿!A:L,5,FALSE) -> - | Z66: =VLOOKUP(V66,名簿!A:L,11,FALSE) -> コスメラボラトリー | AA66: =VLOOKUP(V66,名簿!A:L,12,FALSE) -> 3F/事務所
A67: 61 | B67: 45746 | H67: 1 | I67: 1 | R67: ・重すぎて、文字が明瞭ではない時がある。ボケてる。 | V67: 近藤雅人 | W67: =VLOOKUP(V67,名簿!A:L,3,FALSE) -> 研究開発部 | X67: =VLOOKUP(V67,名簿!A:L,4,FALSE) -> 研究開発課 | Y67: =VLOOKUP(V67,名簿!A:L,5,FALSE) -> - | Z67: =VLOOKUP(V67,名簿!A:L,11,FALSE) -> コスメラボラトリー | AA67: =VLOOKUP(V67,名簿!A:L,12,FALSE) -> 3F/事務所
A68: 62 | B68: 45746 | G68: Excel | H68: 1 | I68: 1 | J68: 1 | R68: ・一定の手順で必ずエクセルとワードが落ちることがある。 | V68: 近藤雅人 | W68: =VLOOKUP(V68,名簿!A:L,3,FALSE) -> 研究開発部 | X68: =VLOOKUP(V68,名簿!A:L,4,FALSE) -> 研究開発課 | Y68: =VLOOKUP(V68,名簿!A:L,5,FALSE) -> - | Z68: =VLOOKUP(V68,名簿!A:L,11,FALSE) -> コスメラボラトリー | AA68: =VLOOKUP(V68,名簿!A:L,12,FALSE) -> 3F/事務所
A69: 63 | B69: 45746 | G69: メール検索 | I69: 1 | J69: 1 | R69: ・アウトルックの検索が遅い | V69: 近藤雅人 | W69: =VLOOKUP(V69,名簿!A:L,3,FALSE) -> 研究開発部 | X69: =VLOOKUP(V69,名簿!A:L,4,FALSE) -> 研究開発課 | Y69: =VLOOKUP(V69,名簿!A:L,5,FALSE) -> - | Z69: =VLOOKUP(V69,名簿!A:L,11,FALSE) -> コスメラボラトリー | AA69: =VLOOKUP(V69,名簿!A:L,12,FALSE) -> 3F/事務所
A70: 64 | B70: 45746 | H70: 1 | I70: 1 | R70: ・慢性的に動作が遅くてフリーズします。書類（処方、提案書、報告書、成績書、指図書など）作成、メール対応、調査など、本社で作業していた時と比べ、完了するまでの時間が長くなっています。 | V70: 宗近倶枝 | W70: =VLOOKUP(V70,名簿!A:L,3,FALSE) -> 研究開発部 | X70: =VLOOKUP(V70,名簿!A:L,4,FALSE) -> 研究開発課 | Y70: =VLOOKUP(V70,名簿!A:L,5,FALSE) -> - | Z70: =VLOOKUP(V70,名簿!A:L,11,FALSE) -> コスメラボラトリー | AA70: =VLOOKUP(V70,名簿!A:L,12,FALSE) -> 3F/事務所
A71: 65 | B71: 45746 | H71: 1 | I71: 1 | R71: ・コスメは本社に比べ不具合の時間が多いです。 | V71: 宗近倶枝 | W71: =VLOOKUP(V71,名簿!A:L,3,FALSE) -> 研究開発部 | X71: =VLOOKUP(V71,名簿!A:L,4,FALSE) -> 研究開発課 | Y71: =VLOOKUP(V71,名簿!A:L,5,FALSE) -> - | Z71: =VLOOKUP(V71,名簿!A:L,11,FALSE) -> コスメラボラトリー | AA71: =VLOOKUP(V71,名簿!A:L,12,FALSE) -> 3F/事務所
A72: 66 | B72: 45746 | H72: 1 | I72: 1 | R72: ・急に切れる。 | V72: 山下基宏 | W72: =VLOOKUP(V72,名簿!A:L,3,FALSE) -> 研究開発部 | X72: =VLOOKUP(V72,名簿!A:L,4,FALSE) -> 研究開発課 | Y72: =VLOOKUP(V72,名簿!A:L,5,FALSE) -> - | Z72: =VLOOKUP(V72,名簿!A:L,11,FALSE) -> コスメラボラトリー | AA72: =VLOOKUP(V72,名簿!A:L,12,FALSE) -> 3F/事務所
A73: 67 | B73: 45746 | G73: Outlook | H73: 1 | I73: 1 | J73: 1 | R73: ・Outlook使用時に急に落ちる。 | V73: 山下基宏 | W73: =VLOOKUP(V73,名簿!A:L,3,FALSE) -> 研究開発部 | X73: =VLOOKUP(V73,名簿!A:L,4,FALSE) -> 研究開発課 | Y73: =VLOOKUP(V73,名簿!A:L,5,FALSE) -> - | Z73: =VLOOKUP(V73,名簿!A:L,11,FALSE) -> コスメラボラトリー | AA73: =VLOOKUP(V73,名簿!A:L,12,FALSE) -> 3F/事務所
A74: 68 | B74: 45746 | G74: Excel・Word | H74: 1 | I74: 1 | J74: 1 | R74: ・Word、EXcel使用時に急に落ちる。 | V74: 山下基宏 | W74: =VLOOKUP(V74,名簿!A:L,3,FALSE) -> 研究開発部 | X74: =VLOOKUP(V74,名簿!A:L,4,FALSE) -> 研究開発課 | Y74: =VLOOKUP(V74,名簿!A:L,5,FALSE) -> - | Z74: =VLOOKUP(V74,名簿!A:L,11,FALSE) -> コスメラボラトリー | AA74: =VLOOKUP(V74,名簿!A:L,12,FALSE) -> 3F/事務所
A75: 69 | B75: 45746 | H75: 1 | I75: 1 | R75: ・急に止まる。 | V75: 山下基宏 | W75: =VLOOKUP(V75,名簿!A:L,3,FALSE) -> 研究開発部 | X75: =VLOOKUP(V75,名簿!A:L,4,FALSE) -> 研究開発課 | Y75: =VLOOKUP(V75,名簿!A:L,5,FALSE) -> - | Z75: =VLOOKUP(V75,名簿!A:L,11,FALSE) -> コスメラボラトリー | AA75: =VLOOKUP(V75,名簿!A:L,12,FALSE) -> 3F/事務所
A76: 70 | B76: 45746 | H76: 1 | I76: 1 | R76: ・タイピングが遅れて反応。 | V76: 山下基宏 | W76: =VLOOKUP(V76,名簿!A:L,3,FALSE) -> 研究開発部 | X76: =VLOOKUP(V76,名簿!A:L,4,FALSE) -> 研究開発課 | Y76: =VLOOKUP(V76,名簿!A:L,5,FALSE) -> - | Z76: =VLOOKUP(V76,名簿!A:L,11,FALSE) -> コスメラボラトリー | AA76: =VLOOKUP(V76,名簿!A:L,12,FALSE) -> 3F/事務所
A77: 71 | B77: 45746 | H77: 1 | I77: 1 | R77: ・ログインできない。 | V77: 山下基宏 | W77: =VLOOKUP(V77,名簿!A:L,3,FALSE) -> 研究開発部 | X77: =VLOOKUP(V77,名簿!A:L,4,FALSE) -> 研究開発課 | Y77: =VLOOKUP(V77,名簿!A:L,5,FALSE) -> - | Z77: =VLOOKUP(V77,名簿!A:L,11,FALSE) -> コスメラボラトリー | AA77: =VLOOKUP(V77,名簿!A:L,12,FALSE) -> 3F/事務所
A78: 72 | B78: 45746 | H78: 1 | I78: 1 | R78: ・サーバーが重い、遅い。毎日午前9時と午後6時前後は必ず発生。その他の時間帯も突発的に発生。 | V78: 直木美佐子 | W78: =VLOOKUP(V78,名簿!A:L,3,FALSE) -> 研究開発部 | X78: =VLOOKUP(V78,名簿!A:L,4,FALSE) -> 研究開発課 | Y78: =VLOOKUP(V78,名簿!A:L,5,FALSE) -> - | Z78: =VLOOKUP(V78,名簿!A:L,11,FALSE) -> コスメラボラトリー | AA78: =VLOOKUP(V78,名簿!A:L,12,FALSE) -> 3F/事務所
A79: 73 | B79: 45746 | G79: Excel・PDF | H79: 1 | I79: 1 | J79: 1 | R79: ・エクセル、PDF使用時は遅くなりやすい。 | V79: 直木美佐子 | W79: =VLOOKUP(V79,名簿!A:L,3,FALSE) -> 研究開発部 | X79: =VLOOKUP(V79,名簿!A:L,4,FALSE) -> 研究開発課 | Y79: =VLOOKUP(V79,名簿!A:L,5,FALSE) -> - | Z79: =VLOOKUP(V79,名簿!A:L,11,FALSE) -> コスメラボラトリー | AA79: =VLOOKUP(V79,名簿!A:L,12,FALSE) -> 3F/事務所
A80: 74 | B80: 45746 | H80: 1 | I80: 1 | R80: ・サーバーが止まることで打ち損じや誤入力が発生しやすくなっている。電子管理が増える中で、この現象は致命的だと思う。 | V80: 直木美佐子 | W80: =VLOOKUP(V80,名簿!A:L,3,FALSE) -> 研究開発部 | X80: =VLOOKUP(V80,名簿!A:L,4,FALSE) -> 研究開発課 | Y80: =VLOOKUP(V80,名簿!A:L,5,FALSE) -> - | Z80: =VLOOKUP(V80,名簿!A:L,11,FALSE) -> コスメラボラトリー | AA80: =VLOOKUP(V80,名簿!A:L,12,FALSE) -> 3F/事務所
A81: 75 | B81: 45746 | H81: 1 | I81: 1 | R81: ・パソコンが止まることで、進行中の作業が一旦止まる。再開時に誤入力していないか確認することからスタートするので、作業効率が低下。 | V81: 直木美佐子 | W81: =VLOOKUP(V81,名簿!A:L,3,FALSE) -> 研究開発部 | X81: =VLOOKUP(V81,名簿!A:L,4,FALSE) -> 研究開発課 | Y81: =VLOOKUP(V81,名簿!A:L,5,FALSE) -> - | Z81: =VLOOKUP(V81,名簿!A:L,11,FALSE) -> コスメラボラトリー | AA81: =VLOOKUP(V81,名簿!A:L,12,FALSE) -> 3F/事務所
A82: 76 | B82: 45746 | G82: メール振分 | I82: 1 | J82: 1 | R82: ・グループメールが振り分けられないのが困る。 | V82: 直木美佐子 | W82: =VLOOKUP(V82,名簿!A:L,3,FALSE) -> 研究開発部 | X82: =VLOOKUP(V82,名簿!A:L,4,FALSE) -> 研究開発課 | Y82: =VLOOKUP(V82,名簿!A:L,5,FALSE) -> - | Z82: =VLOOKUP(V82,名簿!A:L,11,FALSE) -> コスメラボラトリー | AA82: =VLOOKUP(V82,名簿!A:L,12,FALSE) -> 3F/事務所
A83: 77 | B83: 45746 | H83: 1 | I83: 1 | R83: ・サーバーの動作が重い。 | V83: 津田宝加 | W83: =VLOOKUP(V83,名簿!A:L,3,FALSE) -> 研究開発部 | X83: =VLOOKUP(V83,名簿!A:L,4,FALSE) -> 研究開発課 | Y83: =VLOOKUP(V83,名簿!A:L,5,FALSE) -> - | Z83: =VLOOKUP(V83,名簿!A:L,11,FALSE) -> コスメラボラトリー | AA83: =VLOOKUP(V83,名簿!A:L,12,FALSE) -> 3F/事務所
A84: 78 | B84: 45746 | H84: 1 | I84: 1 | R84: ・Ｂサーバーから突然はじき出される。ログインしなおすと作業途中の画面には戻れる。 | V84: 津田宝加 | W84: =VLOOKUP(V84,名簿!A:L,3,FALSE) -> 研究開発部 | X84: =VLOOKUP(V84,名簿!A:L,4,FALSE) -> 研究開発課 | Y84: =VLOOKUP(V84,名簿!A:L,5,FALSE) -> - | Z84: =VLOOKUP(V84,名簿!A:L,11,FALSE) -> コスメラボラトリー | AA84: =VLOOKUP(V84,名簿!A:L,12,FALSE) -> 3F/事務所
A85: 79 | B85: 45746 | H85: 1 | I85: 1 | R85: ・シンクライアントサーバーの動きが悪く、何度もフリーズする日がある | V85: 矢野恵 | W85: =VLOOKUP(V85,名簿!A:L,3,FALSE) -> 研究開発部 | X85: =VLOOKUP(V85,名簿!A:L,4,FALSE) -> 研究開発課 | Y85: =VLOOKUP(V85,名簿!A:L,5,FALSE) -> - | Z85: =VLOOKUP(V85,名簿!A:L,11,FALSE) -> コスメラボラトリー | AA85: =VLOOKUP(V85,名簿!A:L,12,FALSE) -> 3F/事務所
A86: 80 | B86: 45746 | H86: 1 | I86: 1 | R86: ・動きが悪い日はその状態が一日中続くことが多く、仕事の作業効率が悪くなる（以前に比べると頻度は落ち着いているように感じます…） | V86: 矢野恵 | W86: =VLOOKUP(V86,名簿!A:L,3,FALSE) -> 研究開発部 | X86: =VLOOKUP(V86,名簿!A:L,4,FALSE) -> 研究開発課 | Y86: =VLOOKUP(V86,名簿!A:L,5,FALSE) -> - | Z86: =VLOOKUP(V86,名簿!A:L,11,FALSE) -> コスメラボラトリー | AA86: =VLOOKUP(V86,名簿!A:L,12,FALSE) -> 3F/事務所
A87: 81 | B87: 45746 | H87: 1 | I87: 1 | R87: ・シンクライアントからはじき出されることが数日おきにある | V87: 矢野恵 | W87: =VLOOKUP(V87,名簿!A:L,3,FALSE) -> 研究開発部 | X87: =VLOOKUP(V87,名簿!A:L,4,FALSE) -> 研究開発課 | Y87: =VLOOKUP(V87,名簿!A:L,5,FALSE) -> - | Z87: =VLOOKUP(V87,名簿!A:L,11,FALSE) -> コスメラボラトリー | AA87: =VLOOKUP(V87,名簿!A:L,12,FALSE) -> 3F/事務所
A88: 82 | B88: 45746 | G88: PDF | H88: 1 | I88: 1 | J88: 1 | R88: ・最近PDFの立ち上がりが遅い | V88: 矢野恵 | W88: =VLOOKUP(V88,名簿!A:L,3,FALSE) -> 研究開発部 | X88: =VLOOKUP(V88,名簿!A:L,4,FALSE) -> 研究開発課 | Y88: =VLOOKUP(V88,名簿!A:L,5,FALSE) -> - | Z88: =VLOOKUP(V88,名簿!A:L,11,FALSE) -> コスメラボラトリー | AA88: =VLOOKUP(V88,名簿!A:L,12,FALSE) -> 3F/事務所
A89: 83 | B89: 45746 | G89: メール検索 | H89: 1 | I89: 1 | J89: 1 | R89: ・outlookのメールの検索が遅い | V89: 矢野恵 | W89: =VLOOKUP(V89,名簿!A:L,3,FALSE) -> 研究開発部 | X89: =VLOOKUP(V89,名簿!A:L,4,FALSE) -> 研究開発課 | Y89: =VLOOKUP(V89,名簿!A:L,5,FALSE) -> - | Z89: =VLOOKUP(V89,名簿!A:L,11,FALSE) -> コスメラボラトリー | AA89: =VLOOKUP(V89,名簿!A:L,12,FALSE) -> 3F/事務所
A90: 84 | B90: 45746 | H90: 1 | I90: 1 | R90: ・サーバーが重く、フリーズが多い | V90: 西村穂乃果 | W90: =VLOOKUP(V90,名簿!A:L,3,FALSE) -> 品質保証部 | X90: =VLOOKUP(V90,名簿!A:L,4,FALSE) -> 品質管理課 | Y90: =VLOOKUP(V90,名簿!A:L,5,FALSE) -> - | Z90: =VLOOKUP(V90,名簿!A:L,11,FALSE) -> コスメラボラトリー | AA90: =VLOOKUP(V90,名簿!A:L,12,FALSE) -> 3F/事務所
A91: 85 | B91: 45746 | H91: 1 | I91: 1 | R91: ・ログイン情報が合っているのにサーバーに入れない。（4,5回ログインし直すと入れる） | V91: 西村穂乃果 | W91: =VLOOKUP(V91,名簿!A:L,3,FALSE) -> 品質保証部 | X91: =VLOOKUP(V91,名簿!A:L,4,FALSE) -> 品質管理課 | Y91: =VLOOKUP(V91,名簿!A:L,5,FALSE) -> - | Z91: =VLOOKUP(V91,名簿!A:L,11,FALSE) -> コスメラボラトリー | AA91: =VLOOKUP(V91,名簿!A:L,12,FALSE) -> 3F/事務所
A92: 86 | B92: 45746 | G92: Explorer | H92: 1 | I92: 1 | J92: 1 | R92: ・サーバーに関係あるか分かりませんが、開いている全てのエクスプローラーが勝手に閉じる | V92: 西村穂乃果 | W92: =VLOOKUP(V92,名簿!A:L,3,FALSE) -> 品質保証部 | X92: =VLOOKUP(V92,名簿!A:L,4,FALSE) -> 品質管理課 | Y92: =VLOOKUP(V92,名簿!A:L,5,FALSE) -> - | Z92: =VLOOKUP(V92,名簿!A:L,11,FALSE) -> コスメラボラトリー | AA92: =VLOOKUP(V92,名簿!A:L,12,FALSE) -> 3F/事務所
A93: 87 | B93: 45746 | H93: 1 | I93: 1 | R93: ・サーバーへ入るのに時間がかかる | V93: 橋口千聖 | W93: =VLOOKUP(V93,名簿!A:L,3,FALSE) -> 研究開発部 | X93: =VLOOKUP(V93,名簿!A:L,4,FALSE) -> 研究開発課 | Y93: =VLOOKUP(V93,名簿!A:L,5,FALSE) -> - | Z93: =VLOOKUP(V93,名簿!A:L,11,FALSE) -> コスメラボラトリー | AA93: =VLOOKUP(V93,名簿!A:L,12,FALSE) -> 3F/試験室
A94: 88 | B94: 45746 | H94: 1 | I94: 1 | R94: ・サーバー内で作業中、画面が真っ暗になり強制終了せざるを得ない | V94: 橋口千聖 | W94: =VLOOKUP(V94,名簿!A:L,3,FALSE) -> 研究開発部 | X94: =VLOOKUP(V94,名簿!A:L,4,FALSE) -> 研究開発課 | Y94: =VLOOKUP(V94,名簿!A:L,5,FALSE) -> - | Z94: =VLOOKUP(V94,名簿!A:L,11,FALSE) -> コスメラボラトリー | AA94: =VLOOKUP(V94,名簿!A:L,12,FALSE) -> 3F/試験室
A95: 89 | B95: 45746 | G95: Outlook | H95: 1 | I95: 1 | J95: 1 | R95: ・Outlookの動きが遅い、フリーズする | V95: 橋口千聖 | W95: =VLOOKUP(V95,名簿!A:L,3,FALSE) -> 研究開発部 | X95: =VLOOKUP(V95,名簿!A:L,4,FALSE) -> 研究開発課 | Y95: =VLOOKUP(V95,名簿!A:L,5,FALSE) -> - | Z95: =VLOOKUP(V95,名簿!A:L,11,FALSE) -> コスメラボラトリー | AA95: =VLOOKUP(V95,名簿!A:L,12,FALSE) -> 3F/試験室
A96: 90 | B96: 45746 | G96: Excel | H96: 1 | I96: 1 | J96: 1 | R96: ・Excelの動きが遅い、フリーズして消えることがある | V96: 橋口千聖 | W96: =VLOOKUP(V96,名簿!A:L,3,FALSE) -> 研究開発部 | X96: =VLOOKUP(V96,名簿!A:L,4,FALSE) -> 研究開発課 | Y96: =VLOOKUP(V96,名簿!A:L,5,FALSE) -> - | Z96: =VLOOKUP(V96,名簿!A:L,11,FALSE) -> コスメラボラトリー | AA96: =VLOOKUP(V96,名簿!A:L,12,FALSE) -> 3F/試験室
A97: 91 | B97: 45746 | G97: ブラウザ | H97: 1 | I97: 1 | J97: 1 | R97: ・インターネット検索に時間がかかる、サーバー外でも時間がかかる | V97: 橋口千聖 | W97: =VLOOKUP(V97,名簿!A:L,3,FALSE) -> 研究開発部 | X97: =VLOOKUP(V97,名簿!A:L,4,FALSE) -> 研究開発課 | Y97: =VLOOKUP(V97,名簿!A:L,5,FALSE) -> - | Z97: =VLOOKUP(V97,名簿!A:L,11,FALSE) -> コスメラボラトリー | AA97: =VLOOKUP(V97,名簿!A:L,12,FALSE) -> 3F/試験室
A98: 92 | B98: 45838 | F98: 共有フォルダ | G98: 共有フォルダ | J98: 1 | K98: 1 | P98: 4 | R98: 共有フォルダ整理の具体的な手順や進め方のレクチャー | S98: 中村 | T98: 3/11～構造可視化ツール/検索ツール/データコピーツール作成中 3/23完成 | V98: 鳥山一洋/中島和哉 | W98: 技術製造部 | X98: 生産管理課 | Y98: 生産管理 | Z98: 本社 | AA98: 3F/シンク前
A99: 93 | B99: 45838 | F99: 共有フォルダ | G99: 共有フォルダ | J99: 1 | K99: 1 | P99: 4 | R99: 適切な共有フォルダ運用ルールの作成についてのレクチャー | S99: 中村 | T99: 3/11～構造可視化ツール/検索ツール/データコピーツール作成中 3/23完成 | V99: 鳥山一洋/中島和哉 | W99: 技術製造部 | X99: 生産管理課 | Y99: 生産管理 | Z99: 本社 | AA99: 3F/シンク前
A100: 94 | B100: 45838 | F100: 共有フォルダ | G100: 共有フォルダ | J100: 1 | K100: 1 | P100: 5 | R100: 共有フォルダの5Sの具体的な進め方 | S100: 中村 | T100: 3/11～構造可視化ツール/検索ツール/データコピーツール作成中 3/23完成 | V100: 鳥山一洋 | W100: =VLOOKUP(V100,名簿!A:L,3,FALSE) -> 技術製造部 | X100: =VLOOKUP(V100,名簿!A:L,4,FALSE) -> 生産管理課 | Y100: =VLOOKUP(V100,名簿!A:L,5,FALSE) -> 生産管理 | Z100: =VLOOKUP(V100,名簿!A:L,11,FALSE) -> 本社 | AA100: =VLOOKUP(V100,名簿!A:L,12,FALSE) -> 3F/シンク前
...

Sheet 🔑
F1: Q5.AI・ツール活用 未回答者
K2: 部 | L2: 課 | M2: 係 | N2: 氏名 | O2: 候補者
A3: 氏名 | B3: 部 | C3: 課 | D3: 係 | F3: 部 | G3: 課 | H3: 係 | I3: 個数 / 氏名 | K3: 研究開発部 | L3: 研究開発課 | M3: - | N3: 山下基宏 | O3: 5
A4: 大前道仁 | B4: =VLOOKUP(A4,名簿!A:E,3,FALSE) -> EC事業部 | C4: =VLOOKUP(A4,名簿!A:E,4,FALSE) -> EC事業課 | D4: =VLOOKUP(A4,名簿!A:E,5,FALSE) -> - | F4: 研究開発部 | G4: 研究開発課 | H4: - | I4: 6 | N4: 宗近倶枝 | O4: 5
A5: 小田勇雄 | B5: =VLOOKUP(A5,名簿!A:E,3,FALSE) -> 技術製造部 | C5: =VLOOKUP(A5,名簿!A:E,4,FALSE) -> 製造課 | D5: =VLOOKUP(A5,名簿!A:E,5,FALSE) -> 充填包装 | F5: 品質保証部 | G5: 品質管理課 | H5: - | I5: 1 | O5: 4
A6: 北村優樹 | B6: =VLOOKUP(A6,名簿!A:E,3,FALSE) -> 技術製造部 | C6: =VLOOKUP(A6,名簿!A:E,4,FALSE) -> 生産管理課 | D6: =VLOOKUP(A6,名簿!A:E,5,FALSE) -> 物流 | F6: 技術製造部 | G6: 生産管理課 | H6: 物流 | I6: 2 | N6: 津田宝加 | O6: 4
A7: 近藤雅人 | B7: =VLOOKUP(A7,名簿!A:E,3,FALSE) -> 研究開発部 | C7: =VLOOKUP(A7,名簿!A:E,4,FALSE) -> 研究開発課 | D7: =VLOOKUP(A7,名簿!A:E,5,FALSE) -> - | G7: 製造課 | H7: 充填包装 | I7: 5 | K7: 品質保証部 | L7: 品質管理課 | M7: - | N7: 野村秀太朗 | O7: 4
A8: 田中裕一 | B8: =VLOOKUP(A8,名簿!A:E,3,FALSE) -> 技術製造部 | C8: =VLOOKUP(A8,名簿!A:E,4,FALSE) -> 製造課 | D8: =VLOOKUP(A8,名簿!A:E,5,FALSE) -> 充填包装 | H8: バルク・顆粒 | I8: 1 | K8: EC事業部 | L8: EC事業課 | M8: - | N8: 大前道仁 | O8: 5
A9: 津田宝加 | B9: =VLOOKUP(A9,名簿!A:E,3,FALSE) -> 研究開発部 | C9: =VLOOKUP(A9,名簿!A:E,4,FALSE) -> 研究開発課 | D9: =VLOOKUP(A9,名簿!A:E,5,FALSE) -> - | F9: 企画営業部 | G9: 企画課 | H9: - | I9: 2 | K9: 技術製造部 | L9: - | M9: - | N9: 森山貴史 | O9: 5
A10: 堂山利奈 | B10: =VLOOKUP(A10,名簿!A:E,3,FALSE) -> 企画営業部 | C10: =VLOOKUP(A10,名簿!A:E,4,FALSE) -> 企画課 | D10: =VLOOKUP(A10,名簿!A:E,5,FALSE) -> - | F10: EC事業部 | G10: EC事業課 | H10: - | I10: 1 | L10: 生産管理課 | M10: 生産管理 | N10: 島田智章 | O10: 4
A11: 直木美佐子 | B11: =VLOOKUP(A11,名簿!A:E,3,FALSE) -> 研究開発部 | C11: =VLOOKUP(A11,名簿!A:E,4,FALSE) -> 研究開発課 | D11: =VLOOKUP(A11,名簿!A:E,5,FALSE) -> - | F11: 総計 | I11: 18 | N11: 馬場阿弥子 | O11: 5
A12: 西村穂乃果 | B12: =VLOOKUP(A12,名簿!A:E,3,FALSE) -> 品質保証部 | C12: =VLOOKUP(A12,名簿!A:E,4,FALSE) -> 品質管理課 | D12: =VLOOKUP(A12,名簿!A:E,5,FALSE) -> - | M12: 生産管理事務 | N12: 東香里 | O12: 4
A13: 橋口千聖 | B13: =VLOOKUP(A13,名簿!A:E,3,FALSE) -> 研究開発部 | C13: =VLOOKUP(A13,名簿!A:E,4,FALSE) -> 研究開発課 | D13: =VLOOKUP(A13,名簿!A:E,5,FALSE) -> - | M13: 物流 | N13: 池田悦彰 | O13: 5
A14: 濱西藍伽 | B14: =VLOOKUP(A14,名簿!A:E,3,FALSE) -> 企画営業部 | C14: =VLOOKUP(A14,名簿!A:E,4,FALSE) -> 企画課 | D14: =VLOOKUP(A14,名簿!A:E,5,FALSE) -> - | O14: 4
A15: 藤本洸平 | B15: =VLOOKUP(A15,名簿!A:E,3,FALSE) -> 技術製造部 | C15: =VLOOKUP(A15,名簿!A:E,4,FALSE) -> 製造課 | D15: =VLOOKUP(A15,名簿!A:E,5,FALSE) -> 充填包装 | L15: 製造課 | M15: バルク・顆粒 | N15: 外間裕貴人 | O15: 5
A16: 松山丈弘 | B16: =VLOOKUP(A16,名簿!A:E,3,FALSE) -> 技術製造部 | C16: =VLOOKUP(A16,名簿!A:E,4,FALSE) -> 製造課 | D16: =VLOOKUP(A16,名簿!A:E,5,FALSE) -> 充填包装 | M16: 液体 | N16: 大川泰弘 | O16: 4
A17: 森尾直浩 | B17: =VLOOKUP(A17,名簿!A:E,3,FALSE) -> 技術製造部 | C17: =VLOOKUP(A17,名簿!A:E,4,FALSE) -> 生産管理課 | D17: =VLOOKUP(A17,名簿!A:E,5,FALSE) -> 物流 | M17: 充填包装 | N17: 東口智一 | O17: 5
A18: 矢野恵 | B18: =VLOOKUP(A18,名簿!A:E,3,FALSE) -> 研究開発部 | C18: =VLOOKUP(A18,名簿!A:E,4,FALSE) -> 研究開発課 | D18: =VLOOKUP(A18,名簿!A:E,5,FALSE) -> - | O18: 4
A19: 山下基宏 | B19: =VLOOKUP(A19,名簿!A:E,3,FALSE) -> 研究開発部 | C19: =VLOOKUP(A19,名簿!A:E,4,FALSE) -> 研究開発課 | D19: =VLOOKUP(A19,名簿!A:E,5,FALSE) -> - | M19: 粉体 | N19: 阿部俊樹 | O19: 5
A20: 吉山勝宏 | B20: =VLOOKUP(A20,名簿!A:E,3,FALSE) -> 技術製造部 | C20: =VLOOKUP(A20,名簿!A:E,4,FALSE) -> 製造課 | D20: =VLOOKUP(A20,名簿!A:E,5,FALSE) -> バルク・顆粒 | N20: 内藤恭介 | O20: 4
A21: 小柏拓海 | B21: =VLOOKUP(A21,名簿!A:E,3,FALSE) -> 技術製造部 | C21: =VLOOKUP(A21,名簿!A:E,4,FALSE) -> 製造課 | D21: =VLOOKUP(A21,名簿!A:E,5,FALSE) -> 充填包装 | K21: 管理部 | L21: 管理課 | M21: - | N21: 越智絵美子 | O21: 5
N22: 図書杏子 | O22: 4
K23: 企画営業部 | L23: - | M23: - | N23: 南光彦 | O23: 4
L24: 営業課 | M24: - | N24: 橋本悠司 | O24: 5
N25: 中村剛 | O25: 5
L26: 企画課 | M26: - | N26: 杉尾瑞樹 | O26: 4
K27: 総計

Sheet L
C1: 45838 | G1: 45838 | K1: 45863 | P1: 46073
A3: 期間 | C3: ↓収集した結果から増減 | E3: ヒアリングの視点 | J3: ① | K3: データ管理 | L3: 0 | M3: 無回答・無関心 | O3: 1 | P3: 全く思わない
A4: 短期 | C4: 区分 | E4: 初級 | F4: 実は基本を知らない、知識がないから分からない | J4: ② | K4: 仕組み・ルール | L4: 1 | M4: 気になる | O4: 2 | P4: あまり思わない
A5: 中期 | E5: ↓ | F5: 必ず覚えないといけないこと、今管理者に頼り切りにしていること＝自分で理解できていないこと | J5: ③ | K5: MS365 | L5: 2 | M5: 前向き | O5: 3 | P5: どちらともいえない
A6: 長期 | C6: IT基礎知識 | E6: ↓ | F6: 今の日々の業務で、もっと便利になったら嬉しいこと、変更されると不安なこと | J6: ④ | K6: セキュリティ | O6: 4 | P6: まあまあ思う
C7: 共有フォルダ | E7: 中級 | F7: 具体的な機能/ツールに対して、知りたいこと/活用方法 | J7: ⑤ | K7: ITスキル向上 | O7: 5 | P7: とても思う
C8: MS365(基礎) | J8: ⑥ | K8: その他
C9: MS365(活用)
C10: セキュリティ | F10: ヒアリング イメージ： 今 認識していること →わかりやすい不明点・問題点 →何が起きる？何が必要になる？
H11: ↓後から区分
F12: 初級 | G12: 何も分からないので、何を覚える必要があるのか分からない サーバが重いのは困る、そうならないように個人で守るルールがある？ | H12: IT基礎知識
F13: ↓ | G13: 先ず、今の環境の基礎用語/基本事項から順々に教えてほしい ローカル？サーバ？ 繋がらない・重くなる理由 良いこと・悪いこと | H13: IT基礎知識
F14: 中級 | G14: なぜシンクライアントサーバを使っているのか？ サーバが撤廃されるとどうなるのか？ それぞれの長所・短所 | H14: IT基礎知識
F16: 初級 | G16: 共有フォルダの無駄や重複を減らして、保存・管理する方法 | H16: 共有フォルダ
F17: ↓ | G17: 最初は管理できていても、業務体制が変わったり期間が経つとフォルダの規則性が無くなっていく 長期で維持できるようにするには？ | H17: 共有フォルダ
F18: 中級 | G18: 全部署/全社員が同じ意識やルールで保存したり管理できるようになる方法 上書き/消去/漏洩の回避 マスタデータの保全 | H18: 共有フォルダ
F20: 初級 | G20: 今のOfficeと何が違うのか？ 何が便利になるのか？ 使い方も変わるのか？ | H20: MS365(基礎)
F21: ↓ | G21: クラウドストレージとは？ コミュニティツールとは？ 今のファイルはどうなるのか？ サーバとの違い 便利になること、難しいこと | H21: MS365(基礎)
F22: 中級 | G22: サーバとローカルでどう使う/動作するのか？ ファイル共有・クラウドバックアップとして使う方法 | H22: MS365(基礎)
F24: 初級 | G24: 迷惑メール以外に気をつけること | H24: セキュリティ
F25: ↓ | G25: 具体的にどんな危険があって、どうやって対策するもの？ やってはいけないことは？ | H25: セキュリティ
F26: 中級 | G26: 今 動いているセキュリティ対策は？ 接続できない時はどうすればよいのか？ 個人の誤操作で会社全体に及ぶ危険性とは？ | H26: セキュリティ

Sheet 260220
A1: タイムスタンプ | B1: 部署 | C1: 氏名 | D1: Q1.毎回「ちょっと面倒だな…」と感じる作業はありますか？ 具体的な業務内容やファイル名があれば教えてください （例：毎週の集計作業、同じ内容の繰り返し入力 など） | E1: Q2.ミスが起こりやすい、またはチェックに時間がかかる作業はありますか？ 具体的な業務内容やファイル名があれば教えてください （例：転記作業、数値の照合、複数ファイルの突合 など） | F1: Q3. 工数がかかりすぎている、改善したいと感じる作業はありますか？ 具体的な業務内容やファイル名があれば教えてください （例：手順が多い業務、データ集め、資料作成 など） | G1: Q4. 紙や手書きでやっているが、PC化できたら楽になりそうな作業はありますか？ （例：手書き帳票、紙の申請書、メモからの転記 など） | H1: Q5-1. AIや便利ツールを業務で使ってみたいと思いますか？ 1 = 全く思わない 2 = あまり思わない 3 = どちらともいえない 4 = まあまあ思う 5 = とても思う | I1: Q5-2.使用している(使ったことがある)AIがあれば、名称と用途を教えてください。 | J1: Q6. 業務改善のアイデアや要望があれば自由に記入してください
A2: 46066.558 | B2: 技術製造部 製造課（化粧品） | C2: 森山 貴史 | D2: パートさんの給与時間計算、社員同様にKING OF TIME化できれば負担軽減できる。 | F2: ISO22716取得後の書類作成が多すぎる。特に製造指図書 | G2: 製造指図書、製造記録表等々 包装工程は係長が常にPC入力しており作業負担のため間略化希望する。 | H2: 5 | I2: 溶融充填機設備仕様 冷却設備仕様について
A3: 46066.567 | B3: 技術製造部 生産管理課 | C3: 鳥山 一洋 | D3: ・日/週ルーティンのデータベースからの抽出/加工作業 手動作業が多く、日々時間がかかってしまうため、AIを用いて改善中 ・電話での原料の在庫/入荷/使用予定の問い合わせへの対応 ヒアリングの上、ツールを作成し改善を計画している | E3: ・入荷資材検品 支給資材などで、事前連絡なく微細な改版があるものなど 目視検査では見落としてしまうリスクがある | F3: ・日/週のルーティン作業 Q1の内容と同じです | G3: 自身の作業の中で、手書き業務で負荷の高いものはないため ここに該当する作業はございません | H3: 5 | I3: ・Genspark、ChatGPT どのようなことができるのか、試しに使った程度 ・Claude VBA、SQL、スクリプトなどの作成と修正に日常的に使用 | J3: 全員がAIに興味・関心を持ち、使用するような環境には恐らくならないと思われるが 社内で1名でも多くAIの使い方を知り、活用することで日常業務の細かなことでも 日々改善できるような環境ができれば良いと感じる
A4: 46066.576 | B4: 企画営業部 営業課 | C4: 南 光彦 | D4: クライアント毎のスケジュール表作成・概算コストの試算 | H4: 4
A5: 46066.584 | B5: 技術製造部 生産管理課 | C5: 馬場阿弥子 | D5: バルク・充填製造予定表の更新、定例会議の議事録 | E5: 充填製造予定表で島田主任に作成いただき、そのあと、変更箇所・資材納期状況確認し色付けするなどは、意外に時間をとるため少し手間です。 バルク製造予定表は、バルクの昔からの予定表で確認・転記して、充填日・検査合格日の記載とチェックは大切ですが手間ではあります。 | H5: 5 | J5: ・製品の出荷依頼済の内容を、日付順で受注番号別の一覧化で見れたらなと思います 製造が立て込んだ際やトラブルなどで、出荷依頼が出てるか現場から聞かれたり、 直近の予定変更の対応の場合でも、自分のタイミングで確認ができれば問い合わせも減り、 確認自体も手間が減るので助かります。 また、担当者も出荷依頼したかどうかの確認もしやすいと思います。 ・各製品の入数やパレット積載、納品時のルール、商品または得意先様毎の特記事項などを共有・管理できて、各自のタイミングで見れる場所があれば、担当者変更やトラブルがあっても、基本情報は確認しやすく周囲もフォローしやすいと思います。 新規の取引先・商品、納品先などの場合は、必要情報の登録などは発生しますが、それだけしておけば、毎回受注フォーマット記載も不要にできるのではと思います。 TPICSでできることもあると思いますが、各自のタイミングで確認できるのがポイントで、ログイン権限など気にせず、理想は社外にいてもできるといいなと思います。
A6: 46066.59 | B6: 技術製造部 生産管理課 | C6: 池田悦彰 | D6: アンファー資材の入荷日ごとの入荷記録と入出庫記録用紙の作成・ファイリング→生産管理課が出来る前からの作業。システムで大体把握できる気がするのでデータで管理したい | E6: アンファー製造予定変更時の化粧箱納期間に合っているかの確認 | H6: 5 | I6: ChatGPTでちょっとした疑問やエクセル操作など
A7: 46066.606 | B7: 企画営業部 営業課 | C7: 中村剛 | D7: 定期的な集計作業や、複数のExcel・CSVを扱う作業。 特に、同じ内容を複数ファイルへ入力・転記する工程が当てはまると思います。 | E7: 数値の転記や、複数ファイル間の数値照合作業。 手作業でのチェックが多く、集中力を要するため、負荷がかかっていると思います。 | F7: 定型フォーマットの報告資料作成や、データ収集から集計までの一連の作業。 手順が多く、改善余地があると感じます。 | G7: 経費申請 | H7: 5 | I7: ChatGPT ・画像生成 ・WEBやPythonのコードの改善 Ollama ・ローカル環境でのLLM実行 | J7: 小さな改善を積み重ねることで、現場の負担軽減と品質向上の両立ができると思います。 「少し楽になった」と実感できる事例が増えると、DXも自然に浸透していくと感じます。
A8: 46066.818 | B8: 技術製造部 製造課（食品添加物） | C8: 伊澤浩司 | D8: 経済産業省アルコール使用簿作成、グリセリンドレー手配作業、パソコン等電化製品処分、毎日のグリセリン在庫調べ、アルタン在庫報告、裏の駐輪場他の掃除、製造中の入出荷作業 | E8: 液体製品で別名が複数ある商品 | H8: 3
A9: 46069.722 | B9: 企画営業部 営業課 | C9: 橋本悠司 | D9: 案件依頼書の作成、案件見込共有、出荷判定取次、出荷連絡、契約書チェック | F9: 案件依頼書、案件見込管理、出荷判定取次フロー、出荷連絡フロー、契約書チェック | H9: 5 | I9: Copilot、Gemini、Canva、ChatGPT | J9: 外出や離席が多い業務は極力作業をスマホなどで出来るようにして業務効率を上げたい。 出荷連絡や出荷判定など営業を介さずに直接CLへ連絡する形にして、営業工数や連絡のタイムラグを少なくしたい。 クライアントに提出等が必要な書類関係はスマホからでも閲覧やダウンロードなど出来るようにしたい。 案件を一覧管理（受注、契約書、取り決め書、安定性試験、容器相性試験、支給原料依頼書など）して抜けや漏れを防げるようにしたい。
A10: 46069.727 | B10: 品質保証部 品質管理課 | C10: 井上 幸哉 | D10: 毎月の社員の体温を記録する用紙の作成 （ファイル名：健康管理①就業前検温測定記録 (00000003) 内容：基本的な色付けや社員名は自動化できているが、参照が上手く出来ない部分は手で行っている） 毎週、食添（粉体）の包材の個数をチェックし、必要な物は発注を行う。 （ファイル名：包材在庫管理表 内容：包材（ダンボール、袋、ラベル）の個数をチェックし、必要な物は発注を行う。） | E10: ミス：試験成績書の作成。数値の照合 チェックに時間がかかる：ロート製薬の出荷判定書の作成。転記作業 | F10: 包材管理。在庫がなければ製造ができないのに、在庫管理が全て人力に依存している。 管理品目の多さ。通年を通してマンパワー不足。管理名称と包材などの商品名がイコールではないことが、時間を削っている（工数がかかりすぎている）。 | G10: 包材に限らず、在庫管理にPC化が必要と思う。 できれば、エクセルで引き落としをして、在庫量を印刷 ⇒ 人がチェックして、実数と合わせる ⇒ 不足分は発注する。みたいな流れが取れるといいと思う。 メモからの転記はロートでよくしている。予定がわかっている分は、先に書類を出して欲しい。 | H10: 3 | I10: ない（携帯電話のSiriとか言葉での文字入力は含まれます？） | J10: AIを利用したことがないので、AIが分析をできるのかわからないですが、 食添は、分析値を残せば、安定・不安定な製剤が数値から見えてくる分野だと思います。 下記のエクセルファイルのようなことをしたくても、とっつきにくいようで、理解が得られないのが現状です。 （ファイル名：容器のキャビナンバーごとの重量測定と開栓トルク値の結果） 何とかしたいけど、お金もかけたくないし、情報が流出するリスクは避けたいです。
A11: 46070.369 | B11: 技術製造部 製造課（食品添加物） | C11: 内藤 恭介 | D11: 「月産製造結果表 2026年粉体」日毎と週間の毎月範囲指定する必要がある | E11: 受注商品（在庫品）のロット管理 同一商品を複数の客先に出し、受注順と納期順も異なる | F11: 特に思いつきません。 | G11: 打ち合わせのメモをジャンル毎で整理できれば便利かも。（衛生管理委員、製造会議等） | H11: 4 | I11: ｃｈａｔＧＰＴ | J11: 原料や資材の納期日が一覧で管理できれば便利かも。
A12: 46070.378 | B12: 企画営業部 企画課 | C12: 杉尾 瑞樹 | D12: 現状特にありません | E12: 現状特にありません | F12: 現状特にありません | H12: 4 | I12: chat GPT:調べた情報を文言をまとめるために使用、画像作成等 | J12: 特に今のところ問題なく業務に取り掛かれているかと思います。宜しくお願い致します。
A13: 46070.424 | B13: 技術製造部 生産管理課 | C13: 東香里 | D13: メールを送る際にどういったメーリスが存在し、どなたに配信されるのかいまだに不明です。メールアドレス一覧やメーリス配信先など閲覧しやすくなるとメールを送る際の時短になり送り漏れがなくなると感じます。 メールを送る際に送り先に悩む時間が発生する事がある為まずは一覧が欲しいです。 | E13: 武内製薬様など製品数が多い種類の在庫表の作業を行う際どうしても見落としが出てしまいます。 単純にファイルの問題というよりは製品全てが同じ在庫表の為(笑栄様などは案件毎に在庫表があります)、チェック項目が多くありミス自体は個人的な問題かと思います。ただ、在庫表の中で一番作業時間がかかる業務です。 | F13: 特にありません。 | G13: 特にありません。 | H13: 4 | I13: ChatGPT。無理なお願いをする際などメールの文章に困った際に参考にしていますが仕事上ではほぼ使わずほぼプライベートで使用しています。 | J13: どの部署にどなたがいるのか入れ替わりもありよくわからない為、所属部署・名前・メールアドレスなどが一覧で確認できるようになると助かるなと思います。他部署からこの人どなたですかと聞かれる事もある為、社員一覧(役職)もあると新しい人にも説明しやすいです。もしすでに存在するのであれば公に告知して欲しいです。
A14: 46070.434 | B14: 研究開発部 研究開発課 | C14: 宗近倶枝 | D14: バルク製造指図書の新規発行、原料在庫表と識別表の一元化できていない、バルクの概算原価（原料発注を開発でしなくなったため、生産管理に聞かないと解決できない場合がある） | E14: 案件依頼書は他案件からのコピペで作成していること等があり、案件を取り組む前に指図があっているかのやりとりをする工程が時々ある。案件依頼書は実務する方がやりやすいように改善検討してはどうかと考えます。 | F14: 特になし | G14: 議事録作成 | H14: 5 | I14: 特になし
A15: 46070.628 | B15: 品質保証部 品質管理課 | C15: 野村秀太朗 | D15: 化粧品用資材における検品用サンプルの抜取作業が、本社から第一倉庫まで移動せねばならず不便に感じています。 | E15: 納品予定資材と納品書の照合、資材ケースからの検品用サンプルの抜き取り作業 | F15: 予定資材の照合の際、急な予定変更が行われていると、その正否が確認できない。第一倉庫で抜き取りを行うが作業場が衛生的でないため汚れの混入が心配。 | G15: 納品予定資材と納品書の照合の際の予定表カレンダー。資材抜取の際には端末を使い最新データを確認できるようにしたい。 | H15: 4 | J15: 化粧品の検品用資材の抜取作業について、区画分けしたエリアで行ったほうがよいと思われます。開封した資材ケースにゴミが混入する可能性があります。そして物流担当者の事務作業スペースとあわせてフォークリフトの通り道にあるため接触事故が起こる危険があります。
A16: 46070.743 | B16: 技術製造部 製造課（化粧品） | C16: 外間 裕貴人 | F16: 〇グリセリンを使用するとき、ドラム原料のためエアーで充填できる治具を使用しているのですが、古くなっているせいか出てくる量があまりにも遅いです。多く量を使用するときなどとても時間がかかります。新しいものを購入するなどして改善したいです。 〇常温や冬などに気温が低い状態で保管していると固まる原料があります。使用するときに加温をして溶かさないといけないのですが、加温機に入れるか湯煎をするかで対応しています。現在使用している加温機が一斗缶を最大4缶までしか入れられず、それ以上溶かさないといけない原料がある場合に困っています。大きい加温機を購入するなど改善をしたいです。 〇原料を保管する冷蔵庫もいっぱいになってきており、新しい冷蔵庫を購入するなどして改善したいです。 | G16: 製造したバルクの現品票にメッシュの種類や香料の有無等の記載をするのですが、手書きで書いているものもあり10枚ほど現品票があるときは時間がかかりめんどくさく感じます。それぞれの製品ごとにデータ上で記入し保存したたうえで印刷出来ると楽になると思います。 | H16: 5
A17: 46070.785 | B17: 技術製造部 製造課（化粧品） | C17: 小田晶彦 | D17: ない | E17: 指図書等の書類の確認。 | F17: 無い | G17: 無い | H17: 2 | I17: 無い
A18: 46070.792 | B18: 技術製造部 生産管理課 | C18: 徳永彩花 | D18: 奉行クラウド使用者が生産管理内で4人いるがアカウント数が2しかない。後者が乗っ取り出来るので使用と終了の共有をしているが手間であり、急ぎ発注の時や他人の使用を妨げそうで不便 | E18: 原料発注において堂島実業様納品分を記録する直送予定一覧エクセルの更新漏れが起きやすい。 週1～2回TPiCSとエクセルを参照して変更漏れがないか確認はしているが発注済みの納期変更や数量変更が多くTPiCSの変更のみになっていることがたまにある | F18: 毎週行っている1か月分の危険物保管量の計算。計算自体は足し引きだが使用日とその数量を調べるのに時間がかかる | H18: 3
A19: 46071.349 | B19: 技術製造部 製造課（食品添加物） | C19: 阿部俊樹 | D19: 特にありません | E19: 配合時に指示書と照らし合わせての数量、数字の確認 | F19: 特にありません | G19: 手書きの仮伝票申請 | H19: 5 | I19: 現在使用しているAIはありません
A20: 46071.362 | B20: 技術製造部 製造課（化粧品） | C20: 松井 敬視 | D20: 特になし。 | E20: 特になし。 | F20: 特になし。 | G20: 特になし。 | H20: 3 | J20: 特になし。
A21: 46071.539 | B21: 技術製造部 製造課（食品添加物） | C21: 大川 泰弘 | D21: ファイル名：週末在庫(伊澤入力分)（会長と善鐘取締役に毎週末報告しています） | E21: 特に思い当たりません。 | F21: 現場での手順の多い配合などはこれまで改善もしてきており、今現在工程の多いものは今のところ仕方ないかなと思います。事務仕事では別にありません。 | G21: どちらかというとＰＣは苦手ですので、紙で書いているほうがかえって楽です。 | H21: 2 | I21: 使用したことがありません。 | J21: 今のところ、人員増加ができればと思います。
A22: 46071.587 | B22: 技術製造部 生産管理課 | C22: 中島 和哉 | D22: 業務内容：翌週の分までの包装指図書の進捗状況のリスト更新 理由：各包装指図書について、ひとつずつ状況を確認しているため、手間となっています。 ファイル名：包装製造指図書の進捗状況.xlsx | E22: 業務内容：包装指図書の作成(システムデータ及びExcelやpdfからのデータ転記・確認) 理由：確認する資料が複数あり、入力を間違えていても気付く仕組みができていない為 ファイル名：例 製造指図書／包装 (Rev.03) mamacharmママクリーム＜柑橘＞Amazon仕様300g.xlsx | F22: 業務内容：バルク製造量の計算用データ作成 理由：バルク製造量の計算に必要な情報(最大充填規格値、充填予定数、危険物を考慮した最大バルク製造量、開発担当者、製造予定設備等)を集めるのに時間が掛かる ファイル名：バルク製造量確認依頼(生産管理用).xlsx | G22: ありません | H22: 5 | I22: 使用AI及びAIエージェント：ChatGPT、Genspark 用途：情報収集や図解などの画像生成
A23: 46071.658 | B23: 技術製造部 製造課（化粧品） | C23: 東口智一 | D23: 生産管理システムの実績入力などのNG数や資材ロットの選択などの入力作業。 エラーの頻度が多く都度生産管理の方へ一報いれているが、エラーが出ないように 出来るのであればありがたいです。 | E23: 製造の加工賃を比較する時に、誰が作業していたかを確認するために 毎日撮影しているホワイトボードの人員割り振りの画像と各工程の加工賃を照らし合わせているので、加工賃のページで各工程と作業者がリンクしていれば捗ります。 あと、製造日を記載しといて欲しいです。 | F23: ありません。 | G23: いまのところありません。 | H23: 4 | J23: いまのところありません。
A24: 46071.788 | B24: 技術製造部 製造課（化粧品） | C24: 松下賢 | D24: 現場作業の物理的な問題になりますが、半製品置き場の収容ドラムのピッキング（有香、無香） | E24: 特にありません。 | F24: 特にありません。 | G24: 色々なチェックシート | H24: 2 | I24: ありません。
A25: 46072.424 | B25: 技術製造部 生産管理課 | C25: 島田 智章 | D25: ほぼルーティン業務はないので、特にありません。 | E25: 概算見積もりの作成、確認に多少時間はかかっています。資材メーカーの見積もりをエクセルに詳細打ち込むのと内容あっているかの確認が面倒です。 | F25: Q2と同じ。 | G25: ちょっと違うかもですが議事録関係の作成は、メモして入力するのが手間です。 音声の書き出しをしていくつもりではいます。 | H25: 1 | I25: コパイロット、チャットジーピーティー
A26: 46072.485 | B26: 管理部 管理課 | C26: 越智 | D26: 取引先からの書類を電子保存するとき、個別にアクセスしたり保存法に合わせた名前に変えるときに思います | F26: ・食添の納品書チェック 納品日・仕入先・商品名・数量・金額のリストがあればいいなと思ってます ・経費の請求書チェック 一部は請求書が届いてから発注者を探して内容確認してもらってるのでなんか良い方法ないかなとは思ってます | G26: ＰＤＦや画像をエクセルで加工できたらなと思ったことあります。 特に表などＰＤＦの変換機能やＷｏｒｄ，メモを経由してみましたが画像になってしまい加工できなかったので諦めてました そのときの環境や状況でどうしても手書きになることもあるのでそういう機能があれば教えてほしいです | H26: 5 | I26: ないです | J26: 今回の趣旨とは外れるかもしれませんがすべての現場に放送が届くようになれば良いなと思います 急ぎの電話や用件を伝えられるようにしたいです （携帯などは持込規制がありそうなので）
A27: 46072.514 | B27: 管理部 管理課 | C27: 丸中 都 | D27: ・包装工程作業日報のメール配信。 毎日ファックスで来たものをスキャンしてpdf化しているため、手間に感じることがあります。 ・無料の本での企業調査 95年版のためデータが古く、該当企業が載ってないことが多い。 | E27: 請求金額と入金額の照合。 ネットバンキングで抽出したデータを奉行クラウド内で自動照合できればミスも手間も省けるのではないかと思います。（既に方法があって、自分が知らないだけかもしれませんが） | F27: BeGardenの原価計上 （良い方法がないか現在、思案中です） | H27: 3
A28: 46072.557 | B28: 管理部 管理課 | C28: 図書 杏子 | D28: 「資材入荷状況一覧」を時々使用しますが生産管理部と管理部で共有で使用するファイルのため、どなたかが使用中ですと入力できません。入力できるタイミングをお互いに確認しあわないといけないため少し面倒だなと思います。あと使用していない時にその人が使用している表示が出ることがあります。 | E28: 「コスメファクトリー包装工程作業日報」を出荷送り状のチェックの際にロットナンバーや数量の確認に使用しています。現在コスメから本社へＦＡＸで受信し丸中さんがＰＤＦにしてメールでお送りいただいていますがときどき文字が見えにくい場合がありますのでエクセルなどになれば見やすくなり検索もできるかと思いますが、製造現場での作業の都合もあるかと思いますのでお互いに負担にならない感じで何かいい方法があればいいと思います。 | F28: 特に無いです。 | G28: 特に無いです。 | H28: 4 | I28: 使用したことがないです。

Sheet 要約
A1: ①データ管理
B2: ■ 全体的な課題
C3: 保存場所がバラバラ・ルールが曖昧
D4: 各部署・各個人で保存場所やフォルダ構成が統一されておらず、どれが最新版・正確なデータなのか分からない
D5: 古いデータの整理・削除が進まず、データが増える一方で管理負担が増大
C6: 検索性・見つけやすさの問題
D7: フォルダ階層が深い、命名ルールが曖昧などの理由で検索に時間がかかる
D8: 不要ファイルや似たようなファイルが多く、必要なデータにたどり着きにくい
C9: セキュリティ・データ損失の懸念
D10: ウイルス感染や誤操作によるデータ消失の経験があり、ローカル保存やショートカット管理への不安がある
D11: USBやメールでの持ち出しの容易さがセキュリティリスクになっている
C12: 権限管理と共有体制の不備
D13: 誰でも簡単に編集・削除できる環境であるため、誤操作が起きやすい
D14: フォルダ移動や削除に制限をかけたいという要望あり
D15: 引継ぎが不十分なまま異動・退職があると、重要データが行方不明になる
B16: ■ 部署別の主な意見
C17: 管理部
D18: フォルダ構成が乱雑で、引継ぎや検索に時間がかかる
D19: ローカル保存不可やサーバー障害への不安あり
C20: 技術製造部
D21: 保存先が複雑で、検索性が悪くルールもない
D22: 不要なデータの見極めが困難
C23: 研究開発部
D24: データ持ち出しリスク・誤操作による移動や削除への懸念あり
D25: 整理の時間がとりにくい
C26: 生産管理課
D27: フォルダ階層が深すぎる、命名・運用ルールが未整備
D28: ショートカットの消失経験あり
C29: 直販事業部
D30: 個人管理でバラバラ、最新ファイルの判別が困難
D31: システムでの一元管理が理想
C32: 品質保証部
D33: 旧社名・旧データが混在して検索困難
D34: フォルダ構成が無秩序、部署専用フォルダが必要
D35: 重要データの持ち出しリスクや未使用ファイルの放置が課題
C36: 企画課
D37: 管理方法に対する理解が浅く、バックアップの有無も不明
D38: 過去のデータ消失事例に対する不安あり
B39: ■ まとめ
C40: 各部署共通の課題として「保存場所の統一」「フォルダ構成と命名のルール化」「不要データの整理」
C41: 「アクセス権限の設定」などが浮き彫りに
C42: これらを解決するための全社的なデータ管理ルールの策定と運用体制の整備が急務
C43: (必要に応じて、データベース化やクラウド型システムへの移行も検討)
A45: ②仕組み・ルール化
B46: ■ 全体的な課題
C47: 全社的・部署単位でのフォルダ構成や整理ルールの明確化が求められている
C48: 更新履歴の管理、ファイル名ルールの設定、セキュリティ対策、権限管理の整備なども強く希望されている
C49: 運用の属人化（個人プレー）を避け、全社員で統一したルールで運用したいという声が多い
B50: ■ 部署別の主な意見
C51: 管理部
D52: フォルダの共有ルールの整備が必要
D53: 削除や上書きミスの防止のため、セキュリティ対策を導入したい
D54: 部署内での共有ルールの策定を希望
C55: 企画課
D56: 整理ルール、フォルダ構成、更新履歴管理の明確化を希望
C57: 技術製造部
D58: 過去の不要なファイルの削除やまとめを希望
D59: 部署や全社単位でのルール決定を望む
D60: 共有フォルダは部門長の許可制にしたい
D61: 他部署からのアクセス制限やフォルダの分別も求められている
C62: 研究開発部
D63: ISO関連文書の更新管理やファイルの命名規則を希望
D64: マニュアルの整備が求められている
C65: 生産管理課
D66: 条件別のフォルダ構成パターン化を提案 誰と共有するかによる保存場所ルールの明確化が必要
D67: 1年以上更新されていないファイルの整理・移動システムを希望
D68: クライアント名・読み方共有などの命名ルールの統一も必要
C70: 直販事業部
D71: 部署単位の共通フォルダルールを作りたい
D72: 上書き防止、編集者の記録が可能な仕組みを導入したい
D73: シンプルなフォルダ構成と役職別の権限管理を希望
C74: 品質保証部
D75: ルール作成の必要性を認識しているが、簡便で手間のない運用を希望
D76: 似た名前のファイル・フォルダが多く、命名ルールの標準化と整理が必要
D77: データの蓄積だけでなく分析活用の仕組みも希望
D78: 新規ソフト導入手順のルール化も求めている
B79: ■ まとめ
C80: 全社的な「フォルダ構成ガイドライン」や「ファイル管理ルールブック」の策定が必要
A82: ③MS365
B83: ■ 全体的な課題
C84: MS365に対する理解不足・不安
D85: 多くの部門でMS365の基本的な使い方が分からず、不安を感じている
D86: 特に技術製造部・研究開発部・生産管理課などは「何ができるのか分からない」「まずは使ってみたい」との声
D87: マニュアルやガイドラインの整備が必要
C88: ネット環境の影響
D89: オフライン環境下での利用可否、動作不安定への懸念（管理部、研究開発部、企画課など）
C90: OneDrive / SharePointの使い分け
D91: 保存先の基準や使い方の違いが分からず、統一ルールが必要（直販事業部、生産管理課など）
C92: ファイル操作・管理に関する疑問
D93: 削除ファイルの復元可否（営業課）
D94: 編集履歴の確認方法（営業課）
D95: データ保存期間やセキュリティ、共同編集時の権限管理（複数部署）
C96: 共同編集やリンク共有機能
D97: 未経験者が多く、基礎的な操作を学ぶ機会が求められている（直販事業部、生産管理課など）
D98: Googleスプレッドシートとの違いに関する疑問もあり（品質保証部）
C99: サポートとライセンス管理
D100: ツールが個人でバラバラに使われることによる混乱や、ライセンスの違いによる支障を懸念（管理部）
C101: セキュリティ・権限管理
D102: データ持ち出し防止、不要な書き込みの制限などへの関心（研究開発部）
C103: 教育・支援の必要性
...

Sheet 集計P
A1: 0無回答・無関心 1気になる 2前向き
A3: ①データ管理 | B3: 部署名 | C3: データの個数 / ①データ管理 | E3: ②仕組み・ルール | F3: 部署名 | G3: データの個数 / ②仕組み・ルール | I3: ③MS365 | J3: 部署名 | K3: データの個数 / ③MS365 | M3: ④セキュリティ | N3: 部署名 | O3: データの個数 / ④セキュリティ | Q3: ⑤ITスキル向上 | R3: 部署名 | S3: データの個数 / ⑤ITスキル向上 | U3: ⑥その他 | V3: 部署名 | W3: データの個数 / ⑥その他
A4: 2 | B4: 管理部 | C4: 3 | E4: 2 | F4: 管理部 | G4: 2 | I4: 2 | J4: 営業課 | K4: 1 | M4: 2 | N4: 営業課 | O4: 1 | Q4: 2 | R4: 営業課 | S4: 2 | U4: 2 | V4: 営業課 | W4: 2
B5: 技術製造部 | C5: 6 | F5: 企画課 | G5: 1 | J5: 管理部 | K5: 3 | N5: 管理部 | O5: 2 | R5: 管理部 | S5: 2 | V5: 管理部 | W5: 2
B6: 研究開発部 | C6: 3 | F6: 技術製造部 | G6: 6 | J6: 企画課 | K6: 1 | N6: 企画課 | O6: 2 | R6: 企画課 | S6: 1 | V6: 技術製造部 | W6: 1
B7: 生産管理課 | C7: 5 | F7: 研究開発部 | G7: 3 | J7: 技術製造部 | K7: 2 | N7: 技術製造部 | O7: 1 | R7: 技術製造部 | S7: 7 | V7: 研究開発部 | W7: 1
B8: 直販事業部 | C8: 2 | F8: 生産管理課 | G8: 7 | J8: 研究開発部 | K8: 2 | N8: 研究開発部 | O8: 4 | R8: 研究開発部 | S8: 2 | V8: 生産管理課 | W8: 3
B9: 品質保証部 | C9: 5 | F9: 直販事業部 | G9: 1 | J9: 生産管理課 | K9: 4 | N9: 生産管理課 | O9: 5 | R9: 生産管理課 | S9: 7 | V9: 直販事業部 | W9: 1
A10: 2 集計 | C10: 24 | D10: =C10/45 -> 0.53333333 | F10: 品質保証部 | G10: 3 | J10: 直販事業部 | K10: 2 | N10: 直販事業部 | O10: 2 | R10: 直販事業部 | S10: 1 | V10: 品質保証部 | W10: 1
A11: 1 | B11: 企画課 | C11: 2 | E11: 2 集計 | G11: 23 | H11: =G11/45 -> 0.51111111 | J11: 品質保証部 | K11: 1 | N11: 品質保証部 | O11: 1 | R11: 品質保証部 | S11: 4 | U11: 2 集計 | W11: 11 | X11: =W11/45 -> 0.24444444
B12: 技術製造部 | C12: 4 | E12: 1 | F12: 企画課 | G12: 1 | I12: 2 集計 | K12: 16 | L12: =K12/45 -> 0.35555556 | M12: 2 集計 | O12: 18 | P12: =O12/45 -> 0.4 | Q12: 2 集計 | S12: 26 | T12: =S12/45 -> 0.57777778 | U12: 1 | V12: 技術製造部 | W12: 8
B13: 研究開発部 | C13: 2 | F13: 技術製造部 | G13: 3 | I13: 1 | J13: 企画課 | K13: 1 | M13: 1 | N13: 管理部 | O13: 1 | Q13: 1 | R13: 管理部 | S13: 1 | V13: 研究開発部 | W13: 2
B14: 生産管理課 | C14: 1 | F14: 研究開発部 | G14: 1 | J14: 技術製造部 | K14: 6 | M14: 1 集計 | O14: 1 | P14: =O14/45 -> 0.022222222 | R14: 企画課 | S14: 1 | V14: 生産管理課 | W14: 2
A15: 1 集計 | C15: 9 | D15: =C15/45 -> 0.2 | F15: 直販事業部 | G15: 1 | J15: 研究開発部 | K15: 2 | M15: 0 | N15: 営業課 | O15: 3 | R15: 技術製造部 | S15: 3 | U15: 1 集計 | W15: 12 | X15: =W15/45 -> 0.26666667
A16: 0 | B16: 営業課 | C16: 4 | E16: 1 集計 | G16: 6 | H16: =G16/45 -> 0.13333333 | J16: 生産管理課 | K16: 3 | N16: 技術製造部 | O16: 13 | R16: 研究開発部 | S16: 3 | U16: 0 | V16: 営業課 | W16: 2
B17: 技術製造部 | C17: 4 | E17: 0 | F17: 営業課 | G17: 4 | I17: 1 集計 | K17: 12 | L17: =K17/45 -> 0.26666667 | N17: 研究開発部 | O17: 2 | R17: 生産管理課 | S17: 1 | V17: 管理部 | W17: 1
B18: 研究開発部 | C18: 1 | F18: 管理部 | G18: 1 | I18: 0 | J18: 営業課 | K18: 3 | N18: 生産管理課 | O18: 3 | R18: 直販事業部 | S18: 1 | V18: 企画課 | W18: 2
B19: 生産管理課 | C19: 2 | F19: 技術製造部 | G19: 5 | J19: 技術製造部 | K19: 6 | N19: 直販事業部 | O19: 1 | Q19: 1 集計 | S19: 10 | T19: =S19/45 -> 0.22222222 | V19: 技術製造部 | W19: 5
B20: 直販事業部 | C20: 1 | F20: 研究開発部 | G20: 2 | J20: 研究開発部 | K20: 2 | N20: 品質保証部 | O20: 4 | Q20: 0 | R20: 営業課 | S20: 2 | V20: 研究開発部 | W20: 3
A21: 0 集計 | C21: 12 | D21: =C21/45 -> 0.26666667 | F21: 生産管理課 | G21: 1 | J21: 生産管理課 | K21: 1 | M21: 0 集計 | O21: 26 | P21: =O21/45 -> 0.57777778 | R21: 技術製造部 | S21: 4 | V21: 生産管理課 | W21: 3
A22: 総計 | C22: 45 | F22: 直販事業部 | G22: 1 | J22: 直販事業部 | K22: 1 | M22: 総計 | O22: 45 | R22: 研究開発部 | S22: 1 | V22: 直販事業部 | W22: 2
F23: 品質保証部 | G23: 2 | J23: 品質保証部 | K23: 4 | R23: 直販事業部 | S23: 1 | V23: 品質保証部 | W23: 4
E24: 0 集計 | G24: 16 | H24: =G24/45 -> 0.35555556 | I24: 0 集計 | K24: 17 | L24: =K24/45 -> 0.37777778 | R24: 品質保証部 | S24: 1 | U24: 0 集計 | W24: 22 | X24: =W24/45 -> 0.48888889
E25: 総計 | G25: 45 | I25: 総計 | K25: 45 | Q25: 0 集計 | S25: 9 | T25: =S25/45 -> 0.2 | U25: 総計 | W25: 45
Q26: 総計 | S26: 45

Sheet 250725
A1: No | B1: 拠点 | C1: 部署名 | D1: 回答者名 | E1: ① 今、部署で「データ管理や保管」で困っていることや不安なことは何ですか？ 例：どのファイルが最新かわからない、勝手に消される、保存場所がバラバラなど | F1: ①データ管理 | G1: ② 部署やチームで責任を持って管理するために「こんな仕組み・ルールがほしい」という希望はありますか？ 例：整理のルール、フォルダ構成、更新履歴の管理など | H1: ②仕組み・ルール | I1: ③ MS365を使う上で「よくわからないこと」「不安なこと」「こんなサポートがほしい」ということはありますか？ 例：OneDrive/SharePointの使い分け、共同編集、権限管理など | J1: ③MS365 | K1: ④ セキュリティ面で「心配なこと」「もっと知りたいこと」はありますか？ 例：パスワード管理、ウイルス対策、情報漏洩、アクセス権限の設定など | L1: ④セキュリティ | M1: ⑤ 部署でITスキルを上げるために「こういうサポートや研修があればいい」という希望はありますか？ 例：操作マニュアルがほしい、実演で教えてほしい、質問しやすい環境など | N1: ⑤ITスキル向上 | O1: ⑥ その他、自由に意見・要望があればご記入ください （例：小さいことでも何でもOKです） | P1: ⑥その他
A2: 1 | B2: CFCL | C2: 研究開発部 | D2: 津田宝加 | E2: 特になし | F2: 0 | G2: 特になし（整理のルールなどは開発内のルールで不便を感じたことはありません） | H2: 0 | I2: どれも使ったことがないので、とりあえず使ってみたいと思っています。 | J2: 1 | K2: 特になし | L2: 0 | M2: 操作マニュアルがあればありがたいです。 | N2: 2 | P2: 0
A3: 2 | B3: CFCL | C3: 品質保証部 | D3: 近藤雅人 | E3: 原料資料等、添付ファイルが重いものがアウトルックに残っているがなかなか消せない。共通サーバーにアップするようにルール化しているが、一部守れていない社員がいる。処方や製造指図書のような重要ファイルが持ち出せる状況になっている。 | F3: 2 | G3: ルールは作りたいですが、社員が逸脱することの方が多いので、なるべく手間のない仕組みを希望します。 | H3: 2 | I3: ないです。 | J3: 0 | K3: パスワード管理、ウイルス対策、情報漏洩 | L3: 2 | M3: 実演で教えていただきたいです。 | N3: 2 | P3: 0
A4: 3 | B4: CFCL | C4: 直販事業部 | D4: 大前 | E4: 部署内では特にありませんが、受注～製造までをエクセル管理ではなくシステムなどで一元管理になるのが理想だと思っています | F4: 2 | G4: 整理のルール | H4: 1 | I4: 共同編集について詳しく知りたい。スプレッドシートとどう違うか | J4: 2 | K4: ウイルス対策 | L4: 2 | M4: 中土主任を通さずにそれぞれがITサポートを受けられる環境 | N4: 1 | O4: チャットワークも人によって有料、無料プランのバラツキがあるので、Microsoft 365で同じチャットツールが使えるのは良いと思います。 | P4: 2
A5: 4 | B5: CFCL | C5: 技術製造部 | D5: 松山丈弘 | E5: 発注書や見積書の保管が個人でバラバラで管理出来ていない。 | F5: 1 | G5: 保存場所の統一化や業者毎のフォルダ分け | H5: 2 | J5: 0 | L5: 0 | N5: 0 | O5: 現場で使用しているパソコンのスペックが良くないので固まったり再接続の回数が多く作業に時間を要している。 | P5: 1
A6: 5 | B6: CFCL | C6: 直販事業部 | D6: 酒井絢音 | E6: 特になし | F6: 0 | G6: 特になし | H6: 0 | I6: 特になし | J6: 0 | K6: 特になし | L6: 0 | M6: 特になし | N6: 0 | O6: 業務が１人作業のため使いづらい等の意見が出ませんでした。何卒よろしくお願いいたします。 | P6: 0
A7: 6 | B7: CFCL | C7: 技術製造部 | D7: 藤本洸平 | E7: 保存場所がバラバラ | F7: 1 | G7: なし | H7: 0 | I7: なし | J7: 0 | K7: なし | L7: 0 | M7: 社内、取引先へのメールマナーがわからない。 | N7: 1 | O7: パソコン本体が重たい。 | P7: 1
A8: 7 | B8: CFCL | C8: 技術製造部 | D8: 田中裕一 | E8: 何がどこにあって、どれが最新か分からない・分かりづらい。 | F8: 1 | H8: 0 | I8: 使い方がExcelしか分かりません。 | J8: 1 | L8: 0 | N8: 0 | P8: 0
A9: 8 | B9: CFCL | C9: 技術製造部 | D9: 東口智一 | E9: 主に06コスメファクトリー(08Ｑ美共有も）フォルダを使用しているが、ファイルの保存場所に明確なルールが無く探すのに時間がかかり、検索しても重く見つからない場合がある。 | F9: 2 | G9: どのようなルールが適しているかわからないのでインフィニティさんにサポートしてもらいたい。過去の使用していないファイル、データなどもまとめるか、削除したい。 | H9: 2 | I9: Microsoft 365 公式サイトを確認したが、いまいちピンとこない。現場に常駐しているのでデスクワークが少ないが、理解して使いこなせられるようにはなりたい。 | J9: 2 | K9: ここ最近AppleやＳＢＩ証券を名乗る迷惑メールがくることがあり、無視しているが 来ないように出来ないか。 | L9: 0 | M9: マニュアルがあれば空き時間や、家でも確認できるので欲しい。 ＩＴ関係の知識が全くないので基礎的な内容から研修して頂きたいです。 | N9: 2 | O9: ＩＴ関係の知識がないのでこれを機に向上出来る機会にしたいので、研修などには 参加していきたい。 | P9: 2
A10: 9 | B10: CFCL | C10: 技術製造部 | D10: 小田勇雄 | E10: 保存場所が統一されておらず、各自保管しているものもあり皆が共有できていない。不必要なフォルダもあるので削除したい | F10: 2 | G10: 整理のルールがあれば教えて欲しいです。 | H10: 1 | I10: MS365自体がよくわからないです。すみません。 | J10: 1 | K10: PCのデスクトップ上で保管してしまっているので、正式な保管場所や方法を教えて欲しい。 | L10: 2 | M10: PCの操作マニュアル、表作成、計算式など基本的なことを教えてもらえる場があれば助かります。 | N10: 2 | P10: 0
A11: 10 | B11: CFCL | C11: 技術製造部 | D11: 小田晶彦 | E11: 特になし | F11: 0 | G11: ﾊﾞﾙｸﾒﾝﾊﾞｰだけ使えるフォルダがあればよい。整理などは少しづつしている。 | H11: 2 | I11: MS365自体よく知らない | J11: 1 | K11: 迷惑メールがよく来るので来ないようにしてほしい。削除がめんどくさい。 | L11: 0 | M11: 製造中になるので実演や研修は製造日程を考えないといけないので難しい。質問ができすぐに答えてくれる人がいてくれると助かる。 | N11: 1 | O11: 現状問題なのは製造中空いた時間にパソコン作業する際フリーズや動作が遅くなるのが一番不便を感じる。TPIXも動作が鈍い時があるので改善してほしい。 どんなふうに変わるのか分からないので、フォルダやデータ管理を個々で管理していきましょうと言われても、変わることによってどういう事をしていいか分からない。 なので色々と質問されても分からないので、後々こうしたいとかは出てくる。 | P11: 1
A12: 11 | B12: CFCL | C12: 技術製造部 | D12: 阿部俊樹 | E12: 今のところありません。 | F12: 0 | G12: まだ思いつきません。 | H12: 0 | I12: 特にありません。 | J12: 0 | K12: 特にありません。 | L12: 0 | M12: 操作マニュアルが欲しいです。 | N12: 2 | P12: 0
A13: 12 | B13: CFCL | C13: 品質保証部 | D13: 西村 | E13: 使用していないファイルがたくさんあり、必要なファイルやデータが探しづらい | F13: 2 | G13: 特にありません | H13: 0 | I13: 特にありません | J13: 0 | K13: 特にありません | L13: 0 | M13: 特にありません | N13: 0 | O13: 特にありません | P13: 0
A14: 13 | B14: CFCL | C14: 技術製造部 | D14: 外間裕貴人 | E14: 特になし | F14: 0 | G14: 特になし | H14: 0 | I14: 分かりません | J14: 0 | K14: 最近迷惑メールが来るようになっているので出来ればなくしたいです。 | L14: 0 | M14: 特になし | N14: 0 | O14: 軽いフリーズをすることが結構あるので回線がもっといい環境になれば嬉しいです。 | P14: 1
A15: 14 | B15: CFCL | C15: 研究開発部 | D15: 矢野恵 | E15: 共有フォルダ内のフォルダの移動・削除に権限を設けてほしい（パソコンの動きが遅かったり、手元が少し狂ったりで自分の意思に反して簡単にフォルダが移動されてしまうため） | F15: 2 | H15: 0 | J15: 0 | K15: 急な休みを取らなければいけない時などに遠隔でシンクライアントにログイン出来たら便利だと感じるが、セキュリティ上難しいのか。 | L15: 2 | M15: Excelのマクロの組み方?を教えてほしい（処方を組んだら、自動的に全成分表が出来上がる仕組みが欲しい） | N15: 2 | P15: 0
A16: 15 | B16: CFCL | C16: 技術製造部 | D16: 松井敬視 | E16: 特になし | F16: 0 | G16: 特になし | H16: 0 | I16: 特になし | J16: 0 | K16: 特になし | L16: 0 | M16: 特になし | N16: 0 | O16: プレDXによってサーバー内がどのように変わるのか知りたいと思います。 | P16: 1
A17: 16 | B17: CFCL | C17: 技術製造部 | D17: 松下賢 | E17: どこに技術製造部のフォルダがあるのか知らず、まだ活用まで至っていない為、不安点は特にありません。 | F17: 1 | G17: 他部署が触れないようにする。 | H17: 2 | I17: 使用してから色々要望が生まれるかもわかりませんが現時点ではありません。 | J17: 1 | K17: 特にありません。 | L17: 0 | M17: シンコーでの作業内容で必要なスキルについては、部署ごとに集まって実演で教育してほしいです。 OneDrive（個人用クラウドストレージ）、SharePoint（チーム用共有フォルダ） Teams（チャット・会議）等 | N17: 2 | O17: 回線が遅い（フリーズが多い）気がするので少しでもスムーズになってほしいと思います。 | P17: 1
A18: 17 | B18: CFCL | C18: 品質保証部 | D18: 寺石歩実 | E18: お客様が会社名を変更された際、データを探すのに時間がかかります。最新の会社名で登録されているものもあれば昔の会社名のまま保管されているデータもあり、戸惑うことがあります。 | F18: 2 | H18: 0 | J18: 0 | L18: 0 | M18: いつでも見れる操作マニュアルがあればうれしいです。 | N18: 2 | P18: 0
A19: 18 | B19: CFCL | C19: 研究開発部 | D19: 山下基宏 | E19: データ管理、保管で困ることはございません。エクセルが固まってデータが消えるぐらいです。 | F19: 1 | G19: 更新履歴の管理 | H19: 2 | I19: 権限管理、セキュリティーの強化（他者による処方などの書き込み、操作をやめる。データ持ち出しさせない。） | J19: 2 | K19: 情報漏洩。処方、指図書をUSB等、外部メディアで持ち出しされる。 | L19: 2 | M19: 質問しやすい環境 | N19: 1 | O19: 簡易になればうれしいです。 | P19: 1
A20: 19 | B20: CFCL | C20: 研究開発部 | D20: 直木美佐子 | E20: USBやメールでデータの持ち出しが簡単にできてしまうことが不安です。 | F20: 2 | G20: ISOに関わる書類で、REV.が更新された時のファイルの取り扱い（別ファイルにするのかどうか） | H20: 2 | I20: 現段階でMS365がどんなものかがわからないので、特にありません。 | J20: 1 | K20: ウイルス対策、情報漏洩 | L20: 2 | M20: わからなくなった時にすぐに質問できる環境があると嬉しいです。 | N20: 1 | O20: 全体的にITスキルが上がり、個人差が少しでも埋まれば、もう少しスムーズな運用が可能になるのかな、と思ったりすることがあります。 | P20: 2
A21: 20 | B21: CFCL | C21: 研究開発部 | D21: 橋口千聖 | E21: 慣れるまでファイルの保管場所が分からなくなることが多かった | F21: 1 | G21: マニュアルがない | H21: 1 | J21: 0 | L21: 0 | N21: 0 | P21: 0
A22: 21 | B22: CFCL | C22: 研究開発部 | D22: 宗近倶枝 | E22: 不要なデータを削除するなど仕分けや整理の時間がとりにくいです。 | F22: 2 | G22: 書類名の付け方のルールも希望します。 | H22: 2 | I22: クラウド上の操作はネット環境の調子が良くない時も問題ないかどうかは気になります。 | J22: 2 | K22: パスワード管理、アクセス権限 | L22: 2 | M22: 質問しやすい環境はほしいです。 | N22: 1 | O22: 操作が複雑にならない、工程が増えないことが希望です。 | P22: 1
A23: 22 | B23: CFCL | C23: 直販事業部 | D23: 中土陽介 | E23: ファイルの保存先や管理方法が人によってバラバラになっている。 どれが最新ファイルか分からなくなることがあり、特に複数人で作業する時に不安を感じる。 また、退職や異動があると引き継ぎ漏れで大事なデータが見つからないケースもある。 | F23: 2 | G23: 部署単位での共通フォルダ構成ルールを決めて整理をしたい。 更新履歴や編集者が分かる仕組みを使って、上書きミスや「誰が変えたか分からない問題」を減らしたい。 権限管理を部署ごと・役職ごとに明確にしたいが、シンプルなフォルダ構成と権限にしたい。 | H23: 2 | I23: OneDriveとSharePointの使い分けがまだ曖昧で、どこに何を保存すればいいのか標準ルールがほしい。 共同編集やリンク共有を使ったことがないメンバーが多いため、基本操作を部署内で学べる機会が必要だと思う。 | J23: 2 | K23: 外部へのメール送信やデータ共有で情報漏えいしないか不安だが、情報漏えいすると雇用契約上 個人へのリスクがあることを周知したい。 社外からのアクセスやウイルス感染リスクなど、何をどう防げるのか社員全体で意識を高める必要を感じる。 | L23: 2 | M23: MS365の基本操作（OneDrive、SharePoint、Teamsなど）を実演ベースで学ぶ研修がほしい。 部署内で聞けるように少人数での勉強会も検討したい。 また、IT用語が難しいく感じるので、初心者でも理解できる資料やマニュアルを用意してほしい。 | N23: 2 | P23: 0
A24: 23 | B24: 本社 | C24: 生産管理課 | D24: 馬場阿弥子 | E24: 保存場所の把握に困るのと、送付側受け取り側でデータを各自データ保存のため、最新版が把握しずらくなる（クライアント様との共有資料等）・エクセル等のデータ開きっぱなしで使用できない 等 | F24: 2 | G24: 現在も部署や課のフォルダはあるが、使用ルールが不明で、生産管理の名前のフォルダでも、他部署と共有で使用するフォルダだったり、誰と使ってるのかわからないし、似た名前で複数存在したら混乱する 誰と共有すべきデータか（課内？自分だけ？全体？）、共有しないのか等で、保存場所をルール化できたら、少し整理がつくのかなと感じます。 | H24: 2 | I24: 従来のフォルダ運用と、OneDriveとの使い分けは不安 共同編集、権限管理は誰がどこまで制限できたり、クライアント様との共有なども可能か知りたい | J24: 2 | K24: 迷惑メールが一定数あったり、必要なメールがSPAM認定されてるので、エラーとかで届かない等にならないかは気になる | L24: 2 | M24: 各部署でどこまでを管理範囲するのか、そのためにどんなITスキルが必要なのかを先ず教えて欲しいです。 範囲が見えたことで、理解不足の度合いが具体的になると思うので、質問もしやすくなると思います。 現時点では求められてることがわかってないので、質問することが難しいです。 | N24: 2 | O24: 今すぐでなぐの要望ではないですが、会社を大きくしていきたい。していく。という前提の上で、 常駐でなくて外部委託でもいいと思うので、先ず情報システム部の専任が欲しいです。 会社が大きくなれば、インフラやシステム保守は今後重要度は増すので、兼任では厳しいタイミングが来ると思うのと、サーバリプレイスで、クラウド等もうまく利用して仕事しやすい環境を目指す上で、社員や顧客の個人情報や、クライアント様が絡むような情報漏洩（イベント、商品企画・発売やコラボ情報等）を防ぐ環境作りを希望します。 | P24: 2
A25: 24 | B25: 本社 | C25: 技術製造部 | D25: 池田悦彰 | E25: どこに何が保管されているのか、ツリー図のようなものがあれば良い気がしました。 | F25: 2 | G25: 全社としてのルール、部署としてのルール、両方もしくはいずれかを決めればそれに沿えば良いのでわかりやすいです。 | H25: 2 | I25: 知識が無いためマニュアルが欲しいです。 | J25: 1 | L25: 0 | M25: 一度社内説明会のようなものがあれば嬉しい気がしました。後は覚えるためにも極力マニュアルで各個人がやってみて、行きづまってから相談するようにした方が良いと感じます。 | N25: 2 | P25: 0
A26: 25 | B26: 本社 | C26: 生産管理課 | D26: 鳥山一洋 | E26: 不要なファイル、フォルダ、ショートカット等が散見される状態 要不要分からず、誰も手をつけることができていない 似たようなフォルダ、ファイルなども見受けられ、無駄なデータが多い | F26: 2 | G26: フォルダ作成のルール作り 個々での運用に任せきりになっており、収集がつかないので 全社員統一のルールを設定し、無駄を省く 1年以上更新されていないファイルなど抽出し、不要フォルダへ移すようなシステム | H26: 2 | I26: 全く知見が無いので、基本の使い方～応用まで教えていただきたい 大畑様が仰っていた、社内コミュニケーションツールとしての活用方法をレクチャーいただきたい | J26: 2 | K26: 社内でのセキュリティ意識、知識の維持向上のためのトレーニング方法 弊社にあったセキュリティ導入の範囲を知りたい Lanscopeを使った具体的な管理方法 PCやAPなどに社内機器ではないものを接続できてしまうため それをシャットアウトできるようなセキュリティ | L26: 2 | M26: 全体的な知識の底上げの研修 ・クライアントPCからサーバーに接続してサーバー内でPC業務を行っているなどの基礎知識 サーバーに負荷をかけない日常業務の進め方の研修 ・メールに極力データを添付しない、Excelなど重くならないやり方など | N26: 2 | O26: 専門的な内容多く、とっつきにくい印象をもたれがちではあるものの サーバーは全員が使用しており、サーバーに接続しないとPC業務が行えないので 全員最低限の知識と、決められた運用守りより良いサーバー環境での業務ができるよう意識をもって取り組んでいきたいと思います | P26: 2
A27: 26 | B27: 本社 | C27: 生産管理課 | D27: 徳永彩花 | E27: 同じ案件でも名前がバラバラで複数あったりrejectしきれていない。クライアント名が変わった際変更しきれていなかったり一部だけが変わっていたりする。 | F27: 2 | G27: 見積保管などフォルダ作成時クライアント名、製品名の頭文字読み方を入れているが新規は読み方が共有されず字面からの予測でしか作れていないのでローマ字の新規案件は読み方を教えてほしい。 | H27: 2 | I27: やってみないとわからないのでわからないがマニュアルやルールは明確にしてほしい。 | J27: 2 | K27: 最近迷惑メールが来る頻度が増えている。 | L27: 0 | M27: マニュアルが欲しい。そのうえで質問しやすい環境がほしい。 | N27: 2 | O27: 定期的にパソコンのフリーズがあるので安定してほしい。 工程が複雑にならず、ダブった作業は増えないでほしい。 簡易になれば嬉しい。 | P27: 1
A28: 27 | B28: 本社 | C28: 生産管理課 | D28: 中島和哉 | E28: ・ファイルの階層が多い為、探しにくい(多くても5階層までが理想) ・ファイル名に対して保管されているデータ名がマッチしないものがある ・フォルダ名に変更が必要となる場合のルールが決まっていない為、例えばクライアントに変更があった場合に、旧フォルダ名を残したままにし新たなフォルダを作成するのか、対象のフォルダの名称を直接変更するのかなど対応方法が明確になっていない ・不要なデータらしきものが結構ある | F28: 2 | G28: ・フォルダ構成のルールがほしい(階層単位での一律ルール化は使いにくい可能性がある為、条件別のフォルダ構成のパターン化) 年月日で区別する必要のない場合、1階層目(部署)、2階層目(業務内容)、3階層目(対象ファイル)など 年度別でのデータがある場合、1階層目(部署)、2階層目(業務内容)、3階層目(年度)、4階層目(対象ファイル)など 月日別でのデータがある場合、1階層目(部署)、2階層目(業務内容)、3階層目(年度)、4～5階層目(月別、日別の対象ファイル)など クライアント毎のデータがある場合、1階層目(部署)、2階層目(業務内容)、3階層目(クライアントの頭文字)、4階層目(クライアント)、5階層目(対象データ)など | H28: 2 | I28: ・MS365のExcel(クラウド版)の基本操作 ・OneDriveやSharePointの基本操作及び使い分け | J28: 2 | K28: 具体的なNG行為とNG行為を行った場合にどのようなリスクがあるのか 事例を用いた詳細が知りたいです。 | L28: 2 | M28: ・MS365の基本操作の実演と初心者でもわかりやすいマニュアルがほしいです | N28: 2 | P28: 0
A29: 28 | B29: 本社 | C29: 技術製造部 | D29: 内藤恭介 | E29: 保存場所がバラバラで整理されていない為、探しにくい。昔のデータは不要か判断できない為、追加する一方で増え続けていることも原因と思われる。整理できれば要領の負担軽減につながると思う。 | F29: 2 | G29: 今は誰でも新規ファイル、フォルダををつくれるが、共有のフォルダは各長が許可した場合のみ追加できるようにし、その他は個人ファイルにとどめた方が良い。 | H29: 2 | I29: 特になし | J29: 0 | K29: 特になし | L29: 0 | M29: 製造の新入社員はエクセル、ワードのスキルがない人が多い。上司が直接教える以外のサポート環境があれば有難い。 | N29: 2 | O29: 迷惑メールが増えている。今でもフリーズすることがある。 | P29: 1
A30: 29 | B30: 本社 | C30: 生産管理課 | D30: 島田智章 | E30: 部署内では特になし。 | F30: 0 | G30: 更新履歴の管理。 | H30: 2 | I30: 調べてもピンとこなかったのですが、使ってみたいです。 | J30: 1 | K30: ウイルス対策と迷惑メールはなくしてほしい | L30: 2 | M30: 質問しやすい環境と操作マニュアルは欲しい | N30: 2 | O30: ルールなど決まった際はみんながきちんとルール通りにしていけることを希望です | P30: 2
A31: 30 | B31: 本社 | C31: 生産管理課 | D31: 東香里 | E31: 見積書の保管管理でショートカットを作成し管理を行っていたがウイルス騒動時に全てショートカットが外れてしまった事があった為、また突然消えるのではと不安を感じる。 | F31: 2 | G31: 企画で使用していたフォルダを生産管理(一部で)でも使用している為、保管場所の統一を行いたい。 | H31: 2 | I31: 社内で使用についてルール化すると思われる為現時点での不安は特になし。 | J31: 1 | K31: 毎日迷惑メールが来る。(2～3件) | L31: 0 | M31: 気になる事があればどこの何へ質問をすれば良いか窓口が明確にあると助かる。 | N31: 1 | O31: ウイルス騒動以降ずっとメールの振り分けがおかしい(全体の設定？をやりなおすと聞いていたが何も始まらず、振り分けを一から設定しなおすべきか知りたい)。メールタイトルに「～が次の人の代理で送信しました」というのが出ないようにして欲しい。デスクトップのアイコンが頻度は低いがシャッフルされてしまう現象を止めて欲しい。 | P31: 1
A32: 31 | B32: 本社 | C32: 企画課 | D32: 濱西藍伽 | E32: 何をどう管理したらいいか分からない | F32: 1 | G32: 整理のルール | H32: 1 | I32: 使い分け、使い方 | J32: 1 | K32: アクセス権限、パスワード管理 | L32: 2 | M32: 操作マニュアル | N32: 2 | O32: 特にございません。 | P32: 0
A33: 32 | B33: 本社 | C33: 企画課 | D33: 杉尾瑞樹 | E33: 入社したばかりなので現在は問題なく進めれています。 昔にパソコンが飛びデータが消えたという話を聞いたのでバックアップなどは一応あるのか知っておきたいです。 | F33: 1 | G33: 整理のルール、フォルダ構成、更新履歴の管理が明確にあれば助かります。 | H33: 2 | I33: OneDriveの接続環境(前職で使用した際に接続がうまくいかないパソコンがあったため) | J33: 2 | K33: パスワード管理について(今後MS３６５で使用する場合各自のパスワードになるのか、現在自身のoutlockなどパスワードを知らないため) | L33: 2 | M33: 質問しやすい環境があれば嬉しいです。 | N33: 1 | P33: 0
A34: 33 | B34: 本社 | C34: 品質保証部 | D34: 野村秀太朗 | E34: ネット発注等の関係で新規ソフトのインストールを行いたいが、現状のシステムでは困難なこと | F34: 2 | G34: 新規ソフトのインストールを行うための手順をルール化し明確にしてほしい | H34: 2 | J34: 0 | K34: 迷惑メールが多量に届くためブロックする方法や対策について相談を行いたい | L34: 0 | M34: 社内のネットワーク関連について質問できる、担当者や部署を定めてほしい | N34: 2 | P34: 0
A35: 34 | B35: 本社 | C35: 管理部 | D35: 丸中都 | E35: フォルダの種類が多く保存場所も統一されてないので、検索するのに時間が要する。 同じようなデータが点在してるので、どれが正しいデータなのか不明である。 | F35: 2 | G35: 他部署と共有で使用してるフォルダもあるので、全体的なルールが必要かと思われる。 | H35: 2 | I35: ネット環境次第で動作が左右されるのかが気になる。 | J35: 2 | K35: ウイルス対策が強化されるのか心配。 | L35: 2 | M35: MS365をネットで調べるだけでは知識が身につかないので、実務ベースでの研修をしていただきたい。パソコン用語が難しいので理解できるような資料もほしい。 | N35: 2 | O35: 特になし。 | P35: 0
A36: 35 | B36: 本社 | C36: 管理部 | D36: 図書杏子 | E36: 管理部内でも個人別で保存場所や保存方法がバラバラなので部署内共有フォルダを整理し誰が見ても分かりやすく引継ぎなどスムーズに行えるようにしたい。しかし誰でも簡単にアクセスできる環境になると不注意で削除や書き換えしてしまう心配もある。 | F36: 2 | G36: 部署内の他の人のフォルダを把握したいが削除上書きのミスが心配なので何かセキュリティーあると安心です。現状個人プレーで保管管理しているので部署内でルールを決めて共有したい。 | H36: 2 | I36: MS365はインターネット回線が繋がらなくなった場合仕事がストップしてしうか不安です。必要最小限のファイルをローカルに保管できるとありがたいです。 | J36: 2 | K36: 今まで通り管理部のフォルダは他部署からアクセスできない設定にしていただきたいです。 | L36: 2 | M36: ＩＴに疎いので分からない時に気軽に確認できるコールセンターやチャット相談などがあれば嬉しいです。 | N36: 1 | O36: ネットへアクセスできない時の日々の業務が滞ることが心配なので最悪の場合、電話・ＦＡＸ・手書き伝票で対応出来るようにローカルで作業できる保険があると安心です。 | P36: 2
A37: 36 | B37: 本社 | C37: 管理部 | D37: 越智絵美子 | E37: 共有フォルダとは別にデスクトップにも保存してますが、前サーバーが感染した時消えました。私のPCはローカルにも保存できないので少し不安です | F37: 2 | G37: 特にありません | H37: 0 | I37: MS365をどう使うか理解できてなく申し訳ないのですが、ツールが増えて各個人が好きなように使いだすと確認作業が増えて見逃しが起こらないか気になります。使用者によって有料・無料の区別があると認識がずれたり、受けれるサポートが違ったりしないかどうか、データの保存に制限があるのかでしょうか。ずれてる話だったらすみません | J37: 2 | K37: こうした方がよいとかあれば教えてほしいです | L37: 1 | M37: いつでも質問できる環境があると嬉しいです。Chatなどでもありがたいですが伝わりにくかったり説明に時間がかかるので電話でも繋がるとさらに嬉しいです | N37: 2 | O37: 電子化が進んでるので今より電子データの容量が増えるのが心配です。ネットが繋がらなかったときに予備の回線というか別回線が使えたらなーと思います。すみません。 | P37: 2
A38: 37 | B38: 本社 | C38: 生産管理課 | D38: 北村 | E38: 特になし | F38: 0 | G38: 特になし | H38: 0 | I38: 実際に触ってみないと何とも言えない | J38: 1 | K38: 特になし | L38: 0 | M38: 操作マニュアルがあれば非常にありがたいです | N38: 2 | O38: 特になし | P38: 0
A39: 38 | B39: 本社 | C39: 技術製造部 | D39: 大川泰弘 | E39: 必要なファイルと不必要なファイルがどれなのか考えるときがあります | F39: 2 | G39: パソコン自体がくわしくありませんので、どうしたらいいのかがわかりません。 | H39: 1 | I39: まずMS３６５を詳しく理解したいです。 | J39: 2 | K39: 特にありません。 | L39: 0 | M39: 例であげていただいてるように実演や勉強会のようなもので教えてほしい。 | N39: 2 | O39: 特にはありません。 | P39: 0
A40: 39 | B40: 本社 | C40: 技術製造部 | D40: 伊澤浩司 | E40: ファイルの保存先が複雑である。製造で必要な情報が製造用以外にある。 | F40: 2 | G40: パソコンが得意では無いので希望がぱっと浮かびませんが、出来るだけ簡単にして欲しいです。 | H40: 1 | I40: 日々製造がメインで事務所にいる人と違いパソコンは夕方にしか使用しません。よってMS365が何かもわかりませんので不安だらけです。 | J40: 1 | K40: 迷惑メール(野村證券、アマゾン等)よく来ます。 | L40: 0 | M40: 液体製造は人員が不足の為、日々製造で手一杯です。夕方にパソコンを使用するのでわからない事があれば電話ですぐに対応して欲しい。 | N40: 1 | O40: 管理のリーダーはパソコンが強い人が行った方が良いと思います。 | P40: 1
A41: 40 | B41: 本社 | C41: 生産管理課 | D41: 森尾直浩 | E41: 保存場所がバラバラで検索に苦労する | F41: 1 | G41: 更新履歴の管理 | H41: 2 | J41: 0 | K41: ウイルス対策 | L41: 2 | M41: 操作マニュアルが欲しい | N41: 2 | P41: 0
A42: 41 | B42: 本社 | C42: 品質保証部 | D42: 井上幸哉 | E42: データがどこにあるか分からない。 たぶん昔と今で作業者や作業部署が違うので、点在していることが原因だと思う。 平たく言うとフォルダ構成が無茶苦茶 品保のフォルダを作って欲しい。 食添とコスメの品保のフォルダを分けて欲しい。 各自が自由に使えるフォルダが欲しい （スキャンフォルダの感じ） デバイス（プリンタ―）が多いので、「どれ？」になる。 ない分は削除して欲しい。全部あるならごめんなさい。 記録しているデータの目的と実際（データ加工）に必要としている内容が合ってない 食添の試験成績書の作成関係の基準があいまい過ぎて困っている。 台帳は、商品名⇒出荷先で検索すると見つけやすいが、試験成績書は商品名と出荷先名が並列であるので探すことが難しい（慣れはした）。 | F42: 2 | G42: 似た名称のフォルダやファイルが多く「どれ？」になる。 規格書も「自社FM」と「他社FM」と「食添の購入原料の規格書」「コスメの購入原料の規格書」 のように複数ありそれぞれ点在している。 出来れば、発行した規格書、SDS、試験成績書系と、購入原料の規格書で分けて欲しい 「01食添_規格書_自社FM_250708_第1版.xlsx」のような分けかたをしたい。 品目マスタ的なもの 品目コードと絡めて書類を作る習慣化 食添の製造が在庫管理をどうしているか存じませんが、注文がきた⇒入力⇒製品在庫のチェック⇒予定在庫から引く⇒足りない場合は製造するので、原材料のチェック⇒原材料の発注⇒入荷したら原材料のチェック⇒・・・ 人の手をかけすぎているように思う。 入力までしたら、何とかして欲しい。 データを蓄積するのはいいが、分析や解析ができていない。簡単に出来たらいい。 | H42: 2 | I42: MSのOneDriveなど使い方を知らない。 昔、Googleのスプレッドシートを使ったことはあるが、いまいちしっくりこなかった記憶がある。 MSがサービスを止めるってなった時、どうします？ | J42: 2 | L42: 0 | M42: エクセルのVBAを教えて欲しい（独学の限界を感じてます）。 | N42: 2 | O42: シンクライアントを使わないなら、PCのスペックを上げて欲しい。 （ラベル屋さん的なアプリを使うことがあるのですが、GPUとかって高い方がいいですか？） サーバーに付随して思ったことですが、 当社のHPに、規格書やSDSを載せれる物だけ載せれば、問い合わせ対応が減ると思う（営業や付随部署の負担軽減目的）。 調味料製剤のご要望承ります。みたいな物があればいいと思う（売上アップ目的）。 | P42: 2
A43: 42 | B43: 東京 | C43: 営業課 | D43: 南光彦 | F43: 0 | H43: 0 | J43: 0 | L43: 0 | N43: 0 | O43: 商談時や移動時にVPN接続をしなければ共有フォルダなど見られず、よりクイックにスマホやPCから閲覧・操作をしたい。 新幹線移動が多く、電波が悪い時にローカルで作業できそれがサーバーと紐づけると良い。 スマホである程度のメールチェックなどしたいが、全て入ると量が多すぎて困る。現在チャットなどは保存機能を活用。 メールもアプリで管理できると。。 | P43: 2
A44: 43 | B44: 東京 | C44: 営業課 | D44: 橋本悠司 | F44: 0 | H44: 0 | J44: 0 | K44: サーバーやアプリに繋がらないなどの時の簡易トラブル対処マニュアル作成 | L44: 2 | M44: IT、セキュリティー、MS365などのリテラシーを高める勉強会 | N44: 2 | O44: サーバーや回線等による作業待ち時間を減らしたい スマホから資料を作成、確認、送付できるようにしたい（見積書、発注書、試作概要書、受注フォーマット、裏面原稿、仕様書、製造予定、倉庫在庫、営業資料etc...） 売上、粗利、数量などの予実を極力リアルタイムで共有、把握できるようにしたい。 案件全体の進捗状況を一覧でタスク化（把握、確認）したい。（試作、原価、見積、安定性試験、容器相性試験、受注、契約書締結、校正、資材納期、製造予定、出荷etc...） メールやcahtの連絡時間を省略したい（保存や更新をしたら共有者へ自動通知など） 生成AIなどで試作概要書や提案書を自動作成したい 必要な情報をすぐに見つけられるようにしたい（例：ワークフローからその資料へアクセスなど） ワークフローを誰でもすぐに確認して実行できるようにしたい（ISOの手順書のような紙ベースでは、手順通りの実行が難しいと感じる） 売上機会損失を減らしたい（納品から一定期間が空いたら担当営業へ自動通知など） 日報が属人的な内容にならないようメール以外の簡単な方法で見やすくしたい 気づきや改善要望は日報ではなく別の共有方法にしたい | P44: 2
A45: 44 | B45: 東京 | C45: 営業課 | D45: 堀真紀 | F45: 0 | H45: 0 | J45: 0 | L45: 0 | M45: PCに負荷がかかる動作についてしっかり理解できていないため、教わりたいです。ゴミ箱を定期的に空にするなど、心がけることや、どういった動作で負荷をかけてしまっているのか、教えていただきたいです。 | N45: 2 | P45: 0
A46: 45 | B46: 東京 | C46: 営業課 | D46: 野田健治 | F46: 0 | H46: 0 | I46: ファイルを間違って削除したとき、元に戻せるのか。→自分で復元できるのか、誰かに頼まないといけないのか知りたいです。 メールやファイルって、どれくらいの期間保存されるのか。→必要な情報が消えてしまわないか不安です。 誰がどのファイルを編集したのか、あとから確認できる？→使うときに「上書き」が怖いので、履歴の見方を知りたいです。 | J46: 2 | L46: 0 | N46: 0 | P46: 0

Sheet 250630
A1: 45838
A2: 区分 | B2: 内容 | C2: 部 | D2: 課 | E2: 名前
A3: 共有フォルダ | B3: 共有フォルダ整理の具体的な手順や進め方のレクチャー | C3: 技術製造部 | D3: 生産管理課 | E3: 中島・鳥山
A4: 共有フォルダ | B4: 適切な共有フォルダ運用ルールの作成についてのレクチャー | C4: 技術製造部 | D4: 生産管理課 | E4: 中島・鳥山
A5: 共有フォルダ | B5: 共有フォルダの5Sの具体的な進め方 | C5: 技術製造部 | D5: 生産管理課 | E5: 鳥山
A6: 共有フォルダ | B6: 可視化ツール導入における管理について 具体的にどのようなことが可能で、どう管理を行うことができるのか | C6: 技術製造部 | D6: 生産管理課 | E6: 鳥山
A7: 共有フォルダ | B7: 製造予定等、関係者が共通の認識を持つ必要があるデータは、メールで周知だと見落としもあるため、指定フォルダや、スプレットシート（ＭＳ版のやつで）みたいに、「各自が見に行く形」を希望です。 「更新しました」連絡だけメールで貰えれば、全員が同じデータを閲覧しながら、話す環境が出来るやすいかなと思います。 | C7: 技術製造部 | D7: 生産管理課 | E7: 馬場
A8: MS365(基礎) | B8: 各機能と使い方の基本～応用のレクチャー | C8: 技術製造部 | D8: 生産管理課 | E8: 中島・鳥山
A9: MS365(基礎) | B9: 社内コミュニケーションツールとしての活用方法詳細 大畑様が仰られていたところの詳細な内容を教えていただきたい | C9: 技術製造部 | D9: 生産管理課 | E9: 鳥山
A10: MS365(基礎) | B10: 基本OJTが欲しいです。マニュアルだけだと、導入しても一部機能しか使わない気がします | C10: 技術製造部 | D10: 生産管理課 | E10: 馬場
A11: セキュリティ | B11: 利用者のトレーニング方法詳細 トレーニングの内容や頻度など教えていただきたい | C11: 技術製造部 | D11: 生産管理課 | E11: 中島・鳥山
A12: セキュリティ | B12: 各セキュリティの導入範囲のご相談 それぞれのセキュリティの内容教えていただき 弊社にとっての最適なセキュリティの導入をしたい | C12: 技術製造部 | D12: 生産管理課 | E12: 鳥山
A13: セキュリティ | B13: Lanscopeを使った具体的な管理方法 | C13: 技術製造部 | D13: 生産管理課 | E13: 鳥山
... A35: MS365(基礎) | B35: 誰がどのファイルを編集したのか、あとから確認できる？ → 使うときに「上書き」が怖いので、履歴の見方を知りたいです。 | C35: 企画営業部 | D35: 営業課 | E35: 野田

Sheet 250330
A2: 徳永さん | B2: ・サーバーのフリーズが多い、ローカルのSkype立ち上がりなど少し遅い印象
B3: ・定期的にハイパーリンクがリンクしなくなる。
B4: ・定期的にデスクトップのアイコン位置シャッフルされる
A6: 東さん | B6: ・たまにハイパーリンクが死亡する(どういった場合かは不明。突然発生する)
B7: ・PDFの文字化け(最近落ち着いた気がしますが…)
B8: ・概ねPDFが重い気がします
B9: ・天気が悪いとPCの動きが鈍い
A11: 東さん＆徳永さん | B11: ・受注時に「クライアント名」「製品名」に読み仮名をつけるようにして欲しい。
B12: 様々の物をフォルダ分けする際に名前が不明な事が多く困る為。
A14: 中島くん | B14: ・ローカル、サーバー共にフリーズが多い
B15: ・パソコンの起動が遅く、シンクラの接続にも時間が掛かる
B16: 電源入～デスクトップの画面表示まで約3分30秒
B17: Aサーバー接続アイコン選択～シンクラ画面まで約2分30秒
B18: ・ローカルのブラウザやSkypeの起動が遅い(1～3分くらい掛かる)
B19: ・複数のデータを見ながら処理を進めることが多いので、デュアルモニターだと作業効率が上がりそうです
A21: 池田くん | B21: ・Bサーバー基本的に重い
B22: ・ハンディの動作反応が年々遅くなっている
B23: →データ蓄積されているため？
A25: 馬場さん | B25: ・メールの検索がしにくく困ってます
B26: これはOutlookだからなのか、Gmailだと変わるのはわかりません
B27: ・エクセルのハイパーリンクはバグりやすいです
B28: ・デュアルモニターの対応ができてデータを並べられたら、効率は上がる可能性あります。
B29: 例えば、製造予定とTPCIS等を並べて確認や、充填バルクの製造予定並べて見れたら、
B30: 画面が広分確認はしやすいです。
B31: ・サーバーのフリーズが多い
B32: ・Rグループが重いのとSkypeも終わるタイミングで、チャットやweb会議、スケジュール管理を、
B33: Microsoft系かGoogle系にまとめられたら、各自予定の登録や確認がしやすいかなと思います。
A35: 島田主任 | B35: ・メールの検索がしにくく困る。
B36: ・ローカルのブラウザやSkypeの起動が遅い(1～3分くらい掛かる)
B37: ・パソコンの起動が遅く、シンクラの接続にも時間が掛かる(中島くんと同等の所要時間)
B38: ※島田主任と中島くんのPCスペックは同等です
B39: ・メーリングリストで受信したbouncesのせい？でメールの振り分けが僕には対応できなくなってます。
A41: 北村リーダー | B41: ・シンクラサーバーの動作が全体的に重い。（シンクラが原因なのか、PC自体が古いからなのかは分からないです）
B42: ・フリーズが頻発する。
B43: ↑社員のパソコン使用が集中する時間帯（主に9時頃、18時頃）は特に多く、長くフリーズする。
A45: 小田係長 | B45: ・サーバーにつながりにくい（特に朝９時ぐらい）
B46: ・ネットの環境か分からないが、現品票の発行（印刷）に
B47: 時間がかかる。
B48: ・朝の９時以外でもメールやTPiCS・PI-naviが遅い時がある。
B49: 時間は見てないです。あきらめて製造に戻る時もあります。
B50: ・要望はパソコンはスムーズに使いたい。
B51: 製造してる合間に打ち込んだりメール見ることが
B52: あるので、ネットがつながらないとかあると、作業効率が悪いです。
A54: 内藤主任 | B54: 私的には以前に容量削減の対策をやってからフリーズすることがかなり改善したように思います。
B55: ただ大川リーダー、伊澤Ｌは今でも動作が重たくなる時はあるとのことです。
B56: あと製造フォルダの中はかなりフォルダ数多く複雑です。
B57: 「製造用」とか「元製造」とか「製造用１」がありあまり分別もできていないと思います。
B58: 探すのが大変なので自分の必要なものはショートカットを作成しまとめていますが
B59: 大昔のデータも多く処分していいかわからないので皆さん放置状態になっているのかと思います。
A61: 小田主任 | B61: サーバーの動作が遅く、すぐ切断される
B62: 移動していないのにWi-fiが途切れ、他のWi-fiにつながってしまう
B63: 開発、BeGardenの出勤時刻9時頃が最もサーバーにつながりにくい
A65: 東口リーダー | B65: サーバーの動作が遅く、切断されがち
B66: ネット環境が関係あるか分かりませんが以前からタブレットの動作は
B67: 常に重いのでそちらも改善できればと思います。
A70: 図書 | B70: ・サーバーのファンの音が激しい時と静かな時があり、激しい時は重くなっている気がする
B71: ・一定期間作業していない時（昼休みなど）ログイン画面が表示され入るとプリンター指定が解除されて毎回ＰＤＦ指定になる
B72: ・会計処理をする際、管理部用のノートＰＣでサーバー接続しCSVデータを取り込んでいますが
B73: デスクトップPCに戻りログインするとデスクトップ上のアイコンの配列がバラバラになり少しストレスです
B74: ･サーバーの置いてある場所が暖房の風が直接あたっていて熱くなっているのではないかと思います。
A77: 越智リーダー | B77: ・毎日最初の一回共有フォルダにはじかれる
B78: ・毎日プリンターを選択する必要がある
B79: →既定にできるのは毎日設定
B80: →既定にできないのは都度プリンター選択
B81: ・印刷するとき用紙設定がカスタムになってるか毎回確認しないといけない
B82: ・テプラの印刷がサーバーでできない
B83: ローカルでアプリ？いれても次の日には消える
B84: ・昔よりは改善されてますがPCが固まったり遅かったりする
B85: ・事務長がサーバーになかなか入れないときがある
A87: 丸中さん | B87: ･アマゾンサイトなどへ接続している時、サイト内の動きがとても遅いです。
B88: ･突然サーバーからはじき出される。ログインしなおすと作業途中の画面には戻れます。
A91: 中土 | B91: サーバ本体の設置環境の改善。電圧・換気・空調の効いた鍵付き個室へ設置したい。
B92: ブラウザ処理の負荷に耐えれていない
B93: 接続・描写遅延
B94: 共有フォルダが複雑
B95: 各部署ローカルバックアップ強化
B96: ストレージの最適化 データアクセスの高速化
A97: 大前 | B97: 昼頃・夕方に遅延がする
B98: 受注が多い日に受注管理システム（ブラウザ）からデータをDLすると重たい
B99: エクセルの操作が固まりやすい
A100: 酒井 | B100: ブラウザ上の業務が多い中、固まることで遅延してしまう。
A103: 近藤 | B103: ・朝立ち上げ時、アウトルックの起動に5分程かかる
B104: ・エクセル・ワードにて、タイピングした内容が反映されるまでのタイムラグがかなりある時がある。
B105: ・重すぎて、文字が明瞭ではない時がある。ボケてる。
B106: ・一定の手順で必ずエクセルとワードが落ちることがある。
B107: ・アウトルックの検索が遅い
A109: 宗近 | B109: ・慢性的に動作が遅くてフリーズします。
B110: 書類（処方、提案書、報告書、成績書、指図書など）作成、メール対応、調査など
B111: 本社で作業していた時と比べ、完了するまでの時間が長くなっています。
B112: ・コスメは本社に比べ不具合の時間が多いです。
A114: 山下 | B114: ・急に切れる。
B115: ・Outlook使用時に急に落ちる。
B116: ・Word、EXcel使用時に急に落ちる。
B117: ・急に止まる。
B118: ・タイピングが遅れて反応。
B119: ・ログインできない。
A121: 直木 | B121: ・サーバーが重い、遅い。毎日午前9時と午後6時前後は必ず発生。その他の時間帯も突発的に発生。
B122: ・エクセル、PDF使用時は遅くなりやすい。
B123: ・サーバーが止まることで打ち損じや誤入力が発生しやすくなっている。電子管理が増える中で、この現象は致命的だと思う。
B124: ・パソコンが止まることで、進行中の作業が一旦止まる。再開時に誤入力していないか確認することからスタートするので、作業効率が低下。
...

Sheet 名簿
A2: 氏名 | B2: 使用者補足 | C2: 部 | D2: 課 | E2: 係 | F2: No | G2: ユーザー名 | H2: サポート | I2: 仮想(旧) | J2: SSID (メイン) | K2: 接続拠点 | L2: 接続エリア | M2: 仮想3本 | N2: 対象
A3: 吉村善成 | B3: - | C3: 取締役 | D3: - | E3: - | F3: 003 | G3: yoshinari | H3: ○ | I3: A | J3: NTT DOCOMO(ETC) | K3: - | L3: - | M3: A | N3: 1
A4: 吉村善鐘 | B4: - | C4: 取締役 | D4: - | E4: - | F4: 004 | G4: yoshikane | H4: ○ | I4: A | J4: SSC-5-3F-01 | K4: 本社 | L4: 3F/シンク前 | M4: A | N4: 1
A5: 吉村善濚 | B5: - | C5: 取締役 | D5: - | E5: - | F5: 006 | G5: yoshimizu | H5: ○ | I5: A | J5: SSC-5-4F-01 | K5: 本社 | L5: 4F/社長室 | M5: A | N5: 1
A6: 近藤雅人 | B6: - | C6: 研究開発部 | D6: 研究開発課 | E6: - | F6: 026 | G6: kondou | H6: ○ | I6: B | J6: SSC-CL-5-3F-02 | K6: コスメラボラトリー | L6: 3F/事務所 | M6: C | N6: 1
A7: 宗近倶枝 | B7: - | C7: 研究開発部 | D7: 研究開発課 | E7: - | F7: 024 | G7: munechika | H7: ○ | I7: B | J7: SSC-CL-5-3F-02 | K7: コスメラボラトリー | L7: 3F/事務所 | M7: C | N7: 1
A8: 山下基宏 | B8: - | C8: 研究開発部 | D8: 研究開発課 | E8: - | F8: 039 | G8: yasuda2 | H8: ○ | I8: B | J8: SSC-CL-5-3F-02 | K8: コスメラボラトリー | L8: 3F/事務所 | M8: C | N8: 1
A9: 直木美佐子 | B9: - | C9: 研究開発部 | D9: 研究開発課 | E9: - | F9: 041 | G9: naoki | H9: ○ | I9: B | J9: SSC-CL-5-3F-02 | K9: コスメラボラトリー | L9: 3F/事務所 | M9: C | N9: 1
A10: 津田宝加 | B10: - | C10: 研究開発部 | D10: 研究開発課 | E10: - | F10: 071 | G10: tsuda | H10: ○ | I10: B | J10: SSC-CL-5-3F-02 | K10: コスメラボラトリー | L10: 3F/事務所 | M10: C | N10: 1
A11: 矢野恵 | B11: - | C11: 研究開発部 | D11: 研究開発課 | E11: - | F11: 092 | G11: yano | H11: ○ | I11: B | J11: SSC-CL-5-3F-02 | K11: コスメラボラトリー | L11: 3F/事務所 | M11: C | N11: 1
A12: 橋口千聖 | B12: - | C12: 研究開発部 | D12: 研究開発課 | E12: - | F12: 124 | G12: hashiguchi | H12: ○ | I12: B | J12: SSC-CL-5-3F-03 | K12: コスメラボラトリー | L12: 3F/試験室 | M12: C | N12: 1
A13: 西村穂乃果 | B13: - | C13: 品質保証部 | D13: 品質管理課 | E13: - | F13: 122 | G13: nishimura | H13: ○ | I13: B | J13: SSC-CL-5-3F-02 | K13: コスメラボラトリー | L13: 3F/事務所 | M13: C | N13: 1
A14: 野村秀太朗 | B14: - | C14: 品質保証部 | D14: 品質管理課 | E14: - | F14: 048 | G14: nomura | H14: ○ | I14: B | J14: SSC-5-3F-01 | K14: 本社 | L14: 3F/シンク前 | M14: A | N14: 1
... A24: 森尾直浩 | B24: - | C24: 技術製造部 | D24: 生産管理課 | E24: 物流 | F24: 106 | G24: morio | H24: × | I24: B | J24: SSC-5-3F-01 | K24: 本社 | L24: 3F/シンク前 | M24: A | N24: 1
A25: 本社実績入力用タブレット | B25: mouse⑥ | C25: 技術製造部 | D25: 生産管理課 | E25: 生産管理 | F25: － | G25: － | H25: － | I25: - | J25: SSC-2-3F-01 | K25: 本社 | L25: 3F/シンク前 | M25: - | N25: -
A26: 幹部会議用タブレット(生産管理) | B26: Expert Book② | C26: 企画営業部 | D26: 企画課 | E26: - | F26: － | G26: － | H26: － | I26: - | J26: SSC-2-3F-01 | K26: 本社 | L26: 3F/シンク前 | M26: - | N26: -
A27: 本社3F共用ノートPC | B27: - | C27: 技術製造部 | D27: 生産管理課 | E27: 生産管理 | F27: － | G27: － | H27: － | I27: - | J27: SSC-2-3F-01 | K27: 本社 | L27: 3F/シンク前 | M27: - | N27: -
A28: 第一倉庫のタブレット現品票印刷用 | B28: LAVIE③ | C28: 技術製造部 | D28: 生産管理課 | E28: 物流 | F28: － | G28: － | H28: － | I28: - | J28: SSC-WH-5 | K28: 第一倉庫 | L28: 1F/南西角 | M28: - | N28: -
A29: 森山貴史 | B29: - | C29: 技術製造部 | D29: - | E29: - | F29: 011 | G29: moriyama | H29: ○ | I29: A | J29: SSC-CL-2-2F-01 | K29: コスメラボラトリー | L29: 2F/事務所 | M29: A | N29: 1
A30: 小田晶彦 | B30: - | C30: 技術製造部 | D30: 製造課 | E30: バルク・顆粒 | F30: 013 | G30: oda | H30: ○ | I30: B | J30: SSC-CL-5-2F-01 | K30: コスメラボラトリー | L30: 2F/事務所 | M30: C | N30: 1
A31: 上辻耕太 | B31: mouse④ | C31: 技術製造部 | D31: 製造課 | E31: バルク・顆粒 | F31: 054 | G31: uetsugi | H31: × | I31: B | J31: SSC-CF-5-1F-03 | K31: コスメファクトリー | L31: 1F/バルク室 | M31: - | N31: -
A32: 外間裕貴人 | B32: mouse④ | C32: 技術製造部 | D32: 製造課 | E32: バルク・顆粒 | F32: 116 | G32: hokama | H32: × | I32: B | J32: SSC-CF-5-1F-03 | K32: コスメファクトリー | L32: 1F/バルク室 | M32: B | N32: 1
A33: 松井敬視 | B33: mouse⑤ | C33: 技術製造部 | D33: 製造課 | E33: バルク・顆粒 | F33: 128 | G33: matsui | H33: × | I33: B | J33: SSC-CF-5-1F-03 | K33: コスメファクトリー | L33: 1F/バルク室 | M33: B | N33: 1
A34: 小田勇雄 | B34: - | C34: 技術製造部 | D34: 製造課 | E34: 充填包装 | F34: 021 | G34: oda-i | H34: ○ | I34: B | J34: SSC-CL-2-2F-01 | K34: コスメラボラトリー | L34: 2F/事務所 | M34: C | N34: 1
A35: 東口智一 | B35: - | C35: 技術製造部 | D35: 製造課 | E35: 充填包装 | F35: 066 | G35: higashiguchi | H35: ○ | I35: B | J35: SSC-CF-5-2F-03 | K35: コスメファクトリー | L35: 2F/充填ライン南 | M35: C | N35: 1
A36: 藤本洸平 | B36: LAVIE⑤ | C36: 技術製造部 | D36: 製造課 | E36: 充填包装 | F36: 091 | G36: fujimoto | H36: × | I36: B | J36: SSC-CF-2-2F-02 | K36: コスメファクトリー | L36: 2F/充填ライン北 | M36: B | N36: 1
A37: 松山丈弘 | B37: LAVIE④ | C37: 技術製造部 | D37: 製造課 | E37: 充填包装 | F37: 099 | G37: matsuyama | H37: × | I37: B | J37: SSC-CL-2-1F-02 | K37: コスメラボラトリー | L37: 1F/作業場南 | M37: B | N37: 1
A38: 田中裕一 | B38: LAVIE⑤ | C38: 技術製造部 | D38: 製造課 | E38: 充填包装 | F38: 105 | G38: y-tanaka | H38: × | I38: B | J38: SSC-CF-2-2F-02 | K38: コスメファクトリー | L38: 2F/充填ライン北 | M38: B | N38: 1
A39: 阿部俊樹 | B39: - | C39: 技術製造部 | D39: 製造課 | E39: 粉体 | F39: 117 | G39: abe | H39: × | I39: B | J39: SSC-CL-5-2F-03 | K39: コスメラボラトリー | L39: 2F/作業場南 | M39: B | N39: 1
A40: 松林三美 | B40: - | C40: 技術製造部 | D40: 製造課 | E40: 事務 | F40: 123 | G40: cosmef02 | H40: × | I40: B | J40: SSC-CF-5-1F-01 | K40: コスメファクトリー | L40: 1F/事務所 | M40: C | N40: 1
A41: 個詰め実績入力用タブレット | B41: ？？？ | C41: 技術製造部 | D41: 製造課 | E41: - | G41: － | H41: － | I41: - | J41: SSC-CF-5-2F-02 | K41: コスメファクトリー | L41: 2F/充填ライン北 | M41: - | N41: -
A42: 鳥山ミキ | B42: - | C42: 技術製造部 | D42: 製造課 | E42: 事務 | F42: 035 | G42: cosmef | H42: × | I42: B | J42: SSC-CF-5-1F-01 | K42: コスメファクトリー | L42: 1F/事務所 | M42: C | N42: 1
A43: 内藤恭介 | B43: - | C43: 技術製造部 | D43: 製造課 | E43: 粉体 | F43: 053 | G43: naitou | H43: ○ | I43: B | J43: SSC-5-3F-01 | K43: 本社 | L43: 3F/シンク前 | M43: B | N43: 1
A44: 大川泰弘 | B44: - | C44: 技術製造部 | D44: 製造課 | E44: 液体 | F44: 012 | G44: okawa | H44: × | I44: B | J44: SSC-5-3F-01 | K44: 本社 | L44: 3F/シンク前 | M44: B | N44: 1
A45: 伊澤浩司 | B45: - | C45: 技術製造部 | D45: 製造課 | E45: 液体 | F45: 016 | G45: izawa | H45: × | I45: B | J45: SSC-5-3F-01 | K45: 本社 | L45: 3F/シンク前 | M45: B | N45: 1
A46: 吉山勝宏 | B46: - | C46: 技術製造部 | D46: 製造課 | E46: バルク・顆粒 | F46: 015 | G46: yoshiyama | H46: × | I46: B | J46: SSC-5-3F-01 | K46: 本社 | L46: 3F/シンク前 | M46: B | N46: 1
A47: 濱本雅喜 | B47: - | C47: 技術製造部 | D47: 製造課 | E47: 粉体 | F47: 018 | G47: hamamoto | H47: × | I47: B | J47: SSC-5-3F-01 | K47: 本社 | L47: 3F/シンク前 | M47: B | N47: -
A48: 幹部会議用タブレット(粉体管理分) | B48: Expert Book① | C48: 技術製造部 | D48: 製造課 | E48: 粉体 | F48: － | G48: － | H48: － | I48: - | J48: SSC-5-4F-02 | K48: 本社 | L48: 4F/食堂 | M48: - | N48: -
A49: 中土陽介 | B49: - | C49: EC事業部 | D49: EC事業課 | E49: - | F49: 029 | G49: nakatsuchi | H49: ○ | I49: B | J49: SSC-CL-5-3F-02 | K49: コスメラボラトリー | L49: 3F/事務所 | M49: B | N49: 1
A50: 大前道仁 | B50: - | C50: EC事業部 | D50: EC事業課 | E50: - | F50: 076 | G50: oomae | H50: ○ | I50: B | J50: SSC-CL-5-3F-02 | K50: コスメラボラトリー | L50: 3F/事務所 | M50: B | N50: 1
A51: 酒井絢音 | B51: - | C51: EC事業部 | D51: EC事業課 | E51: - | F51: 120 | G51: sakai | H51: ○ | I51: B | J51: SSC-CL-5-3F-02 | K51: コスメラボラトリー | L51: 3F/事務所 | M51: B | N51: -
A52: 図書杏子 | B52: - | C52: 管理部 | D52: 管理課 | E52: - | F52: 032 | G52: zusyo | H52: ○ | I52: A | J52: SSC-5-3F-01 | K52: 本社 | L52: 3F/シンク前 | M52: A | N52: 1
A53: 越智絵美子 | B53: - | C53: 管理部 | D53: 管理課 | E53: - | F53: 033 | G53: ochi | H53: ○ | I53: A | J53: SSC-5-3F-01 | K53: 本社 | L53: 3F/シンク前 | M53: A | N53: 1
A54: 丸中都 | B54: - | C54: 管理部 | D54: 管理課 | E54: - | F54: 112 | G54: marunaka | H54: ○ | I54: A | J54: SSC-5-3F-01 | K54: 本社 | L54: 3F/シンク前 | M54: A | N54: 1
A55: 管理部 新人用PC | B55: - | C55: 管理部 | D55: 管理課 | E55: - | F55: － | G55: － | H55: － | I55: A | J55: SSC-5-3F-01 | K55: 本社 | L55: 3F/シンク前 | M55: A | N55: -
A56: 管理部のJDL専用(シンコー)のノートPC | B56: - | C56: 管理部 | D56: 管理課 | E56: - | F56: － | G56: － | H56: － | I56: - | J56: SSC-5-3F-01 | K56: 本社 | L56: 3F/シンク前 | M56: - | N56: -
A57: 管理部のJDL専用(Q美ワールド)のノートPC | B57: - | C57: 管理部 | D57: 管理課 | E57: - | F57: － | G57: － | H57: － | I57: - | J57: SSC-5-3F-01 | K57: 本社 | L57: 3F/シンク前 | M57: - | N57: -
A58: 管理部送り状印刷用PC | B58: - | C58: 管理部 | D58: 管理課 | E58: - | F58: － | G58: － | H58: － | I58: - | J58: SSC-5-3F-01 | K58: 本社 | L58: 3F/シンク前 | M58: - | N58: -
A59: 濱西藍伽 | B59: - | C59: 企画営業部 | D59: 企画課 | E59: - | F59: 121 | G59: hamanishi | H59: ○ | I59: B | J59: SSC-5-3F-01 | K59: 本社 | L59: 3F/シンク前 | M59: B | N59: 1
A60: 企画課 新人用PC① | B60: - | C60: 企画営業部 | D60: 企画課 | E60: - | F60: － | G60: － | H60: － | I60: B | J60: SSC-5-3F-01 | K60: 本社 | L60: 3F/シンク前 | M60: B | N60: -
A61: 企画課 新人用PC② | B61: - | C61: 企画営業部 | D61: 企画課 | E61: - | F61: － | G61: － | H61: － | I61: B | J61: SSC-5-3F-01 | K61: 本社 | L61: 3F/シンク前 | M61: B | N61: -
A62: 南光彦 | B62: - | C62: 企画営業部 | D62: - | E62: - | F62: 007 | G62: minami | H62: ○ | I62: A | J62: QB-SSC-5-R4 | K62: 東京営業所 | L62: - | M62: A | N62: 1
A63: 橋本悠司 | B63: - | C63: 企画営業部 | D63: 営業課 | E63: - | F63: 058 | G63: hashimoto | H63: × | I63: B | J63: QB-SSC-5-R4 | K63: 東京営業所 | L63: - | M63: B | N63: 1
A64: 野田健治 | B64: - | C64: 企画営業部 | D64: 営業課 | E64: - | F64: 008 | G64: noda | H64: ○ | I64: B | J64: QB-SSC-5-R4 | K64: 東京営業所 | L64: - | M64: B | N64: -
A65: 堀真紀 | B65: - | C65: 企画営業部 | D65: 営業課 | E65: - | F65: 110 | G65: hori | H65: ○ | I65: B | J65: QB-SSC-5-R4 | K65: 東京営業所 | L65: - | M65: B | N65: -
A66: 松本佳奈 | B66: - | C66: 企画営業部 | D66: 営業課 | E66: - | F66: 108 | G66: matsumoto | H66: ○ | I66: A | J66: QB-SSC-5-R4 | K66: 東京営業所 | L66: - | M66: A | N66: -
A67: 髙野愛子 | B67: - | C67: 企画営業部 | D67: 営業課 | E67: - | F67: 009 | G67: takano | H67: ○ | I67: A | J67: QB-SSC-5-R4 | K67: 東京営業所 | L67: - | M67: A | N67: 1
A68: mouse① | B68: バルク | C68: 技術製造部 | D68: 製造課 | E68: バルク・顆粒 | F68: － | G68: － | H68: － | I68: - | J68: SSC-CF-5-1F-03 | K68: コスメファクトリー | L68: 1F/バルク室 | M68: - | N68: -
A69: mouse② | B69: バルク | C69: 技術製造部 | D69: 製造課 | E69: バルク・顆粒 | F69: － | G69: － | H69: － | I69: - | J69: SSC-CF-5-1F-03 | K69: コスメファクトリー | L69: 1F/バルク室 | M69: - | N69: -
A70: mouse③ | B70: バルク | C70: 技術製造部 | D70: 製造課 | E70: バルク・顆粒 | F70: － | G70: － | H70: － | I70: - | J70: SSC-CF-5-1F-03 | K70: コスメファクトリー | L70: 1F/バルク室 | M70: - | N70: -
A71: mouse④ | B71: バルク | C71: 技術製造部 | D71: 製造課 | E71: バルク・顆粒 | F71: － | G71: － | H71: － | I71: - | J71: SSC-CF-5-1F-03 | K71: コスメファクトリー | L71: 1F/バルク室 | M71: - | N71: -
A72: mouse⑤ | B72: バルク | C72: 技術製造部 | D72: 製造課 | E72: バルク・顆粒 | F72: － | G72: － | H72: － | I72: - | J72: SSC-CF-5-1F-03 | K72: コスメファクトリー | L72: 1F/バルク室 | M72: - | N72: -
A73: mouse⑥ | B73: バルク(予備) | C73: 技術製造部 | D73: 製造課 | E73: バルク・顆粒 | F73: － | G73: － | H73: － | I73: - | J73: SSC-2-3F-01 | K73: 本社 | L73: 3F/シンク前 | M73: - | N73: -
A74: LAVIE① | B74: 充填包装 | C74: 技術製造部 | D74: 製造課 | E74: 充填包装 | F74: － | G74: － | H74: － | I74: - | J74: - | K74: - | L74: - | M74: - | N74: -
A75: LAVIE② | B75: 充填包装 | C75: 技術製造部 | D75: 製造課 | E75: 充填包装 | F75: － | G75: － | H75: － | I75: - | J75: - | K75: - | L75: - | M75: - | N75: -
A76: LAVIE③ | B76: 第一倉庫 現品票印刷 | C76: 技術製造部 | D76: 製造課 | E76: 充填包装 | F76: － | G76: － | H76: － | I76: - | J76: SSC-WH-5 | K76: 第一倉庫 | L76: 1F/南西角 | M76: - | N76: -
A77: LAVIE④ | B77: 充填包装/松山 | C77: 技術製造部 | D77: 製造課 | E77: 充填包装 | F77: － | G77: － | H77: － | I77: - | J77: SSC-CL-2-1F-02 | K77: コスメラボラトリー | L77: 1F/作業場南 | M77: - | N77: -
A78: LAVIE⑤ | B78: 充填包装/藤本・田中 | C78: 技術製造部 | D78: 製造課 | E78: 充填包装 | F78: － | G78: － | H78: － | I78: - | J78: SSC-CF-2-2F-02 | K78: コスメファクトリー | L78: 2F/充填ライン北 | M78: - | N78: -
A79: LAVIE⑥ | B79: 充填包装(端末不調) | C79: 技術製造部 | D79: 製造課 | E79: 充填包装 | F79: － | G79: － | H79: － | I79: - | J79: - | K79: - | L79: - | M79: - | N79: -
... A84: 寺石歩実 | B84: - | C84: 品質保証部 | D84: 品質管理課 | E84: - | F84: 132 | G84: teraishi | H84: ○ | I84: B | J84: SSC-CL-5-3F-02 | K84: コスメラボラトリー | L84: 3F/事務所 | M84: C | N84: -
A85: 杉尾瑞樹 | B85: - | C85: 企画営業部 | D85: 企画課 | E85: - | F85: 131 | G85: sugio | H85: ○ | I85: B | J85: SSC-5-3F-01 | K85: 本社 | L85: 3F/シンク前 | M85: B | N85: 1
A86: 松下賢 | B86: mouse⑤ | C86: 技術製造部 | D86: 製造課 | E86: バルク・顆粒 | F86: 130 | G86: matsushita | H86: × | I86: B | J86: SSC-CF-5-1F-03 | K86: コスメファクトリー | L86: 1F/バルク室 | M86: B | N86: 1
A87: 小柏拓海 | B87: LAVIE⑤ | C87: 技術製造部 | D87: 製造課 | E87: 充填包装 | F87: 134 | G87: kogashiwa | H87: × | I87: B | J87: SSC-CF-2-2F-02 | K87: コスメファクトリー | L87: 2F/充填ライン北 | M87: B | N87: 1
A88: 吉村幸市 | B88: - | C88: 取締役 | D88: - | E88: - | F88: 001 | G88: yoshimura | H88: × | I88: B | J88: - | K88: - | L88: - | M88: B | N88: 1
A89: 吉村美佐子 | B89: - | C89: 取締役 | D89: - | E89: - | F89: 002 | G89: misako | H89: ○→× | I89: A | J89: - | K89: - | L89: - | M89: A | N89: 1
A90: 中村剛 | B90: - | C90: 企画営業部 | D90: 営業課 | E90: - | F90: 137 | G90: nakamura | H90: ○ | I90: A | J90: QB-SSC-5-R4 | K90: 東京営業所 | L90: - | M90: A | N90: 1
A91: 堂山利奈 | B91: - | C91: 企画営業部 | D91: 企画課 | E91: - | F91: 138 | G91: doyama | H91: ○ | I91: B | J91: - | K91: - | L91: - | M91: B | N91: 1
A92: 中村友美 | B92: - | C92: EC事業部 | D92: EC事業課 | E92: - | F92: 135 | G92: nakamura-t | H92: × | I92: B | J92: - | K92: - | L92: - | M92: B | N92: -
A93: 羽渕友麻 | B93: - | C93: EC事業部 | D93: EC事業課 | E93: - | F93: 136 | G93: habuchi | H93: ○→× | I93: B | J93: SSC-CL-5-3F-02 | K93: コスメラボラトリー | L93: 3F/事務所 | M93: B | N93: -
A94: 旧 神門PC | B94: 余剰PC→配置換え | C94: EC事業部 | D94: EC事業課 | E94: - | F94: － | G94: － | H94: － | I94: B | J94: SSC-CL-5-3F-01 | K94: コスメラボラトリー | L94: 3F/休憩/応接室 | M94: B | N94: -
A95: 増員 予定 | B95: - | C95: 技術製造部 | D95: 製造課 | E95: 粉体 | F95: 未 | G95: 未 | H95: × | I95: B | J95: SSC-5-3F-01 | K95: 本社 | L95: 3F/シンク前 | M95: B | N95: -
A96: 管理部集約 | B96: - | C96: 管理部 | D96: 管理課 | E96: - | F96: 129 | G96: info-kanri | H96: × | I96: A | J96: SSC-5-3F-01 | K96: 本社 | L96: 3F/シンク前 | M96: A | N96: -
A97: ラボ3F応接 | B97: 応接用 | C97: 技術製造部 | D97: - | E97: - | F97: － | G97: － | H97: － | I97: - | J97: SSC-CL-2-3F-01 | K97: コスメラボラトリー | L97: 3F/休憩/応接室 | M97: - | N97: -
A98: 旧 EC事業部PC | B98: 余剰PC | C98: EC事業部 | D98: EC事業課 | E98: - | F98: － | G98: － | H98: － | I98: - | J98: - | K98: - | L98: - | M98: - | N98: -

Sheet (統合)
C1: 1 | K1: 殆ど使わない | L1: 殆ど使わない | M1: 殆ど使わない | N1: 週に1～2日は重い時がある | O1: Microsoft Edge | P1: 1～2個 | Q1: 履歴を自動で削除している | R1: ID・パスワードを保存していない | S1: 週に1～2日は重い時がある | T1: 殆ど使わない | U1: 殆ど使わない | V1: 殆ど使わない | W1: 殆ど使わない | X1: 週に1～2日は重い時がある | Y1: シンコーのみ使う | Z1: - | AA1: - | AB1: 殆ど使わない | AC1: 殆ど使わない | AD1: データ入力・SUM関数がメイン | AE1: 週に1～2日は重い時がある | AF1: 殆ど使わない | AG1: 殆ど使わない | AH1: 殆ど使わない | AI1: 殆ど使わない | AJ1: 殆ど使わない | AK1: PDFを閲覧する | AL1: 週に1～2日は重い時がある | AM1: アカウントを持っていない | AN1: 使わない | AO1: 使わない | AP1: 使わない | AQ1: 使わない | AR1: 使わない | AS1: 使わない | AT1: ブラウザで使う | AU1: 打刻・スケジュール申請のみ | AV1: 殆ど使わない | AW1: 使わない | AY1: - | AZ1: - | BA1: - | BB1: - | BC1: - | BD1: - | BE1: - | BF1: - | BG1: - | BH1: - | BJ1: 個人専用PCを使う | BK1: ノートPC | BL1: SSD | BM1: 主に有線LANで接続する | BN1: 有線LANのみ使う | BO1: - | BP1: - | BQ1: - | BR1: - | BS1: - | BT1: - | BU1: - | BV1: OSが3分以内に起動する | CL1: 使わない | CM1: 使わない | CN1: 使わない | CP1: アクセス権限なし | CQ1: アクセス権限なし | CR1: アクセス権限なし | CS1: アクセス権限なし | CT1: アクセス権限なし | CU1: アクセス権限なし | CV1: アクセス権限なし | CW1: アクセス権限なし | CX1: アクセス権限なし | CY1: アクセス権限なし | CZ1: アクセス権限なし | DA1: アクセス権限なし | DB1: アクセス権限なし | DC1: アクセス権限なし | DD1: アクセス権限なし | DE1: アクセス権限なし | DF1: アクセス権限なし | DG1: アクセス権限なし | DH1: アクセス権限なし | DI1: アクセス権限なし | DJ1: アクセス権限なし | DK1: アクセス権限なし | DL1: 継続使用 | DM1: - | DN1: 無 | DO1: - | DP1: ノートPC | DQ1: 標準/低稼働 | DR1: BBasic(WEB) | DS1: 共用 | DT1: - | DU1: 1次 | DV1: A | DW1: A | DX1: 0 現場作業が主要業務 | DY1: 1
C2: 2 | K2: 1週間で1～2日は使う | L2: 主に出勤直後・退勤前に使う | M2: 社内・固定の拠点で接続する | N2: +フリーズする時がある | O2: Firefox | P2: 3～5個 | Q2: 履歴を手動で削除している | R2: ID・パスワードをブラウザで保存している | S2: +フリーズする時がある | T2: 1週間で1～2日は使う | U2: 主に出勤直後・退勤前に使う | V2: メーリングリストの送受信がメイン | W2: 文章メイン | X2: +フリーズする時がある | Y2: シンコー・Q美どちらも使う | Z2: - | AA2: - | AB2: 1週間で1～2日は使う | AC2: 主に出勤直後・退勤前に使う | AD2: +グラフ・SUM以外の関数を使う | AE2: +フリーズする時がある | AF2: 月に数回使う | AG2: 月に数回使う | AH2: 月に数回使う | AI2: 1週間で1～2日は使う | AJ2: 主に出勤直後・退勤前に使う | AK2: +コメント・ハイライト・ページ整理を使う | AL2: +フリーズする時がある | AM2: スマホで使う | AN2: 閲覧のみ | AO2: 閲覧のみ | AP2: 仕入を入力する/発注書を作成する | AQ2: サブ担当者として使う | AR2: サブ担当者として使う | AS2: サブ担当者として使う | AT2: ブラウザ・スマホどちらも使う | AU2: 管理者として使う | AV2: 月に数回使う | AW2: 使う | AY2: - | AZ2: - | BA2: - | BB2: - | BC2: - | BD2: - | BE2: - | BF2: - | BG2: - | BH2: - | BJ2: 共用PCを使う | BK2: デスクトップPC | BL2: HDD | BM2: 主に無線LANで接続する | BN2: メインの接続先のみ自動で接続する | BO2: - | BP2: - | BQ2: - | BR2: - | BS2: - | BT2: - | BU2: - | BV2: OSが5分以内に起動する | CL2: 使う | CM2: 使う | CN2: 使う | CP2: 殆ど使わない | CQ2: 殆ど使わない | CR2: 殆ど使わない | CS2: 殆ど使わない | CT2: 殆ど使わない | CU2: 殆ど使わない | CV2: 殆ど使わない | CW2: 殆ど使わない | CX2: 殆ど使わない | CY2: 殆ど使わない | CZ2: 殆ど使わない | DA2: 殆ど使わない | DB2: 殆ど使わない | DC2: 殆ど使わない | DD2: 殆ど使わない | DE2: 殆ど使わない | DF2: 殆ど使わない | DG2: 殆ど使わない | DH2: 殆ど使わない | DI2: 殆ど使わない | DJ2: 殆ど使わない | DK2: 殆ど使わない | DL2: 買替 | DM2: - | DN2: 有 | DO2: - | DP2: デスクトップPC | DQ2: 標準/高稼働 | DR2: BStandard(デスク) | DS2: 専用 | DT2: - | DU2: 2次 | DV2: B | DW2: B | DX2: 0.5 サーバ外の作業可 | DY2: 保留
C3: 3 | K3: 1週間の半分は使う | L3: 特定の時間に集中して使う | M3: 社内・複数の拠点で接続する | N3: +強制終了する時がある | O3: Google Chrome | P3: 6～9個 | Q3: 履歴管理をしていない | R3: ID・パスワードをサイト上で保存している | S3: +強制終了する時がある | T3: 1週間の半分は使う | U3: 特定の時間に集中して使う | V3: +社内でのやり取りが多い | W3: 添付(1MB未満)が多い | X3: +強制終了する時がある | Y3: シンコー・Q美以外も使う | Z3: - | AA3: - | AB3: 1週間の半分は使う | AC3: 特定の時間に集中して使う | AD3: +IF・VLOOKUP系の関数もよく使う | AE3: +強制終了する時がある | AF3: 週に数回使う | AG3: 週に数回使う | AH3: 週に数回使う | AI3: 1週間の半分は使う | AJ3: 特定の時間に集中して使う | AK3: +それ以外の編集ツールも使う | AL3: +強制終了する時がある | AM3: ブラウザで使う | AN3: データ入力担当者として使う | AO3: データ入力担当者として使う | AP3: 売上を入力する/請求書を作成する | AQ3: メイン担当者として使う | AR3: メイン担当者として使う | AS3: メイン担当者として使う | AT3: 未登録 | AU3: - | AV3: 週に数回使う | AW3: - | AY3: - | AZ3: - | BA3: - | BB3: - | BC3: - | BD3: - | BE3: - | BF3: - | BG3: - | BH3: - | BJ3: +特定業務専用のPCを使う | BK3: タブレット | BL3: SSD+HDD | BM3: 接続場所によって変える | BN3: 全て自動で接続する | BO3: - | BP3: - | BQ3: - | BR3: - | BS3: - | BT3: - | BU3: - | BV3: OSが10分以内に起動する | CL3: - | CM3: - | CN3: - | CP3: 定期的に使う | CQ3: 定期的に使う | CR3: 定期的に使う | CS3: 定期的に使う | CT3: 定期的に使う | CU3: 定期的に使う | CV3: 定期的に使う | CW3: 定期的に使う | CX3: 定期的に使う | CY3: 定期的に使う | CZ3: 定期的に使う | DA3: 定期的に使う | DB3: 定期的に使う | DC3: 定期的に使う | DD3: 定期的に使う | DE3: 定期的に使う | DF3: 定期的に使う | DG3: 定期的に使う | DH3: 定期的に使う | DI3: 定期的に使う | DJ3: 定期的に使う | DK3: 定期的に使う | DL3: ▲端末不調 | DM3: - | DN3: - | DO3: - | DP3: - | DQ3: 高性能 | DR3: - | DS3: - | DT3: - | DU3: - | DV3: - | DW3: C | DX3: 1 サーバ停止=主要業務停止 | DY3: -
C4: 4 | K4: 毎日使う | L4: 終日使う | M4: +社外の拠点からも接続する | N4: 毎日不具合があり支障を来たしている | O4: - | P4: 10個以上 | Q4: 分からない | R4: 分からない | S4: 毎日不具合があり支障を来たしている | T4: 毎日使う | U4: 終日使う | V4: +社外でのやり取りも多い | W4: 添付(1MB以上)が多い | X4: 毎日不具合があり支障を来たしている | Y4: - | Z4: - | AA4: - | AB4: 毎日使う | AC4: 終日使う | AD4: +マクロ・ピボットテーブルも使う | AE4: 毎日不具合があり支障を来たしている | AF4: ほぼ毎日使う | AG4: ほぼ毎日使う | AH4: ほぼ毎日使う | AI4: 毎日使う | AJ4: 終日使う | AK4: - | AL4: 毎日不具合があり支障を来たしている | AM4: ブラウザ・スマホどちらも使う | AN4: 管理者/責任者として使う | AO4: 管理者/責任者として使う | AP4: 入出金まで管理する | AQ4: - | AR4: - | AS4: - | AT4: - | AU4: - | AV4: ほぼ毎日使う | AW4: - | AY4: - | AZ4: - | BA4: - | BB4: - | BC4: - | BD4: - | BE4: - | BF4: - | BG4: - | BH4: - | BJ4: - | BK4: - | BL4: - | BM4: - | BN4: 分からない | BO4: - | BP4: - | BQ4: - | BR4: - | BS4: - | BT4: - | BU4: - | BV4: OSの起動に10分以上かかる | CL4: - | CM4: - | CN4: - | CP4: 毎日使う | CQ4: 毎日使う | CR4: 毎日使う | CS4: 毎日使う | CT4: 毎日使う | CU4: 毎日使う | CV4: 毎日使う | CW4: 毎日使う | CX4: 毎日使う | CY4: 毎日使う | CZ4: 毎日使う | DA4: 毎日使う | DB4: 毎日使う | DC4: 毎日使う | DD4: 毎日使う | DE4: 毎日使う | DF4: 毎日使う | DG4: 毎日使う | DH4: 毎日使う | DI4: 毎日使う | DJ4: 毎日使う | DK4: 毎日使う | DL4: ▲廃棄 | DM4: - | DN4: - | DO4: - | DP4: - | DQ4: - | DR4: - | DS4: - | DT4: - | DU4: - | DV4: - | DW4: - | DX4: - | DY4: -
J5: サーバ | K5: サーバ | L5: サーバ | M5: サーバ | N5: サーバ | O5: アプリ | P5: アプリ | Q5: アプリ | R5: アプリ | S5: アプリ | T5: アプリ | U5: アプリ | V5: アプリ | W5: アプリ | X5: アプリ | Y5: アプリ | Z5: アプリ | AA5: アプリ | AB5: アプリ | AC5: アプリ | AD5: アプリ | AE5: アプリ | AF5: アプリ | AG5: アプリ | AH5: アプリ | AI5: アプリ | AJ5: アプリ | AK5: アプリ | AL5: アプリ | AM5: アプリ | AN5: アプリ | AO5: アプリ | AP5: アプリ | AQ5: アプリ | AR5: アプリ | AS5: アプリ | AT5: アプリ | AU5: アプリ | AV5: アプリ | AW5: アプリ | AX5: - | AY5: サーバ | AZ5: サーバ | BA5: サーバ | BB5: サーバ | BC5: サーバ | BD5: サーバ | BE5: サーバ | BF5: サーバ | BG5: サーバ | BH5: サーバ | BI5: - | BJ5: 環境 | BK5: 環境 | BL5: 環境 | BM5: 環境 | BN5: 環境 | BO5: 環境 | BP5: 環境 | BQ5: 環境 | BR5: 環境 | BS5: 環境 | BT5: 環境 | BU5: 環境 | BV5: 環境 | BW5: - | BX5: 環境 | BY5: 環境 | BZ5: 環境 | CA5: 環境 | CB5: 環境 | CC5: 環境 | CD5: 環境 | CE5: - | CF5: 環境 | CG5: 環境 | CH5: 環境 | CI5: 環境 | CJ5: 環境 | CK5: 環境 | CL5: 環境 | CM5: 環境 | CN5: 環境 | CO5: - | CP5: サーバ | CQ5: サーバ | CR5: サーバ | CS5: サーバ | CT5: サーバ | CU5: サーバ | CV5: サーバ | CW5: サーバ | CX5: サーバ | CY5: サーバ | CZ5: サーバ | DA5: サーバ | DB5: サーバ | DC5: サーバ | DD5: サーバ | DE5: サーバ | DF5: サーバ | DG5: サーバ | DH5: サーバ | DI5: サーバ | DJ5: サーバ | DK5: サーバ | DL5: 環境 | DM5: 環境 | DN5: 環境 | DO5: 環境 | DP5: 環境 | DQ5: 環境 | DR5: M365 | DS5: M365 | DT5: M365 | DU5: M365 | DV5: サーバ | DW5: サーバ | DX5: サーバ | DY5: 環境 | DZ5: 環境
A6: 回答日 | B6: 氏名 | C6: 使用者補足 | D6: 部 | E6: 課 | F6: 係 | G6: No | H6: ユーザー名 | I6: サポート | J6: 仮想 | K6: シンクライアント (日数) | L6: シンクライアント (時間) | M6: シンクライアント (拠点) | N6: シンクライアント (動作) | O6: WEBブラウザ (種類) | P6: WEBブラウザ (同時に開くタブ) | Q6: WEBブラウザ (履歴) | R6: WEBブラウザ (ID・パスワード) | S6: WEBブラウザ (動作) | T6: Outlook (日数) | U6: Outlook (時間) | V6: Outlook (宛先) | W6: Outlook (用途) | X6: Outlook (動作) | Y6: Outlook (アドレス) | Z6: Outlook pstファイル【KB】 | AA6: Outlook pstファイル【GB】 | AB6: Excel (日数) | AC6: Excel (時間) | AD6: Excel (用途) | AE6: Excel (動作) | AF6: Word | AG6: PowerPoint | AH6: Access | AI6: AdobeAcrobat (日数) | AJ6: AdobeAcrobat (時間) | AK6: AdobeAcrobat (用途) | AL6: AdobeAcrobat (動作) | AM6: Chatwork | AN6: TPiCS | AO6: PI-navi | AP6: 商蔵奉行 | AQ6: FD申請 | AR6: ラベル印刷 | AS6: 送り状印刷 | AT6: Sansan | AU6: KING OF TIME | AV6: TeamViewer | AW6: JDL | AX6: ◆デスクトップ容量 | AY6: サイズ【GB】 | AZ6: ディスク上のサイズ【GB】 | BA6: ファイル数 | BB6: フォルダ数 | BC6: SCAN ディスク上のサイズ【GB】 | BD6: SCAN ファイル数 | BE6: SCAN フォルダ数 | BF6: 個人データサイズ【GB】 | BG6: 個人ファイル数 | BH6: 個人フォルダ数 | BI6: ◆ローカル側 | BJ6: パソコン (割当) | BK6: パソコン (種類) | BL6: パソコン (ドライブ) | BM6: パソコン (通信) | BN6: パソコン (Wi-Fi接続) | BO6: SSID (メイン) | BP6: 接続拠点 | BQ6: 接続エリア | BR6: SSID (サブ1) | BS6: SSID (サブ2) | BT6: SSID (サブ3) | BU6: SSID (サブ4) | BV6: パソコン (起動) | BW6: ◆デバイスの仕様 | BX6: デバイス名 | BY6: プロセッサ | BZ6: 実装 RAM | CA6: デバイス ID | CB6: プロダクト ID | CC6: システムの種類 | CD6: ペンとタッチ | CE6: ◆OSの仕様 | CF6: エディション | CG6: バージョン | CH6: インストール日 | CI6: OS ビルド | CJ6: シリアル番号 | CK6: エクスペリエンス | CL6: 社用スマートフォン | CM6: 社用タブレット | CN6: ハンディターミナル | CO6: ◆共有フォルダ | CP6: 01営業部 | CQ6: 02製造部 | CR6: 03総務部 | CS6: 04開発部 | CT6: 05企画部 | CU6: 06コスメファクトリー | CV6: 07SHINKO共有 | CW6: 08Q美共有 | CX6: 10デリバリー | CY6: 11製造部（報告用） | CZ6: 12BeGarden | DA6: 90過去未整理 | DB6: 98在庫管理 | DC6: 99管理 | DD6: Infinity_一時利用 | DE6: Q美ワールド | DF6: SCAN | DG6: シンコーサイエンス | DH6: 移動用一時フォルダ | DI6: 共有ファイル | DJ6: 復元データ | DK6: 予算管理 | DL6: PC 買替/継続使用 | DM6: 買替時期 | DN6: 配置換え有無 | DO6: 配置換え先 | DP6: ノート/デスクトップ | DQ6: 標準性能/高性能 | DR6: M365プラン | DS6: M365アカウント | DT6: M365共用グループ | DU6: 導入時期 | DV6: 仮想2本 | DW6: 仮想3本 | DX6: サーバ依存度 | DY6: 対象 | DZ6: 意見/要望/備考
A7: 45762 | B7: 吉村善成 | C7: - | D7: 取締役 | E7: - | F7: - | G7: 003 | H7: yoshinari | I7: ○ | J7: A | K7: 4 | L7: 2 | M7: 4 | N7: 1 | O7: 3 | P7: 2 | Q7: 3 | R7: 4 | S7: 1 | T7: 4 | U7: 2 | V7: 4 | W7: 3 | X7: 1 | Y7: 2 | Z7: 10065858 | AA7: 10.065858 | AB7: 1 | AC7: 1 | AD7: 1 | AE7: 1 | AF7: 1 | AG7: 1 | AH7: 1 | AI7: 1 | AJ7: 1 | AK7: 1 | AL7: 1 | AM7: 2 | AN7: 1 | AO7: 1 | AP7: 1 | AQ7: 1 | AR7: 1 | AS7: 1 | AT7: 2 | AU7: 2 | AV7: 1 | AW7: 1 | AX7: - | AY7: 59.1 | AZ7: 59.2 | BA7: 10483 | BB7: 881 | BC7: 0 | BD7: 0 | BE7: 0 | BF7: 69.265858 | BG7: 10483 | BH7: 881 | BI7: - | BJ7: 1 | BK7: 1 | BL7: 1 | BM7: 2 | BN7: 3 | BO7: NTT DOCOMO(ETC) | BP7: - | BQ7: - | BR7: - | BS7: - | BT7: - | BU7: - | BV7: 1 | BW7: ↓(ローカル側からコピペしてください。) | BX7: DESKTOP-GUC6N5D | BY7: Intel(R) Core(TM) i5-7200U CPU @ 2.50GHz 2.71 GHz | BZ7: 8.00 GB | CA7: 63001086-D342-4D85-89AC-C12D3CB23535 | CB7: 00330-50691-32915-AAOEM | CC7: 64 ビット オペレーティング システム、x64 ベース プロセッサ | CD7: 10 タッチ ポイントでのペンとタッチのサポート | CE7: ↓(ローカル側からコピペしてください。) | CF7: Windows 10 Pro | CG7: 22H2 | CH7: ‎2020/‎12/‎20 | CI7: 19045.549 | CJ7: 7IKSA19021 | CK7: Windows Feature Experience Pack 1000.19061.1000.0 | CL7: 2 | CM7: 2 | CN7: 1 | CO7: - | CP7: 3 | CQ7: 2 | CR7: 2 | CS7: 2 | CT7: 2 | CU7: 2 | CV7: 2 | CW7: 3 | CX7: 2 | CY7: 2 | CZ7: 2 | DA7: 2 | DB7: 2 | DC7: 2 | DD7: 2 | DE7: 3 | DF7: 3 | DG7: 3 | DH7: 2 | DI7: 2 | DJ7: 2 | DK7: 2 | DL7: 買替 | DM7: 45943 | DN7: 無 | DO7: - | DP7: ノート | DQ7: 要確認 | DR7: 1 | DS7: 1 | DT7: 営業/EC | DU7: 1次 | DV7: A | DW7: A | DX7: 0.5 | DY7: 1
A8: 45763 | B8: 吉村善鐘 | C8: - | D8: 取締役 | E8: - | F8: - | G8: 004 | H8: yoshikane | I8: ○ | J8: A | K8: 4 | L8: 4 | M8: 2 | N8: 1 | O8: 2 | P8: 2 | Q8: 3 | R8: 2 | S8: 1 | T8: 4 | U8: 4 | V8: 4 | W8: 4 | X8: 2 | Y8: 2 | Z8: 9418561 | AA8: 9.418561 | AB8: 4 | AC8: 4 | AD8: 1 | AE8: 2 | AF8: 3 | AG8: 1 | AH8: 1 | AI8: 3 | AJ8: 3 | AK8: 1 | AL8: 1 | AM8: 2 | AN8: 1 | AO8: 1 | AP8: 1 | AQ8: 1 | AR8: 1 | AS8: 1 | AT8: 2 | AU8: 2 | AV8: 1 | AW8: 1 | AX8: - | AY8: 35.5 | AZ8: 35.7 | BA8: 105929 | BB8: 10454 | BC8: 0 | BD8: 0 | BE8: 0 | BF8: 45.118561 | BG8: 105929 | BH8: 10454 | BI8: - | BJ8: 1 | BK8: 1 | BL8: 1 | BM8: 2 | BN8: 2 | BO8: SSC-5-3F-01 | BP8: 本社 | BQ8: 3F/シンク前 | BR8: - | BS8: - | BT8: - | BU8: - | BV8: 2 | BW8: ↓(ローカル側からコピペしてください。) | BX8: DESKTOP-CVP38V5 | BY8: Intel(R) Core(TM) i5-7200U CPU @ 2.50GHz 2.71 GHz | BZ8: 8.00 GB | CA8: C1DA6129-D204-4306-83CC-1E76D139B129 | CB8: 00330-50535-81745-AAOEM | CC8: 64 ビット オペレーティング システム、x64 ベース プロセッサ | CD8: 10 タッチ ポイントでのペンとタッチのサポート | CE8: ↓(ローカル側からコピペしてください。) | CF8: Windows 10 Pro | CG8: 22H2 | CH8: ‎2021/‎02/‎02 | CI8: 19045.574 | CJ8: 7EKSA10284 | CK8: Windows Feature Experience Pack 1000.19061.1000.0 | CL8: 2 | CM8: 1 | CN8: 1 | CO8: - | CP8: 2 | CQ8: 3 | CR8: 2 | CS8: 3 | CT8: 3 | CU8: 3 | CV8: 4 | CW8: 2 | CX8: 2 | CY8: 2 | CZ8: 2 | DA8: 2 | DB8: 2 | DC8: 2 | DD8: 2 | DE8: 2 | DF8: 3 | DG8: 4 | DH8: 3 | DI8: 3 | DJ8: 3 | DK8: 2 | DL8: 買替 | DM8: 45943 | DN8: 無 | DO8: - | DP8: ノート | DQ8: 要確認 | DR8: 1 | DS8: 1 | DT8: 仕様書 | DU8: 2次 | DV8: A | DW8: A | DX8: 1 | DY8: 1
A9: 45763 | B9: 吉村善濚 | C9: - | D9: 取締役 | E9: - | F9: - | G9: 006 | H9: yoshimizu | I9: ○ | J9: A | K9: 3 | L9: 3 | M9: 4 | N9: 1 | O9: 2 | P9: 2 | Q9: 3 | R9: 1 | S9: 1 | T9: 3 | U9: 3 | V9: 4 | W9: 4 | X9: 1 | Y9: 1 | Z9: 8710025 | AA9: 8.710025 | AB9: 3 | AC9: 3 | AD9: 1 | AE9: 1 | AF9: 3 | AG9: 1 | AH9: 1 | AI9: 3 | AJ9: 3 | AK9: 1 | AL9: 1 | AM9: 4 | AN9: 1 | AO9: 1 | AP9: 1 | AQ9: 1 | AR9: 1 | AS9: 1 | AT9: 1 | AU9: 1 | AV9: 1 | AW9: 1 | AX9: - | AY9: 7.89 | AZ9: 7.92 | BA9: 18331 | BB9: 2218 | BC9: 0 | BD9: 0 | BE9: 0 | BF9: 16.630025 | BG9: 18331 | BH9: 2218 | BI9: - | BJ9: 1 | BK9: 1 | BL9: 1 | BM9: 2 | BN9: 3 | BO9: SSC-5-4F-01 | BP9: 本社 | BQ9: 4F/社長室 | BR9: - | BS9: - | BT9: - | BU9: - | BV9: 1 | BW9: ↓(ローカル側からコピペしてください。) | BX9: yosimizu | BY9: Intel(R) Core(TM) i7-10710U CPU @ 1.10GHz 1.61 GHz | BZ9: 16.0 GB (15.7 GB 使用可能) | CA9: F1A53272-43F1-4882-A916-784E8C4E613D | CB9: 00330-53093-61459-AAOEM | CC9: 64 ビット オペレーティング システム、x64 ベース プロセッサ | CD9: このディスプレイでは、ペン入力とタッチ入力は利用できません | CE9: ↓(ローカル側からコピペしてください。) | CF9: Windows 11 Pro | CG9: 24H2 | CH9: 2025/‎02/‎21 | CI9: 26100.377 | CJ9: 0IKSC28173 | CK9: Windows 機能エクスペリエンス パック 1000.26100.66.0 | CL9: 2 | CM9: 1 | CN9: 1 | CO9: - | CP9: 2 | CQ9: 2 | CR9: 2 | CS9: 3 | CT9: 2 | CU9: 2 | CV9: 2 | CW9: 3 | CX9: 2 | CY9: 2 | CZ9: 2 | DA9: 2 | DB9: 2 | DC9: 2 | DD9: 2 | DE9: 2 | DF9: 3 | DG9: 2 | DH9: 3 | DI9: 3 | DJ9: 3 | DK9: 2 | DL9: 継続使用 | DM9: - | DN9: 無 | DO9: - | DP9: - | DQ9: - | DR9: 1 | DS9: 1 | DT9: 開発/品管 | DU9: 1次 | DV9: A | DW9: A | DX9: 0.5 | DY9: 1
A10: 45757 | B10: 近藤雅人 | C10: - | D10: 研究開発部 | E10: 研究開発課 | F10: - | G10: 026 | H10: kondou | I10: ○ | J10: B | K10: 4 | L10: 4 | M10: 2 | N10: 4 | O10: 2 | P10: 2 | Q10: 1 | R10: 1 | S10: 4 | T10: 4 | U10: 3 | V10: 4 | W10: 2 | X10: 4 | Y10: 1 | Z10: 32400000 | AA10: 32.4 | AB10: 4 | AC10: 3 | AD10: 3 | AE10: 3 | AF10: 3 | AG10: 2 | AH10: 1 | AI10: 3 | AJ10: 3 | AK10: 3 | AL10: 1 | AM10: 4 | AN10: 4 | AO10: 4 | AP10: 1 | AQ10: 3 | AR10: 1 | AS10: 1 | AT10: 2 | AU10: 1 | AV10: 1 | AW10: 1 | AX10: - | AY10: 0.618 | AZ10: 0.62 | BA10: 1522 | BB10: 104 | BC10: 0.119 | BD10: 546 | BE10: 16 | BF10: 33.139 | BG10: 2068 | BH10: 120 | BI10: - | BJ10: 1 | BK10: 2 | BL10: 1 | BM10: 1 | BN10: 1 | BO10: SSC-CL-5-3F-02 | BP10: コスメラボラトリー | BQ10: 3F/事務所 | BR10: - | BS10: - | BT10: - | BU10: - | BV10: 1 | BW10: ↓(ローカル側からコピペしてください。) | BX10: DESKTOP-8FJR97J | BY10: Intel(R) Core(TM) i5-6500 CPU @ 3.20GHz 3.19 GHz | BZ10: 8.00 GB (7.89 GB 使用可能) | CA10: BA6887F7-F4DB-43ED-9B72-6BB468C5874B | CB10: 00330-50563-14772-AAOEM | CC10: 64 ビット オペレーティング システム、x64 ベース プロセッサ | CD10: このディスプレイでは、ペン入力とタッチ入力は利用できません | CE10: ↓(ローカル側からコピペしてください。) | CF10: Windows 11 Pro | CG10: 23H2 | CH10: ‎2024/‎07/‎09 | CI10: 22631.519 | CJ10: 表記なし | CK10: Windows 機能エクスペリエンス パック 1000.22700.1077.0 | CL10: 2 | CM10: 1 | CN10: 1 | CO10: - | CP10: 1 | CQ10: 1 | CR10: 1 | CS10: 4 | CT10: 1 | CU10: 4 | CV10: 3 | CW10: 4 | CX10: 1 | CY10: 1 | CZ10: 1 | DA10: 1 | DB10: 1 | DC10: 1 | DD10: 1 | DE10: 1 | DF10: 4 | DG10: 1 | DH10: 1 | DI10: 1 | DJ10: 1 | DK10: 1 | DL10: 買替 | DN10: 無 | DO10: - | DP10: デスクトップ | DQ10: 標準性能 | DR10: 1 | DS10: 1 | DT10: 開発/品管 | DU10: 1次 | DV10: A | DW10: C | DX10: 1 | DY10: 1 | DZ10: 共有フォルダの権限を把握しておらず、アクセス権限があるかもしれないですが、使用しないものは「１」とさせていただいています。
A11: 45756 | B11: 宗近倶枝 | C11: - | D11: 研究開発部 | E11: 研究開発課 | F11: - | G11: 024 | H11: munechika | I11: ○ | J11: B | K11: 4 | L11: 4 | M11: 2 | N11: 4 | O11: 2 | P11: 2 | Q11: 3 | R11: 3 | S11: 4 | T11: 4 | U11: 4 | V11: 4 | W11: 3 | X11: 4 | Y11: 1 | Z11: 31300000 | AA11: 31.3 | AB11: 4 | AC11: 4 | AD11: 1 | AE11: 4 | AF11: 4 | AG11: 2 | AH11: 1 | AI11: 4 | AJ11: 4 | AK11: 2 | AL11: 4 | AM11: 3 | AN11: 2 | AO11: 2 | AP11: 1 | AQ11: 1 | AR11: 2 | AS11: 2 | AT11: 1 | AU11: 1 | AV11: 1 | AW11: 1 | AX11: - | AY11: 44 | AZ11: 44.2 | BA11: 69859 | BB11: 12310 | BC11: 2.72 | BD11: 3140 | BE11: 162 | BF11: 78.22 | BG11: 72999 | BH11: 12472 | BI11: - | BJ11: 1 | BK11: 1 | BL11: 1 | BM11: 2 | BN11: 3 | BO11: SSC-CL-5-3F-02 | BP11: コスメラボラトリー | BQ11: 3F/事務所 | BR11: - | BS11: - | BT11: - | BU11: - | BV11: 1 | BW11: ↓(ローカル側からコピペしてください。) | BX11: shinko | BY11: 11th Gen Intel(R) Core(TM) i5-1135G7 @ 2.40GHz 2.42 GHz | BZ11: 8.00 GB (7.80 GB 使用可能) | CA11: EFDECAF8-D59F-4D5B-AE77-730C72783F3C | CB11: 00342-20880-39352-AAOEM | CC11: 64 ビット オペレーティング システム、x64 ベース プロセッサ | CD11: このディスプレイでは、ペン入力とタッチ入力は利用できません | CE11: ↓(ローカル側からコピペしてください。) | CF11: Windows 11 Home | CG11: 24H2 | CH11: ‎2025/‎01/‎28 | CI11: 26100.319 | CJ11: PF3J6F1M | CK11: Windows 機能エクスペリエンス パック 1000.26100.48.0 | CL11: 1 | CM11: 1 | CN11: 1 | CO11: - | CP11: 1 | CQ11: 1 | CR11: 1 | CS11: 4 | CT11: 2 | CU11: 1 | CV11: 3 | CW11: 4 | CX11: 1 | CY11: 1 | CZ11: 1 | DA11: 2 | DB11: 1 | DC11: 1 | DD11: 1 | DE11: 2 | DF11: 4 | DG11: 2 | DH11: 1 | DI11: 2 | DJ11: 2 | DK11: 1 | DL11: 継続使用 | DM11: - | DN11: 無 | DO11: - | DP11: - | DQ11: - | DR11: 1 | DS11: 1 | DT11: 開発/品管 | DU11: 1次 | DV11: A | DW11: C | DX11: 1 | DY11: 1
A12: 45757 | B12: 山下基宏 | C12: - | D12: 研究開発部 | E12: 研究開発課 | F12: - | G12: 039 | H12: yasuda2 | I12: ○ | J12: B | K12: 4 | L12: 3 | M12: 2 | N12: 4 | O12: 2 | P12: 2 | Q12: 1 | R12: 1 | S12: 3 | T12: 4 | U12: 3 | V12: 4 | W12: 2 | X12: 3 | Y12: 1 | Z12: 32253161 | AA12: 32.253161 | AB12: 4 | AC12: 3 | AD12: 2 | AE12: 3 | AF12: 4 | AG12: 1 | AH12: 1 | AI12: 2 | AJ12: 3 | AK12: 1 | AL12: 1 | AM12: 3 | AN12: 1 | AO12: 1 | AP12: 1 | AQ12: 1 | AR12: 1 | AS12: 1 | AT12: 1 | AU12: 1 | AV12: 1 | AW12: 1 | AX12: - | AY12: 40.7 | AZ12: 40.8 | BA12: 58440 | BB12: 15204 | BC12: 0.423 | BD12: 707 | BE12: 5 | BF12: 73.476161 | BG12: 59147 | BH12: 15209 | BI12: - | BJ12: 2 | BK12: 2 | BL12: 2 | BM12: 1 | BN12: 1 | BO12: SSC-CL-5-3F-02 | BP12: コスメラボラトリー | BQ12: 3F/事務所 | BR12: - | BS12: - | BT12: - | BU12: - | BV12: 1 | BW12: ↓(ローカル側からコピペしてください。) | BX12: DESKTOP-HLEJEO5 | BY12: Intel(R) Core(TM) i5-6500 CPU @ 3.20GHz 3.19 GHz | BZ12: 8.00 GB (7.87 GB 使用可能) | CA12: 8950DB7C-476F-42D0-95DD-132C4A9F6F91 | CB12: 00342-50204-35151-AAOEM | CC12: 64 ビット オペレーティング システム、x64 ベース プロセッサ | CD12: このディスプレイでは、ペン入力とタッチ入力は利用できません | CE12: ↓(ローカル側からコピペしてください。) | CF12: Windows 11 Pro | CG12: 24H2 | CH12: 2024/‎10/‎04 | CI12: 26100.377 | CJ12: 表記なし | CK12: 1000.26100.66.0 | CL12: 1 | CM12: 1 | CN12: 1 | CO12: - | CP12: 1 | CQ12: 1 | CR12: 1 | CS12: 4 | CT12: 1 | CU12: 1 | CV12: 2 | CW12: 3 | CX12: 1 | CY12: 1 | CZ12: 1 | DA12: 1 | DB12: 1 | DC12: 1 | DD12: 1 | DE12: 1 | DF12: 3 | DG12: 1 | DH12: 1 | DI12: 1 | DJ12: 1 | DK12: 1 | DL12: 買替 | DN12: 無 | DO12: - | DP12: デスクトップ | DQ12: 標準性能 | DR12: 1 | DS12: 1 | DT12: 開発/品管 | DU12: 1次 | DV12: A | DW12: C | DX12: 1 | DY12: 1 | DZ12: 一日も早いネット環境の復興をお祈りしております。
A13: 45755 | B13: 直木美佐子 | C13: - | D13: 研究開発部 | E13: 研究開発課 | F13: - | G13: 041 | H13: naoki | I13: ○ | J13: B | K13: 4 | L13: 4 | M13: 2 | N13: 2 | O13: 2 | P13: 3 | Q13: 3 | R13: 3 | S13: 2 | T13: 4 | U13: 4 | V13: 4 | W13: 3 | X13: 2 | Y13: 1 | Z13: 22343611 | AA13: 22.343611 | AB13: 4 | AC13: 4 | AD13: 3 | AE13: 4 | AF13: 3 | AG13: 3 | AH13: 1 | AI13: 4 | AJ13: 3 | AK13: 2 | AL13: 4 | AM13: 3 | AN13: 2 | AO13: 1 | AP13: 1 | AQ13: 2 | AR13: 1 | AS13: 1 | AT13: 1 | AU13: 1 | AV13: 1 | AW13: 1 | AX13: - | AY13: 26.9 | AZ13: 27 | BA13: 70703 | BB13: 8231 | BC13: 0.0452 | BD13: 107 | BE13: 4 | BF13: 49.388811 | BG13: 70810 | BH13: 8235 | BI13: - | BJ13: 1 | BK13: 2 | BL13: 2 | BM13: 1 | BN13: 4 | BO13: SSC-CL-5-3F-02 | BP13: コスメラボラトリー | BQ13: 3F/事務所 | BR13: - | BS13: - | BT13: - | BU13: - | BV13: 1 | BW13: ↓(ローカル側からコピペしてください。) | BX13: DESKTOP-HLEJEO5 | BY13: Intel(R) Core(TM) i5-6500 CPU @ 3.20GHz 3.19 GHz | BZ13: 8.00 GB (7.87 GB 使用可能) | CA13: 8950DB7C-476F-42D0-95DD-132C4A9F6F91 | CB13: 00330-50878-51163-AAOEM | CC13: 64 ビット オペレーティング システム、x64 ベース プロセッサ | CD13: このディスプレイでは、ペン入力とタッチ入力は利用できません | CE13: ↓(ローカル側からコピペしてください。) | CF13: Windows 11 Pro | CG13: 24H2 | CH13: 2024/‎10/‎04 | CI13: 26100.348 | CJ13: 表記なし | CK13: Windows 機能エクスペリエンス パック 1000.26100.54.0 | CL13: 1 | CM13: 1 | CN13: 1 | CO13: - | CP13: 1 | CQ13: 1 | CR13: 1 | CS13: 4 | CT13: 3 | CU13: 1 | CV13: 3 | CW13: 4 | CX13: 1 | CY13: 1 | CZ13: 1 | DA13: 2 | DB13: 1 | DC13: 1 | DD13: 1 | DE13: 3 | DF13: 4 | DG13: 2 | DH13: 2 | DI13: 2 | DJ13: 2 | DK13: 2 | DL13: 買替 | DN13: 無 | DO13: - | DP13: デスクトップ | DQ13: 標準性能 | DR13: 1 | DS13: 1 | DT13: 開発/品管 | DU13: 1次 | DV13: A | DW13: C | DX13: 1 | DY13: 1
A14: 45756 | B14: 津田宝加 | C14: - | D14: 研究開発部 | E14: 研究開発課 | F14: - | G14: 071 | H14: tsuda | I14: ○ | J14: B | K14: 4 | L14: 4 | M14: 3 | N14: 3 | O14: 3 | P14: 4 | Q14: 4 | R14: 3 | S14: 2 | T14: 4 | U14: 4 | V14: 4 | W14: 3 | X14: 3 | Y14: 1 | Z14: 6540521 | AA14: 6.540521 | AB14: 4 | AC14: 4 | AD14: 3 | AE14: 3 | AF14: 3 | AG14: 2 | AH14: 1 | AI14: 4 | AJ14: 4 | AK14: 1 | AL14: 3 | AM14: 3 | AN14: 3 | AO14: 1 | AP14: 1 | AQ14: 3 | AR14: 1 | AS14: 1 | AT14: 1 | AU14: 1 | AV14: 1 | AW14: 1 | AX14: - | AY14: 14.8 | AZ14: 15 | BA14: 61683 | BB14: 4581 | BC14: 0.0292 | BD14: 84 | BE14: 11 | BF14: 21.569721 | BG14: 61767 | BH14: 4592 | BI14: - | BJ14: 1 | BK14: 2 | BL14: 1 | BM14: 1 | BN14: 1 | BO14: SSC-CL-5-3F-02 | BP14: コスメラボラトリー | BQ14: 3F/事務所 | BR14: - | BS14: - | BT14: - | BU14: - | BV14: 1 | BW14: ↓(ローカル側からコピペしてください。) | BX14: DESKTOP-HLEJEO5 | BY14: Intel(R) Core(TM) i5-6500 CPU @ 3.20GHz 3.19 GHz | BZ14: 8.00 GB (7.87 GB 使用可能) | CA14: 8950DB7C-476F-42D0-95DD-132C4A9F6F91 | CB14: 00330-51306-26263-AAOEM | CC14: 64 ビット オペレーティング システム、x64 ベース プロセッサ | CD14: このディスプレイでは、ペン入力とタッチ入力は利用できません | CE14: ↓(ローカル側からコピペしてください。) | CF14: Windows 11 Pro | CG14: 24H2 | CH14: 2024/‎10/‎04 | CI14: 26100.348 | CJ14: 表記なし | CK14: Windows 機能エクスペリエンス パック 1000.26100.54.0 | CL14: 1 | CM14: 1 | CN14: 1 | CO14: - | CP14: 1 | CQ14: 1 | CR14: 1 | CS14: 4 | CT14: 2 | CU14: 1 | CV14: 3 | CW14: 4 | CX14: 1 | CY14: 1 | CZ14: 1 | DA14: 2 | DB14: 1 | DC14: 1 | DD14: 1 | DE14: 2 | DF14: 3 | DG14: 1 | DH14: 1 | DI14: 1 | DJ14: 1 | DK14: 2 | DL14: 買替 | DN14: 無 | DO14: - | DP14: デスクトップ | DQ14: 標準性能 | DR14: 1 | DS14: 1 | DT14: 開発/品管 | DU14: 1次 | DV14: A | DW14: C | DX14: 1 | DY14: 1
A15: 45756 | B15: 矢野恵 | C15: - | D15: 研究開発部 | E15: 研究開発課 | F15: - | G15: 092 | H15: yano | I15: ○ | J15: B | K15: 4 | L15: 4 | M15: 2 | N15: 3 | O15: 3 | P15: 3 | Q15: 3 | R15: 3 | S15: 2 | T15: 4 | U15: 4 | V15: 4 | W15: 2 | X15: 2 | Y15: 1 | Z15: 6596073 | AA15: 6.596073 | AB15: 4 | AC15: 4 | AD15: 1 | AE15: 2 | AF15: 3 | AG15: 1 | AH15: 1 | AI15: 4 | AJ15: 4 | AK15: 1 | AL15: 1 | AM15: 3 | AN15: 2 | AO15: 2 | AP15: 1 | AQ15: 1 | AR15: 2 | AS15: 1 | AT15: 1 | AU15: 1 | AV15: 1 | AW15: 1 | AX15: - | AY15: 12.6 | AZ15: 12.7 | BA15: 41458 | BB15: 2937 | BC15: 0.13 | BD15: 430 | BE15: 7 | BF15: 19.426073 | BG15: 41888 | BH15: 2944 | BI15: - | BJ15: 1 | BK15: 2 | BL15: 1 | BM15: 1 | BN15: 1 | BO15: SSC-CL-5-3F-02 | BP15: コスメラボラトリー | BQ15: 3F/事務所 | BR15: - | BS15: - | BT15: - | BU15: - | BV15: 1 | BW15: ↓(ローカル側からコピペしてください。) | BX15: DESKTOP-HLEJEO5 | BY15: Intel(R) Core(TM) i5-6500 CPU @ 3.20GHz 3.19 GHz | BZ15: 8.00 GB (7.89 GB 使用可能) | CA15: 8950DB7C-476F-42D0-95DD-132C4A9F6F91 | CB15: 00330-51273-09376-AAOEM | CC15: 64 ビット オペレーティング システム、x64 ベース プロセッサ | CD15: このディスプレイでは、ペン入力とタッチ入力は利用できません | CE15: ↓(ローカル側からコピペしてください。) | CF15: Windows 11 Pro | CG15: 24H2 | CH15: ‎2024/‎10/‎04 | CI15: 26100.348 | CJ15: 表記なし | CK15: Windows 機能エクスペリエンス パック 1000.26100.54.0 | CL15: 1 | CM15: 1 | CN15: 1 | CO15: - | CP15: 1 | CQ15: 1 | CR15: 1 | CS15: 4 | CT15: 1 | CU15: 1 | CV15: 2 | CW15: 3 | CX15: 1 | CY15: 1 | CZ15: 1 | DA15: 1 | DB15: 1 | DC15: 1 | DD15: 1 | DE15: 2 | DF15: 3 | DG15: 2 | DH15: 2 | DI15: 2 | DJ15: 2 | DK15: 2 | DL15: 買替 | DN15: 無 | DO15: - | DP15: デスクトップ | DQ15: 標準性能 | DR15: 1 | DS15: 1 | DT15: 開発/品管 | DU15: 1次 | DV15: A | DW15: C | DX15: 1 | DY15: 1
A16: 45757 | B16: 橋口千聖 | C16: - | D16: 研究開発部 | E16: 研究開発課 | F16: - | G16: 124 | H16: hashiguchi | I16: ○ | J16: B | K16: 4 | L16: 4 | M16: 2 | N16: 4 | O16: 1 | P16: 3 | Q16: 3 | R16: 4 | S16: 4 | T16: 4 | U16: 4 | V16: 4 | W16: 2 | X16: 4 | Y16: 1 | Z16: 3019169 | AA16: 3.019169 | AB16: 4 | AC16: 4 | AD16: 1 | AE16: 4 | AF16: 2 | AG16: 2 | AH16: 1 | AI16: 4 | AJ16: 4 | AK16: 1 | AL16: 4 | AM16: 3 | AN16: 2 | AO16: 2 | AP16: 1 | AQ16: 1 | AR16: 1 | AS16: 1 | AT16: 1 | AU16: 1 | AV16: 1 | AW16: 1 | AX16: - | AY16: 8.52 | AZ16: 8.6 | BA16: 42183 | BB16: 5582 | BC16: 0.0154 | BD16: 84 | BE16: 5 | BF16: 11.634569 | BG16: 42267 | BH16: 5587 | BI16: - | BJ16: 1 | BK16: 2 | BL16: 2 | BM16: 1 | BN16: 4 | BO16: SSC-CL-5-3F-03 | BP16: コスメラボラトリー | BQ16: 3F/試験室 | BR16: - | BS16: - | BT16: - | BU16: - | BV16: 2 | BW16: ↓(ローカル側からコピペしてください。) | BX16: DESKTOP-HLEJEO5 | BY16: Intel(R) Core(TM) i5-6500 CPU @ 3.20GHz 3.19 GHz | BZ16: 8.00 GB (7.87 GB 使用可能) | CA16: 8950DB7C-476F-42D0-95DD-132C4A9F6F91 | CB16: 00330-50712-99403-AAOEM | CC16: 64 ビット オペレーティング システム、x64 ベース プロセッサ | CD16: このディスプレイでは、ペン入力とタッチ入力は利用できません | CE16: ↓(ローカル側からコピペしてください。) | CF16: Windows 11 Pro | CG16: 24H2 | CH16: 2024/‎10/‎04 | CI16: 26100.377 | CJ16: 表記なし | CK16: Windows 機能エクスペリエンス パック 1000.26100.66.0 | CL16: 1 | CM16: 1 | CN16: 1 | CO16: - | CP16: 1 | CQ16: 1 | CR16: 1 | CS16: 4 | CT16: 1 | CU16: 1 | CV16: 1 | CW16: 4 | CX16: 1 | CY16: 1 | CZ16: 1 | DA16: 1 | DB16: 1 | DC16: 1 | DD16: 1 | DE16: 1 | DF16: 3 | DG16: 1 | DH16: 1 | DI16: 1 | DJ16: 1 | DK16: 1 | DL16: 買替 | DN16: 無 | DO16: - | DP16: デスクトップ | DQ16: 標準性能 | DR16: 1 | DS16: 1 | DT16: 開発/品管 | DU16: 1次 | DV16: A | DW16: C | DX16: 1 | DY16: 1
A17: 45756 | B17: 西村穂乃果 | C17: - | D17: 品質保証部 | E17: 品質管理課 | F17: - | G17: 122 | H17: nishimura | I17: ○ | J17: B | K17: 4 | L17: 4 | M17: 2 | N17: 4 | O17: 3 | P17: 3 | Q17: 3 | R17: 1 | S17: 3 | T17: 4 | U17: 4 | V17: 2 | W17: 2 | X17: 2 | Y17: 1 | Z17: 3000073 | AA17: 3.000073 | AB17: 4 | AC17: 4 | AD17: 1 | AE17: 2 | AF17: 2 | AG17: 1 | AH17: 1 | AI17: 2 | AJ17: 3 | AK17: 1 | AL17: 2 | AM17: 3 | AN17: 3 | AO17: 2 | AP17: 1 | AQ17: 3 | AR17: 1 | AS17: 1 | AT17: 1 | AU17: 1 | AV17: 1 | AW17: 1 | AX17: - | AY17: 6.9 | AZ17: 7.08 | BA17: 41771 | BB17: 2294 | BC17: - | BD17: - | BE17: - | BF17: 10.080073 | BG17: 41771 | BH17: 2294 | BI17: - | BJ17: 1 | BK17: 2 | BL17: 1 | BM17: 1 | BN17: 1 | BO17: SSC-CL-5-3F-02 | BP17: コスメラボラトリー | BQ17: 3F/事務所 | BR17: - | BS17: - | BT17: - | BU17: - | BV17: 1 | BW17: ↓(ローカル側からコピペしてください。) | BX17: DESKTOP-HLEJEO5 | BY17: Intel(R) Core(TM) i5-6500 CPU @ 3.20GHz 3.19 GHz | BZ17: 8.00 GB (7.87 GB 使用可能) | CA17: 8950DB7C-476F-42D0-95DD-132C4A9F6F91 | CB17: 00330-50878-51194-AAOEM | CC17: 64 ビット オペレーティング システム、x64 ベース プロセッサ | CD17: このディスプレイでは、ペン入力とタッチ入力は利用できません | CE17: ↓(ローカル側からコピペしてください。) | CF17: Windows 11 Pro | CG17: 24H2 | CH17: ‎2024/‎10/‎04 | CI17: 26100.348 | CJ17: 表記なし | CK17: Windows 機能エクスペリエンス パック 1000.26100.54.0 | CL17: 1 | CM17: 1 | CN17: 1 | CO17: - | CP17: 1 | CQ17: 1 | CR17: 1 | CS17: 4 | CT17: 2 | CU17: 1 | CV17: 4 | CW17: 4 | CX17: 1 | CY17: 1 | CZ17: 1 | DA17: 2 | DB17: 1 | DC17: 1 | DD17: 1 | DE17: 2 | DF17: 3 | DG17: 2 | DH17: 1 | DI17: 2 | DJ17: 2 | DK17: 2 | DL17: 買替 | DN17: 無 | DO17: - | DP17: デスクトップ | DQ17: 標準性能 | DR17: 1 | DS17: 1 | DT17: 開発/品管 | DU17: 1次 | DV17: A | DW17: C | DX17: 1 | DY17: 1
A18: 45755 | B18: 野村秀太朗 | C18: - | D18: 品質保証部 | E18: 品質管理課 | F18: - | G18: 048 | H18: nomura | I18: ○ | J18: B | K18: 4 | L18: 4 | M18: 2 | N18: 1 | O18: 2 | P18: 1 | Q18: 3 | R18: 1 | S18: 1 | T18: 4 | U18: 4 | V18: 4 | W18: 3 | X18: 1 | Y18: 1 | Z18: 8384496 | AA18: 8.384496 | AB18: 4 | AC18: 4 | AD18: 1 | AE18: 1 | AF18: 4 | AG18: 1 | AH18: 1 | AI18: 4 | AJ18: 4 | AK18: 1 | AL18: 1 | AM18: 3 | AN18: 1 | AO18: 1 | AP18: 1 | AQ18: 1 | AR18: 3 | AS18: 1 | AT18: 1 | AU18: 1 | AV18: 1 | AW18: 1 | AX18: - | AY18: 12 | AZ18: 12.2 | BA18: 61639 | BB18: 6504 | BC18: 0.413 | BD18: 408 | BE18: 43 | BF18: 20.997496 | BG18: 62047 | BH18: 6547 | BI18: - | BJ18: 2 | BK18: 1 | BL18: 2 | BM18: 2 | BN18: 3 | BO18: SSC-5-3F-01 | BP18: 本社 | BQ18: 3F/シンク前 | BR18: - | BS18: - | BT18: - | BU18: - | BV18: 1 | BW18: ↓(ローカル側からコピペしてください。) | BX18: shinko | BY18: 11th Gen Intel(R)Core(TM)i5-1135G7@2.40GHz 2.42GHz | BZ18: 8.00GB(7.80GB使用可能) | CA18: 0FA98B57-3719-4DF2-B3EF-7C0CCD4C11C4 | CB18: 00342-20880-33152-AAOEM | CC18: 64ビット オペレーティング システム、x64ベース プロセッサ | CD18: このディスプレイでは、ペン入力とタッチ入力は利用できません。 | CE18: ↓(ローカル側からコピペしてください。) | CF18: Windows 11 Home | CG18: 24H2 | CH18: 45687 | CI18: 26100.348 | CJ18: PF3J403V | CK18: Windows 機能エクスペリエンス パック 1000.26100.54.0 | CL18: 1 | CM18: 1 | CN18: 1 | CO18: - | CP18: 1 | CQ18: 1 | CR18: 1 | CS18: 4 | CT18: 4 | CU18: 1 | CV18: 4 | CW18: 2 | CX18: 2 | CY18: 1 | CZ18: 1 | DA18: 2 | DB18: 1 | DC18: 1 | DD18: 1 | DE18: 2 | DF18: 4 | DG18: 4 | DH18: 1 | DI18: 2 | DJ18: 2 | DK18: 2 | DL18: 継続使用 | DM18: - | DN18: 無 | DO18: - | DP18: - | DQ18: - | DR18: 1 | DS18: 1 | DT18: 仕様書 | DU18: 2次 | DV18: A | DW18: A | DX18: 1 | DY18: 1
A19: 45755 | B19: 井上幸哉 | C19: - | D19: 品質保証部 | E19: 品質管理課 | F19: - | G19: 097 | H19: inoue | I19: ○ | J19: B | K19: 4 | L19: 4 | M19: 2 | N19: 3 | O19: 3 | P19: 3 | Q19: 2 | R19: 3 | S19: 1 | T19: 4 | U19: 4 | V19: 4 | W19: 4 | X19: 2 | Y19: 1 | Z19: 2908561 | AA19: 2.908561 | AB19: 4 | AC19: 4 | AD19: 4 | AE19: 3 | AF19: 4 | AG19: 1 | AH19: 1 | AI19: 4 | AJ19: 4 | AK19: 3 | AL19: 1 | AM19: 3 | AN19: 1 | AO19: 1 | AP19: 1 | AQ19: 1 | AR19: 3 | AS19: 1 | AT19: 1 | AU19: 1 | AV19: 1 | AW19: 1 | AX19: - | AY19: 7.68 | AZ19: 7.74 | BA19: 36827 | BB19: 2886 | BC19: 0.00175 | BD19: 3 | BE19: 0 | BF19: 10.650311 | BG19: 36830 | BH19: 2886 | BI19: - | BJ19: 1 | BK19: 2 | BL19: 2 | BM19: 1 | BN19: 1 | BO19: SSC-5-3F-01 | BP19: 本社 | BQ19: 3F/シンク前 | BR19: - | BS19: - | BT19: - | BU19: - | BV19: 1 | BW19: ↓(ローカル側からコピペしてください。) | BX19: DESKTOP-PMA0095 | BY19: Intel(R) Celeron(R) CPU J3355 @ 2.00GHz 2.00 GHz | BZ19: 8.00 GB (7.86 GB 使用可能) | CA19: 57DA6298-EADD-4294-8144-E54043118AD0 | CB19: 00325-80906-55912-AAOEM | CC19: 64 ビット オペレーティング システム、x64 ベース プロセッサ | CD19: このディスプレイでは、ペン入力とタッチ入力は利用できません | CE19: ↓(ローカル側からコピペしてください。) | CF19: Windows 10 Home | CG19: 22H2 | CH19: 2021/‎02/‎10 | CI19: 19045.561 | CJ19: DTB6MSJ00273702DFF3000 | CK19: Windows Feature Experience Pack 1000.19061.1000.0 | CL19: 1 | CM19: 1 | CN19: 1 | CO19: - | CP19: 1 | CQ19: 1 | CR19: 1 | CS19: 4 | CT19: 4 | CU19: 1 | CV19: 4 | CW19: 4 | CX19: 3 | CY19: 1 | CZ19: 1 | DA19: 2 | DB19: 1 | DC19: 1 | DD19: 1 | DE19: 2 | DF19: 4 | DG19: 4 | DH19: 1 | DI19: 2 | DJ19: 1 | DK19: 2 | DL19: 買替 | DM19: 45943 | DN19: 無 | DO19: - | DP19: デスクトップ | DQ19: 標準性能 | DR19: 1 | DS19: 1 | DT19: 仕様書 | DU19: 2次 | DV19: A | DW19: A | DX19: 1 | DY19: 1 | DZ19: ローカル側のＯＳ起動時間ですが、事務所の中央にある複合機と繋がらなかった時は、再起動の時に10分以上かかりました。 プリンターのデバイスでエラーがずっと表示されていて、エラーを消すためにキューを開いて削除をしたが実行されなかった(原因も理由も不明)。 Accessは使いたいけど、シンクライアントでエクセルと連動すると、フリーズしそうで使ってない。 エクセルの数式が自動から手動に切り替わっていることがある。 本社の事務所はエアコンの風が直接当たり、体調を崩してる気がする。風向きとデスクの配置が悪い気がする（窓側は暑すぎるし寒すぎる。） 社内に向けてデータの受け渡しをメールですることが多いように感じます。全員が入れる掲示板的な「受け渡しフォルダ」があると便利だと思います。 ※１週間程度でデータが消えれば、容量を取らないかと思います。 ※営業の売上報告書の閲覧ができるように、個人がフレキシブルにフォルダを作れる感じ。
A20: 45755 | B20: 島田智章 | C20: - | D20: 技術製造部 | E20: 生産管理課 | F20: 生産管理 | G20: 022 | H20: shimada | I20: ○ | J20: A | K20: 4 | L20: 4 | M20: 3 | N20: 2 | O20: 3 | P20: 2 | Q20: 4 | R20: 1 | S20: 2 | T20: 4 | U20: 4 | V20: 4 | W20: 3 | X20: 3 | Y20: 1 | Z20: 29390993 | AA20: 29.390993 | AB20: 4 | AC20: 4 | AD20: 1 | AE20: 2 | AF20: 1 | AG20: 1 | AH20: 1 | AI20: 4 | AJ20: 4 | AK20: 1 | AL20: 2 | AM20: 4 | AN20: 2 | AO20: 2 | AP20: 2 | AQ20: 1 | AR20: 1 | AS20: 1 | AT20: 2 | AU20: 1 | AV20: 1 | AW20: 1 | AX20: - | AY20: 33.8 | AZ20: 33.9 | BA20: 50411 | BB20: 2210 | BC20: 0.0858 | BD20: 691 | BE20: 26 | BF20: 63.376793 | BG20: 51102 | BH20: 2236 | BI20: - | BJ20: 1 | BK20: 2 | BL20: 2 | BM20: 1 | BN20: 1 | BO20: SSC-5-3F-01 | BP20: 本社 | BQ20: 3F/シンク前 | BR20: - | BS20: - | BT20: - | BU20: - | BV20: 3 | BW20: ↓(ローカル側からコピペしてください。) | BX20: DESKTOP-GNL3HE7 | BY20: Intel(R) Core(TM) i3-10105 CPU @ 3.70GHz 3.70 GHz | BZ20: 4.00 GB (3.75 GB 使用可能) | CA20: 83024794-55E5-491E-A9CA-CA26AAD227E2 | CB20: 00342-21982-93221-AAOEM | CC20: 64 ビット オペレーティング システム、x64 ベース プロセッサ | CD20: このディスプレイでは、ペン入力とタッチ入力は利用できません | CE20: ↓(ローカル側からコピペしてください。) | CF20: Windows 11 Home | CG20: 24H2 | CH20: ‎2025/‎01/‎21 | CI20: 26100.348 | CJ20: CJD26N3 | CK20: Windows 機能エクスペリエンス パック 1000.26100.54.0 | CL20: 2 | CM20: 1 | CN20: 1 | CO20: - | CP20: 1 | CQ20: 3 | CR20: 1 | CS20: 1 | CT20: 3 | CU20: 2 | CV20: 2 | CW20: 3 | CX20: 1 | CY20: 2 | CZ20: 1 | DA20: 2 | DB20: 3 | DC20: 1 | DD20: 1 | DE20: 2 | DF20: 3 | DG20: 2 | DH20: 2 | DI20: 2 | DJ20: 2 | DK20: 2 | DL20: 継続使用 | DM20: - | DN20: 有 | DO20: 管理部送り状印刷用 | DP20: - | DQ20: - | DR20: 2 | DS20: 1 | DT20: TPiCS/仕様 | DU20: 1次 | DV20: A | DW20: A | DX20: 0.5 | DY20: 1
A21: 45754 | B21: 鳥山一洋 | C21: - | D21: 技術製造部 | E21: 生産管理課 | F21: 生産管理 | G21: 065 | H21: toriyama | I21: ○ | J21: A | K21: 4 | L21: 4 | M21: 3 | N21: 2 | O21: 3 | P21: 2 | Q21: 2 | R21: 2 | S21: 1 | T21: 4 | U21: 4 | V21: 3 | W21: 2 | X21: 2 | Y21: 1 | Z21: 10411057 | AA21: 10.411057 | AB21: 4 | AC21: 4 | AD21: 4 | AE21: 3 | AF21: 1 | AG21: 2 | AH21: 1 | AI21: 3 | AJ21: 3 | AK21: 1 | AL21: 2 | AM21: 4 | AN21: 4 | AO21: 4 | AP21: 1 | AQ21: 1 | AR21: 1 | AS21: 1 | AT21: 1 | AU21: 1 | AV21: 1 | AW21: 1 | AX21: - | AY21: 15.4 | AZ21: 15.5 | BA21: 25499 | BB21: 1940 | BC21: - | BD21: - | BE21: - | BF21: 25.911057 | BG21: 25499 | BH21: 1940 | BI21: - | BJ21: 1 | BK21: 2 | BL21: 1 | BM21: 1 | BN21: 1 | BO21: SSC-5-3F-01 | BP21: 本社 | BQ21: 3F/シンク前 | BR21: - | BS21: - | BT21: - | BU21: - | BV21: 1 | BW21: ↓(ローカル側からコピペしてください。) | BX21: DESKTOP-HTT8PPL | BY21: 12th Gen Intel(R) Core(TM) i5-12400 2.50 GHz | BZ21: 8.00 GB (7.68 GB 使用可能) | CA21: 986EB5DF-54F4-42AF-B0BB-C22745A9A845 | CB21: 00342-20989-95592-AAOEM | CC21: 64 ビット オペレーティング システム、x64 ベース プロセッサ | CD21: このディスプレイでは、ペン入力とタッチ入力は利用できません | CE21: ↓(ローカル側からコピペしてください。) | CF21: Windows 11 Home | CG21: 24H2 | CH21: ‎2024/‎12/‎25 | CI21: 26100.362 | CJ21: GM02G0BC | CK21: Windows 機能エクスペリエンス パック 1000.26100.66.0 | CL21: 2 | CM21: 1 | CN21: 1 | CO21: - | CP21: 1 | CQ21: 4 | CR21: 1 | CS21: 1 | CT21: 4 | CU21: 2 | CV21: 2 | CW21: 4 | CX21: 1 | CY21: 2 | CZ21: 1 | DA21: 1 | DB21: 3 | DC21: 1 | DD21: 1 | DE21: 2 | DF21: 4 | DG21: 4 | DH21: 1 | DI21: 2 | DJ21: 2 | DK21: 2 | DL21: 継続使用 | DM21: - | DN21: 無 | DO21: - | DP21: - | DQ21: - | DR21: 2 | DS21: 1 | DT21: TPiCS/製造 | DU21: 1次 | DV21: A | DW21: A | DX21: 0.5 | DY21: 1
A22: 45756 | B22: 馬場阿弥子 | C22: - | D22: 技術製造部 | E22: 生産管理課 | F22: 生産管理 | G22: 104 | H22: baba | I22: ○ | J22: A | K22: 4 | L22: 4 | M22: 2 | N22: 2 | O22: 3 | P22: 1 | Q22: 3 | R22: 3 | S22: 1 | T22: 4 | U22: 4 | V22: 4 | W22: 3 | X22: 3 | Y22: 1 | Z22: 14575721 | AA22: 14.575721 | AB22: 4 | AC22: 4 | AD22: 1 | AE22: 2 | AF22: 1 | AG22: 1 | AH22: 1 | AI22: 4 | AJ22: 4 | AK22: 1 | AL22: 2 | AM22: 4 | AN22: 3 | AO22: 2 | AP22: 2 | AQ22: 1 | AR22: 1 | AS22: 1 | AT22: 1 | AU22: 1 | AV22: 1 | AW22: 1 | AX22: - | AY22: 61 | AZ22: 100 | BA22: 32 | BB22: 1 | BC22: - | BD22: - | BE22: - | BF22: 114.57572 | BG22: 32 | BH22: 1 | BI22: - | BJ22: 1 | BK22: 1 | BL22: 1 | BM22: 1 | BN22: 2 | BO22: SSC-5-3F-01 | BP22: 本社 | BQ22: 3F/シンク前 | BR22: - | BS22: - | BT22: - | BU22: - | BV22: 1 | BW22: ↓(ローカル側からコピペしてください。) | BX22: DESKTOP-QCCI7DQ | BY22: Intel(R) Core(TM) i5-8350U CPU @ 1.70GHz 1.90 GHz | BZ22: 8.00 GB (7.88 GB 使用可能) | CA22: 85820924-B925-4E6F-BEF5-1A2CFD734C51 | CB22: 00330-80000-00000-AA857 | CC22: 64 ビット オペレーティング システム、x64 ベース プロセッサ | CD22: このディスプレイでは、ペン入力とタッチ入力は利用できません | CE22: ↓(ローカル側からコピペしてください。) | CF22: Windows 11 Pro | CG22: 24H2 | CH22: ‎2025/‎01/‎30 | CI22: 26100.348 | CJ22: 93002411A | CK22: Windows 機能エクスペリエンス パック 1000.26100.54.0 | CL22: 2 | CM22: 1 | CN22: 1 | CO22: - | CP22: 1 | CQ22: 4 | CR22: 1 | CS22: 1 | CT22: 2 | CU22: 2 | CV22: 3 | CW22: 4 | CX22: 1 | CY22: 2 | CZ22: 1 | DA22: 2 | DB22: 3 | DC22: 1 | DD22: 1 | DE22: 2 | DF22: 3 | DG22: 2 | DH22: 1 | DI22: 2 | DJ22: 2 | DK22: 2 | DL22: 継続使用 | DM22: - | DN22: 無 | DO22: - | DP22: - | DQ22: - | DR22: 2 | DS22: 1 | DT22: TPiCS/製造 | DU22: 1次 | DV22: A | DW22: A | DX22: 0.5 | DY22: 1
A23: 45756 | B23: 中島和哉 | C23: - | D23: 技術製造部 | E23: 生産管理課 | F23: 生産管理 | G23: 109 | H23: nakashima | I23: ○ | J23: A | K23: 4 | L23: 4 | M23: 2 | N23: 3 | O23: 3 | P23: 3 | Q23: 3 | R23: 2 | S23: 2 | T23: 4 | U23: 4 | V23: 3 | W23: 2 | X23: 2 | Y23: 1 | Z23: 13139747 | AA23: 13.139747 | AB23: 4 | AC23: 4 | AD23: 4 | AE23: 3 | AF23: 1 | AG23: 1 | AH23: 1 | AI23: 4 | AJ23: 4 | AK23: 1 | AL23: 1 | AM23: 3 | AN23: 4 | AO23: 4 | AP23: 1 | AQ23: 1 | AR23: 1 | AS23: 1 | AT23: 1 | AU23: 1 | AV23: 2 | AW23: 1 | AX23: - | AY23: 16.5 | AZ23: 16.5 | BA23: 21996 | BB23: 2192 | BC23: - | BD23: - | BE23: - | BF23: 29.639747 | BG23: 21996 | BH23: 2192 | BI23: - | BJ23: 1 | BK23: 2 | BL23: 2 | BM23: 1 | BN23: 1 | BO23: SSC-5-3F-01 | BP23: 本社 | BQ23: 3F/シンク前 | BR23: - | BS23: - | BT23: - | BU23: - | BV23: 3 | BW23: ↓(ローカル側からコピペしてください。) | BX23: DESKTOP-8F5M8F8 | BY23: Intel(R) Core(TM) i3-10105 CPU @ 3.70GHz 3.70 GHz | BZ23: 4.00 GB (3.75 GB 使用可能) | CA23: 43D584B0-0961-42BA-8ABD-0947A5E637B4 | CB23: 00342-21982-93229-AAOEM | CC23: 64 ビット オペレーティング システム、x64 ベース プロセッサ | CD23: ペンのサポート | CE23: ↓(ローカル側からコピペしてください。) | CF23: Windows 11 Home | CG23: 24H2 | CH23: ‎2025/‎01/‎31 | CI23: 26100.348 | CJ23: 3KD26N3 | CK23: Windows 機能エクスペリエンス パック 1000.26100.54.0 | CL23: 1 | CM23: 1 | CN23: 1 | CO23: - | CP23: 1 | CQ23: 4 | CR23: 1 | CS23: 1 | CT23: 2 | CU23: 2 | CV23: 2 | CW23: 4 | CX23: 1 | CY23: 2 | CZ23: 1 | DA23: 2 | DB23: 2 | DC23: 1 | DD23: 1 | DE23: 2 | DF23: 3 | DG23: 2 | DH23: 1 | DI23: 2 | DJ23: 2 | DK23: 2 | DL23: 継続使用 | DM23: - | DN23: 有 | DO23: 本社3F共用ノートPC | DP23: - | DQ23: - | DR23: 2 | DS23: 1 | DT23: TPiCS/製造 | DU23: 1次 | DV23: A | DW23: A | DX23: 0.5 | DY23: 1
A24: 45756 | B24: 東香里 | C24: - | D24: 技術製造部 | E24: 生産管理課 | F24: 生産管理事務 | G24: 082 | H24: azuma | I24: ○ | J24: A | K24: 4 | L24: 4 | M24: 2 | N24: 3 | O24: 3 | P24: 3 | Q24: 2 | R24: 2 | S24: 2 | T24: 4 | U24: 4 | V24: 4 | W24: 3 | X24: 4 | Y24: 1 | Z24: 17163849 | AA24: 17.163849 | AB24: 4 | AC24: 4 | AD24: 1 | AE24: 4 | AF24: 3 | AG24: 1 | AH24: 1 | AI24: 4 | AJ24: 4 | AK24: 2 | AL24: 4 | AM24: 4 | AN24: 4 | AO24: 1 | AP24: 2 | AQ24: 1 | AR24: 2 | AS24: 1 | AT24: 1 | AU24: 1 | AV24: 1 | AW24: 1 | AX24: - | AY24: 30.3 | AZ24: 30.5 | BA24: 61 | BB24: 7 | BC24: 0.0306 | BD24: 61 | BE24: 7 | BF24: 47.694449 | BG24: 122 | BH24: 14 | BI24: - | BJ24: 1 | BK24: 2 | BL24: 1 | BM24: 1 | BN24: 1 | BO24: SSC-5-3F-01 | BP24: 本社 | BQ24: 3F/シンク前 | BR24: - | BS24: - | BT24: - | BU24: - | BV24: 1 | BW24: ↓(ローカル側からコピペしてください。) | BX24: DESKTOP-QMHIKTF | BY24: Intel(R) Core(TM) i5-7500 CPU @ 3.40GHz 3.41 GHz | BZ24: 16.0 GB (15.9 GB 使用可能) | CA24: F3F61D24-EBFA-40C1-A0BA-07D6F8E0BBC4 | CB24: 00330-50491-75426-AAOEM | CC24: 64 ビット オペレーティング システム、x64 ベース プロセッサ | CD24: このディスプレイでは、ペン入力とタッチ入力は利用できません | CE24: ↓(ローカル側からコピペしてください。) | CF24: Windows 11 Pro | CG24: 22H2 | CH24: 2022/‎12/‎01 | CI24: 22621.432 | CJ24: 7384YJ2 | CK24: Windows Feature Experience Pack 1000.22700.1041.0 | CL24: 2 | CM24: 1 | CN24: 1 | CO24: - | CP24: 2 | CQ24: 2 | CR24: 2 | CS24: 1 | CT24: 4 | CU24: 2 | CV24: 2 | CW24: 4 | CX24: 2 | CY24: 2 | CZ24: 1 | DA24: 2 | DB24: 2 | DC24: 1 | DD24: 1 | DE24: 2 | DF24: 4 | DG24: 2 | DH24: 1 | DI24: 2 | DJ24: 2 | DK24: 2 | DL24: 買替 | DN24: 無 | DO24: - | DP24: デスクトップ | DQ24: 高性能 | DR24: 2 | DS24: 1 | DT24: TPiCS/仕様 | DU24: 1次 | DV24: A | DW24: A | DX24: 0.5 | DY24: 1 | DZ24: ・日によるがシャットダウンの際に時間がかかる(3～5分程)。開いていないアプリが開いているというエラーが出がち(すぐエラーのポップが消える為何のエラーか不明) 社用スマホ＝サンプル到着報告チャット用に DIGNO(旧島田主任)を使用、AndroidOS要注意
A25: 45756 | B25: 徳永彩花 | C25: - | D25: 技術製造部 | E25: 生産管理課 | F25: 生産管理事務 | G25: 087 | H25: tokunaga | I25: ○ | J25: A | K25: 4 | L25: 4 | M25: 2 | N25: 3 | O25: 3 | P25: 3 | Q25: 3 | R25: 2 | S25: 2 | T25: 4 | U25: 4 | V25: 3 | W25: 3 | X25: 2 | Y25: 1 | Z25: 16415137 | AA25: 16.415137 | AB25: 4 | AC25: 4 | AD25: 1 | AE25: 4 | AF25: 3 | AG25: 1 | AH25: 1 | AI25: 4 | AJ25: 4 | AK25: 2 | AL25: 2 | AM25: 4 | AN25: 4 | AO25: 1 | AP25: 2 | AQ25: 1 | AR25: 1 | AS25: 1 | AT25: 1 | AU25: 1 | AV25: 1 | AW25: 1 | AX25: - | AY25: 0.36 | AZ25: 0.36 | BA25: 513 | BB25: 76 | BC25: 0.365 | BD25: 513 | BE25: 76 | BF25: 17.140137 | BG25: 1026 | BH25: 152 | BI25: - | BJ25: 2 | BK25: 2 | BL25: 2 | BM25: 1 | BN25: 1 | BO25: SSC-5-3F-01 | BP25: 本社 | BQ25: 3F/シンク前 | BR25: - | BS25: - | BT25: - | BU25: - | BV25: 2 | BW25: ↓(ローカル側からコピペしてください。) | BX25: DESKTOP-S87U01J | BY25: Intel(R) Core(TM) i5-9400 CPU @ 2.90GHz 2.90 GHz | BZ25: 8.00 GB (7.84 GB 使用可能) | CA25: 21D3081B-9619-4765-95BD-5A2243034B9E | CB25: 00325-81519-70499-AAOEM | CC25: 64 ビット オペレーティング システム、x64 ベース プロセッサ | CD25: このディスプレイでは、ペン入力とタッチ入力は利用できません | CE25: ↓(ローカル側からコピペしてください。) | CF25: Windows 11 Home | CG25: 24H2 | CH25: ‎2025/‎01/‎30 | CI25: 26100.348 | CJ25: GN1P603 | CK25: Windows 機能エクスペリエンス パック 1000.26100.54.0 | CL25: 1 | CM25: 1 | CN25: 1 | CO25: - | CP25: 2 | CQ25: 3 | CR25: 2 | CS25: 1 | CT25: 3 | CU25: 2 | CV25: 2 | CW25: 3 | CX25: 2 | CY25: 2 | CZ25: 1 | DA25: 2 | DB25: 3 | DC25: 2 | DD25: 1 | DE25: 2 | DF25: 4 | DG25: 2 | DH25: 1 | DI25: 2 | DJ25: 2 | DK25: 2 | DL25: 継続使用 | DM25: - | DN25: 有 | DO25: 森尾直浩(共用) | DP25: - | DQ25: - | DR25: 2 | DS25: 1 | DT25: TPiCS/仕様 | DU25: 1次 | DV25: A | DW25: A | DX25: 0.5 | DY25: 1
A26: 45756 | B26: 北村優樹 | C26: - | D26: 技術製造部 | E26: 生産管理課 | F26: 物流 | G26: 060 | H26: kitamura | I26: × | J26: B | K26: 4 | L26: 4 | M26: 2 | N26: 2 | O26: 2 | P26: 2 | Q26: 3 | R26: 3 | S26: 2 | T26: 4 | U26: 4 | V26: 3 | W26: 2 | X26: 2 | Y26: 1 | Z26: 19567961 | AA26: 19.567961 | AB26: 4 | AC26: 4 | AD26: 1 | AE26: 1 | AF26: 1 | AG26: 1 | AH26: 1 | AI26: 2 | AJ26: 1 | AK26: 1 | AL26: 1 | AM26: 4 | AN26: 1 | AO26: 3 | AP26: 1 | AQ26: 1 | AR26: 1 | AS26: 1 | AT26: 1 | AU26: 1 | AV26: 1 | AW26: 1 | AX26: - | AY26: 21.4 | AZ26: 21.6 | BA26: 69193 | BB26: 2173 | BC26: 23.4 | BD26: 34070 | BE26: 2581 | BF26: 64.567961 | BG26: 103263 | BH26: 4754 | BI26: - | BJ26: 2 | BK26: 1 | BL26: 2 | BM26: 2 | BN26: 2 | BO26: SSC-CF-5-1F-01 | BP26: コスメファクトリー | BQ26: 1F/事務所 | BR26: - | BS26: - | BT26: - | BU26: - | BV26: 1 | BW26: ↓(ローカル側からコピペしてください。) | BX26: MyComputer | BY26: Intel(R) Core(TM) i5-7200U CPU @ 2.50GHz 2.70 GHz | BZ26: 8.00 GB | CA26: 1F1760A0-FE97-4548-B6B4-B9B88B60F02F | CB26: 00325-96203-16953-AAOEM | CC26: 64 ビット オペレーティング システム、x64 ベース プロセッサ | CD26: このディスプレイでは、ペン入力とタッチ入力は利用できません | CE26: ↓(ローカル側からコピペしてください。) | CF26: Windows 10 Home | CG26: 22H2 | CH26: 2021/‎01/‎18 | CI26: 19045.5608 | CJ26: NKN750BU0007G00109 | CK26: Windows Feature Experience Pack 1000.19061.1000.0 | CL26: 2 | CM26: 1 | CN26: 2 | CO26: - | CP26: 1 | CQ26: 2 | CR26: 1 | CS26: 1 | CT26: 1 | CU26: 4 | CV26: 2 | CW26: 3 | CX26: 1 | CY26: 2 | CZ26: 1 | DA26: 2 | DB26: 4 | DC26: 1 | DD26: 1 | DE26: 2 | DF26: 2 | DG26: 2 | DH26: 1 | DI26: 2 | DJ26: 2 | DK26: 2 | DL26: 買替 | DM26: 45943 | DN26: 無 | DO26: - | DP26: ノート | DQ26: 標準性能 | DR26: 1 | DS26: 1 | DT26: 仕様書 | DU26: 2次 | DV26: B | DW26: A | DX26: 0.5 | DY26: 1
A27: 45754 | B27: 池田悦彰 | C27: VivoBook | D27: 技術製造部 | E27: 生産管理課 | F27: 物流 | G27: 100 | H27: ikeda | I27: × | J27: B | K27: 4 | L27: 4 | M27: 2 | N27: 2 | O27: 2 | P27: 1 | Q27: 3 | R27: 2 | S27: 1 | T27: 4 | U27: 4 | V27: 2 | W27: 2 | X27: 2 | Y27: 1 | Z27: 13016793 | AA27: 13.016793 | AB27: 2 | AC27: 2 | AD27: 1 | AE27: 2 | AF27: 1 | AG27: 1 | AH27: 1 | AI27: 1 | AJ27: 1 | AK27: 1 | AL27: 1 | AM27: 4 | AN27: 1 | AO27: 3 | AP27: 1 | AQ27: 1 | AR27: 1 | AS27: 1 | AT27: 2 | AU27: 1 | AV27: 1 | AW27: 1 | AX27: - | AY27: 14.8 | AZ27: 14.9 | BA27: 31709 | BB27: 1896 | BC27: - | BD27: - | BE27: - | BF27: 27.916793 | BG27: 31709 | BH27: 1896 | BI27: - | BJ27: 2 | BK27: 3 | BL27: 1 | BM27: 2 | BN27: 2 | BO27: SSC-WH-5 | BP27: 第一倉庫 | BQ27: 1F/南西角 | BR27: - | BS27: - | BT27: - | BU27: - | BV27: 1 | BW27: ↓(ローカル側からコピペしてください。) | BX27: DESKTOP-9R2BC4C | BY27: Intel(R) Pentium(R) Silver N6000 @ 1.10GHz 1.11 GHz | BZ27: 8.00 GB (7.75 GB 使用可能) | CA27: 12295587-776B-4BE7-BDE0-5E4370AB6DDC | CB27: 00342-20769-22518-AAOEM | CC27: 64 ビット オペレーティング システム、x64 ベース プロセッサ | CD27: 10 タッチ ポイントでのペンとタッチのサポート | CE27: ↓(ローカル側からコピペしてください。) | CF27: Windows 11 Home | CG27: 24H2 | CH27: 2025/‎03/‎14 | CI27: 26100.348 | CJ27: MCN0CX13332050D | CK27: Windows 機能エクスペリエンス パック 1000.26100.54.0 | CL27: 2 | CM27: 2 | CN27: 2 | CO27: - | CP27: 1 | CQ27: 3 | CR27: 1 | CS27: 1 | CT27: 1 | CU27: 3 | CV27: 2 | CW27: 4 | CX27: 1 | CY27: 2 | CZ27: 1 | DA27: 2 | DB27: 3 | DC27: 1 | DD27: 1 | DE27: 2 | DF27: 2 | DG27: 2 | DH27: 1 | DI27: 2 | DJ27: 2 | DK27: 2 | DL27: - | DM27: - | DN27: - | DO27: - | DP27: - | DQ27: - | DR27: 1 | DS27: 1 | DT27: 仕様書 | DU27: 2次 | DV27: B | DW27: A | DX27: 0.5 | DY27: 1
A28: 45755 | B28: 森尾直浩 | C28: - | D28: 技術製造部 | E28: 生産管理課 | F28: 物流 | G28: 106 | H28: morio | I28: × | J28: B | K28: 4 | L28: 3 | M28: 2 | N28: 1 | O28: 2 | P28: 2 | Q28: 3 | R28: 2 | S28: 1 | T28: 4 | U28: 3 | V28: 1 | W28: 1 | X28: 1 | Y28: 1 | Z28: 11365857 | AA28: 11.365857 | AB28: 1 | AC28: 1 | AD28: 1 | AE28: 1 | AF28: 1 | AG28: 1 | AH28: 1 | AI28: 1 | AJ28: 1 | AK28: 1 | AL28: 1 | AM28: 2 | AN28: 1 | AO28: 3 | AP28: 1 | AQ28: 1 | AR28: 1 | AS28: 1 | AT28: 1 | AU28: 1 | AV28: 1 | AW28: 1 | AX28: - | AY28: 13.5 | AZ28: 13.6 | BA28: 51377 | BB28: 2710 | BC28: - | BD28: - | BE28: - | BF28: 24.965857 | BG28: 51377 | BH28: 2710 | BI28: - | BJ28: 2 | BK28: 1 | BL28: 2 | BM28: 1 | BN28: 1 | BO28: SSC-5-3F-01 | BP28: 本社 | BQ28: 3F/シンク前 | BR28: - | BS28: - | BT28: - | BU28: - | BV28: 1 | BW28: ↓(ローカル側からコピペしてください。) | BX28: MYCOMPUTER | BY28: Intel(R) Core(TM) i5-6300U CPU @ 2.40GHz 2.50 GHz | BZ28: 8.00 GB (7.87 GB 使用可能) | CA28: C1EA8D7D-E92C-4F1D-8261-8849D830E7C4 | CB28: 00325-84915-70670-AAOEM | CC28: 64 ビット オペレーティング システム、x64 ベース プロセッサ | CD28: このディスプレイでは、ペン入力とタッチ入力は利用できません | CE28: ↓(ローカル側からコピペしてください。) | CF28: Windows 10 Home | CG28: 22H2 | CH28: ‎2022/‎12/‎01 | CI28: 19045.561 | CJ28: MP1270XH | CK28: Windows Feature Experience Pack 1000.19061.1000.0 | CL28: 2 | CM28: 1 | CN28: 2 | CO28: - | CP28: 1 | CQ28: 2 | CR28: 1 | CS28: 1 | CT28: 1 | CU28: 2 | CV28: 2 | CW28: 3 | CX28: 1 | CY28: 2 | CZ28: 1 | DA28: 2 | DB28: 2 | DC28: 1 | DD28: 1 | DE28: 2 | DF28: 2 | DG28: 2 | DH28: 1 | DI28: 2 | DJ28: 2 | DK28: 2 | DL28: 買替 | DM28: 45943 | DN28: 有 | DO28: 徳永彩花 | DP28: デスクトップ | DQ28: 高性能 | DR28: 1 | DS28: 1 | DT28: 仕様書 | DU28: 2次 | DV28: B | DW28: A | DX28: 0.5 | DY28: 1
A29: 45756 | B29: 本社実績入力用タブレット | C29: mouse⑥ | D29: 技術製造部 | E29: 生産管理課 | F29: 生産管理 | G29: － | H29: － | I29: － | J29: - | K29: - | L29: - | M29: - | N29: - | O29: - | P29: - | Q29: - | R29: - | S29: - | T29: - | U29: - | V29: - | W29: - | X29: - | Y29: - | Z29: - | AA29: - | AB29: - | AC29: - | AD29: - | AE29: - | AF29: - | AG29: - | AH29: - | AI29: - | AJ29: - | AK29: - | AL29: - | AM29: - | AN29: - | AO29: - | AP29: - | AQ29: - | AR29: - | AS29: - | AT29: - | AU29: - | AV29: - | AW29: - | AX29: - | AY29: - | AZ29: - | BA29: - | BB29: - | BC29: - | BD29: - | BE29: - | BF29: 0 | BG29: 0 | BH29: 0 | BI29: - | BJ29: - | BK29: 3 | BL29: 1 | BM29: 2 | BN29: 2 | BO29: SSC-2-3F-01 | BP29: 本社 | BQ29: 3F/シンク前 | BR29: - | BS29: - | BT29: - | BU29: - | BV29: 1 | BW29: ↓(ローカル側からコピペしてください。) | BX29: DESKTOP-PD4HK2F | BY29: Intel(R) Celeron(R) N4100 CPU @ 1.10GHz 1.10 GHz | BZ29: 4.00 GB (3.83 GB 使用可能) | CA29: 77BC05F8-6531-463F-B032-375937D8E62E | CB29: 00330-54055-59709-AAOEM | CC29: 64 ビット オペレーティング システム、x64 ベース プロセッサ | CD29: 10 タッチ ポイントでのペンとタッチのサポート | CE29: ↓(ローカル側からコピペしてください。) | CF29: Windows 10 Pro | CG29: 22H2 | CH29: 44524 | CI29: 19045.441 | CJ29: U104910838 | CK29: Windows Feature Experience Pack 1000.19056.1000.0 | CL29: - | CM29: - | CN29: - | CO29: - | CP29: - | CQ29: - | CR29: - | CS29: - | CT29: - | CU29: - | CV29: - | CW29: - | CX29: - | CY29: - | CZ29: - | DA29: - | DB29: - | DC29: - | DD29: - | DE29: - | DF29: - | DG29: - | DH29: - | DI29: - | DJ29: - | DK29: - | DL29: - | DM29: - | DN29: - | DO29: - | DP29: - | DQ29: - | DR29: - | DS29: - | DT29: - | DU29: - | DV29: - | DW29: - | DX29: - | DY29: - | DZ29: 予備タブレット
A30: 45756 | B30: 幹部会議用タブレット(生産管理) | C30: Expert Book② | D30: 企画営業部 | E30: 企画課 | F30: - | G30: － | H30: － | I30: － | J30: - | K30: - | L30: - | M30: - | N30: - | O30: - | P30: - | Q30: - | R30: - | S30: - | T30: - | U30: - | V30: - | W30: - | X30: - | Y30: - | Z30: - | AA30: - | AB30: - | AC30: - | AD30: - | AE30: - | AF30: - | AG30: - | AH30: - | AI30: - | AJ30: - | AK30: - | AL30: - | AM30: - | AN30: - | AO30: - | AP30: - | AQ30: - | AR30: - | AS30: - | AT30: - | AU30: - | AV30: - | AW30: - | AX30: - | AY30: - | AZ30: - | BA30: - | BB30: - | BC30: - | BD30: - | BE30: - | BF30: 0 | BG30: 0 | BH30: 0 | BI30: - | BJ30: 2 | BK30: 3 | BL30: 1 | BM30: 2 | BN30: 2 | BO30: SSC-2-3F-01 | BP30: 本社 | BQ30: 3F/シンク前 | BR30: - | BS30: - | BT30: - | BU30: - | BV30: 1 | BW30: ↓(ローカル側からコピペしてください。) | BX30: DESKTOP-O080E3G | BY30: Snapdragon (TM) 7c @ 1.96 GHz 2.55 GHz | BZ30: 8.00 GB (7.67 GB 使用可能) | CA30: 424A3461-03FE-42B7-9DA8-6A8910485747 | CB30: 00356-07278-77032-AAOEM | CC30: 64 ビット オペレーティング システム、ARM ベース プロセッサ | CD30: ペンのサポート | CE30: ↓(ローカル側からコピペしてください。) | CF30: Windows 11 Home in S mode | CG30: 21H2 | CH30: ‎2022/‎10/‎18 | CI30: 22000.218 | CJ30: NANXNZ004797424 | CK30: Windows 機能エクスペリエンス パック 1000.22001.1000.0 | CL30: - | CM30: - | CN30: - | CO30: - | CP30: - | CQ30: - | CR30: - | CS30: - | CT30: - | CU30: - | CV30: - | CW30: - | CX30: - | CY30: - | CZ30: - | DA30: - | DB30: - | DC30: - | DD30: - | DE30: - | DF30: - | DG30: - | DH30: - | DI30: - | DJ30: - | DK30: - | DL30: - | DM30: - | DN30: - | DO30: - | DP30: - | DQ30: - | DR30: - | DS30: - | DT30: - | DU30: - | DV30: - | DW30: - | DX30: - | DY30: - | DZ30: 予備タブレット(幹部会議で使用)
A31: 45756 | B31: 本社3F共用ノートPC | C31: - | D31: 技術製造部 | E31: 生産管理課 | F31: 生産管理 | G31: － | H31: － | I31: － | J31: - | K31: - | L31: - | M31: - | N31: - | O31: - | P31: - | Q31: - | R31: - | S31: - | T31: - | U31: - | V31: - | W31: - | X31: - | Y31: - | Z31: - | AA31: - | AB31: - | AC31: - | AD31: - | AE31: - | AF31: - | AG31: - | AH31: - | AI31: - | AJ31: - | AK31: - | AL31: - | AM31: - | AN31: - | AO31: - | AP31: - | AQ31: - | AR31: - | AS31: - | AT31: - | AU31: - | AV31: - | AW31: - | AX31: - | AY31: - | AZ31: - | BA31: - | BB31: - | BC31: - | BD31: - | BE31: - | BF31: 0 | BG31: 0 | BH31: 0 | BI31: - | BJ31: 2 | BK31: 1 | BL31: 1 | BM31: 2 | BN31: 2 | BO31: SSC-2-3F-01 | BP31: 本社 | BQ31: 3F/シンク前 | BR31: - | BS31: - | BT31: - | BU31: - | BV31: 1 | BW31: ↓(ローカル側からコピペしてください。) | BX31: DESKTOP-IANPUMM | BY31: Intel(R) Core(TM) i5-4200M CPU @ 2.50GHz 2.49 GHz | BZ31: 4.00 GB (3.90 GB 使用可能) | CA31: A16C3D26-B2BB-40B8-8A3E-310AF5F823A7 | CB31: 00326-03521-57414-AAOEM | CC31: 64 ビット オペレーティング システム、x64 ベース プロセッサ | CD31: このディスプレイでは、ペン入力とタッチ入力は利用できません | CE31: ↓(ローカル側からコピペしてください。) | CF31: Windows 10 Home | CG31: 22H2 | CH31: ‎2021/‎02/‎17 | CI31: 19045.525 | CJ31: R902T493 | CK31: Windows Feature Experience Pack 1000.19060.1000.0 | CL31: - | CM31: - | CN31: - | CO31: - | CP31: - | CQ31: - | CR31: - | CS31: - | CT31: - | CU31: - | CV31: - | CW31: - | CX31: - | CY31: - | CZ31: - | DA31: - | DB31: - | DC31: - | DD31: - | DE31: - | DF31: - | DG31: - | DH31: - | DI31: - | DJ31: - | DK31: - | DL31: 買替 | DM31: 45943 | DN31: 有 | DO31: 中島和哉 | DP31: デスクトップ | DQ31: 高性能 | DR31: - | DS31: - | DT31: - | DU31: - | DV31: - | DW31: - | DX31: - | DY31: - | DZ31: 共用ノートPC
A32: 45756 | B32: 第一倉庫のタブレット現品票印刷用 | C32: LAVIE③ | D32: 技術製造部 | E32: 生産管理課 | F32: 物流 | G32: － | H32: － | I32: － | J32: - | K32: - | L32: - | M32: - | N32: - | O32: - | P32: - | Q32: - | R32: - | S32: - | T32: - | U32: - | V32: - | W32: - | X32: - | Y32: - | Z32: - | AA32: - | AB32: - | AC32: - | AD32: - | AE32: - | AF32: - | AG32: - | AH32: - | AI32: - | AJ32: - | AK32: - | AL32: - | AM32: - | AN32: - | AO32: 3 | AP32: - | AQ32: - | AR32: - | AS32: - | AT32: - | AU32: - | AV32: - | AW32: - | AX32: - | AY32: - | AZ32: - | BA32: - | BB32: - | BC32: - | BD32: - | BE32: - | BF32: 0 | BG32: 0 | BH32: 0 | BI32: - | BJ32: - | BK32: 3 | BL32: 1 | BM32: 2 | BN32: 2 | BO32: SSC-WH-5 | BP32: 第一倉庫 | BQ32: 1F/南西角 | BR32: - | BS32: - | BT32: - | BU32: - | BV32: - | BW32: ↓(ローカル側からコピペしてください。) | BX32: DESKTOP-03777E0 | BY32: Intel(R) Celeron(R) N4100 CPU @ 1.10GHz 1.10 GHz | BZ32: 4.00 GB (3.64 GB 使用可能) | CA32: 6299E529-C3BF-4E9B-B3D8-FA19A1DBD322 | CB32: 00330-53364-73406-AAOEM | CC32: 64 ビット オペレーティング システム、x64 ベース プロセッサ | CD32: 10 タッチ ポイントでのペンとタッチのサポート | CE32: ↓(ローカル側からコピペしてください。) | CF32: Windows 11 Pro | CG32: 24H2 | CH32: 45708 | CI32: 26100.348 | CJ32: 11006461F | CK32: Windows 機能エクスペリエンス パック 1000.26100.54.0 | CL32: - | CM32: - | CN32: - | CO32: - | CP32: - | CQ32: - | CR32: - | CS32: - | CT32: - | CU32: - | CV32: - | CW32: - | CX32: - | CY32: - | CZ32: - | DA32: - | DB32: - | DC32: - | DD32: - | DE32: - | DF32: - | DG32: - | DH32: - | DI32: - | DJ32: - | DK32: - | DL32: - | DM32: - | DN32: - | DO32: - | DP32: - | DQ32: - | DR32: - | DS32: - | DT32: - | DU32: - | DV32: - | DW32: - | DX32: - | DY32: - | DZ32: 第一倉庫のタブレットで現品票印刷用に使用
A33: 45755 | B33: 森山貴史 | C33: - | D33: 技術製造部 | E33: - | F33: - | G33: 011 | H33: moriyama | I33: ○ | J33: A | K33: 4 | L33: 4 | M33: 2 | N33: 1 | O33: 4 | P33: 1 | Q33: 4 | R33: 4 | S33: 1 | T33: 4 | U33: 4 | V33: 3 | W33: 3 | X33: 1 | Y33: 1 | Z33: 10365921 | AA33: 10.365921 | AB33: 1 | AC33: 4 | AD33: 1 | AE33: 1 | AF33: 1 | AG33: 1 | AH33: 1 | AI33: 1 | AJ33: 1 | AK33: 1 | AL33: 1 | AM33: 4 | AN33: 1 | AO33: 2 | AP33: 1 | AQ33: 1 | AR33: 1 | AS33: 1 | AT33: 2 | AU33: 2 | AV33: 1 | AW33: 1 | AX33: - | AY33: 14.7 | AZ33: 14.8 | BA33: 51164 | BB33: 4015 | BC33: 3 | BD33: 3291 | BE33: 39 | BF33: 28.165921 | BG33: 54455 | BH33: 4054 | BI33: - | BJ33: 1 | BK33: 1 | BL33: 1 | BM33: 2 | BN33: 3 | BO33: SSC-CL-2-2F-01 | BP33: コスメラボラトリー | BQ33: 2F/事務所 | BR33: - | BS33: - | BT33: - | BU33: - | BV33: 1 | BW33: ↓(ローカル側からコピペしてください。) | BX33: DESKTOP-2N6E4LB | BY33: Intel(R) Core(TM) i3-4000M CPU @ 2.40GHz 2.40 GHz | BZ33: 8.00 GB | CA33: 4CE5BCD4-55FA-4216-8DAC-06311174FC73 | CB33: 00330-80000-00000-AA868 | CC33: 64 ビット オペレーティング システム、x64 ベース プロセッサ | CD33: このディスプレイでは、ペン入力とタッチ入力は利用できません | CE33: ↓(ローカル側からコピペしてください。) | CF33: Windows 10 Pro | CG33: 2009 | CH33: ‎2021/‎07/‎29 | CI33: 19045.561 | CJ33: 9E143056H | CK33: 表記なし | CL33: 2 | CM33: 1 | CN33: 1 | CO33: - | CP33: 2 | CQ33: 4 | CR33: 2 | CS33: 1 | CT33: 2 | CU33: 2 | CV33: 2 | CW33: 4 | CX33: 2 | CY33: 2 | CZ33: 2 | DA33: 2 | DB33: 2 | DC33: 2 | DD33: 2 | DE33: 2 | DF33: 4 | DG33: 2 | DH33: 2 | DI33: 2 | DJ33: 2 | DK33: 2 | DL33: 買替 | DM33: 45943 | DN33: 無 | DO33: - | DP33: ノート | DQ33: 標準性能 | DR33: 1 | DS33: 1 | DT33: 製造記録 | DU33: 2次 | DV33: A | DW33: A | DX33: 1 | DY33: 1
A34: 45755 | B34: 小田晶彦 | C34: - | D34: 技術製造部 | E34: 製造課 | F34: バルク・顆粒 | G34: 013 | H34: oda | I34: ○ | J34: B | K34: 4 | L34: 4 | M34: 2 | N34: 1 | O34: 2 | P34: 1 | Q34: 4 | R34: 4 | S34: 1 | T34: 4 | U34: 4 | V34: 3 | W34: 3 | X34: 1 | Y34: 1 | Z34: 4458809 | AA34: 4.458809 | AB34: 2 | AC34: 2 | AD34: 1 | AE34: 1 | AF34: 1 | AG34: 1 | AH34: 1 | AI34: 1 | AJ34: 1 | AK34: 1 | AL34: 1 | AM34: 3 | AN34: 1 | AO34: 3 | AP34: 1 | AQ34: 1 | AR34: 1 | AS34: 1 | AT34: 1 | AU34: 1 | AV34: 1 | AW34: 1 | AX34: - | AY34: 8.37 | AZ34: 8.46 | BA34: 50788 | BB34: 4263 | BC34: 0.0661 | BD34: 178 | BE34: 6 | BF34: 12.984909 | BG34: 50966 | BH34: 4269 | BI34: - | BJ34: 1 | BK34: 1 | BL34: 1 | BM34: 2 | BN34: 2 | BO34: SSC-CL-5-2F-01 | BP34: コスメラボラトリー | BQ34: 2F/事務所 | BR34: - | BS34: - | BT34: - | BU34: - | BV34: 1 | BW34: ↓(ローカル側からコピペしてください。) | BX34: MYCOMPUTER | BY34: Intel(R) Core(TM) i5-7200U CPU @ 2.50GHz 2.71 GHz | BZ34: 8.00 GB (7.85 GB 使用可能) | CA34: 478EA1FC-AE7C-4FE6-B341-F55F83493682 | CB34: 00325-84915-70665-AAOEM | CC34: 64 ビット オペレーティング システム、x64 ベース プロセッサ | CD34: このディスプレイでは、ペン入力とタッチ入力は利用できません | CE34: ↓(ローカル側からコピペしてください。) | CF34: Windows 10 Home | CG34: 22H2 | CH34: ‎2022/‎12/‎13 | CI34: 19045.561 | CJ34: JPH84738P3 | CK34: Windows Feature Experience Pack 1000.19061.1000.0 | CL34: 2 | CM34: 2 | CN34: 2 | CO34: - | CP34: 1 | CQ34: 4 | CR34: 1 | CS34: 1 | CT34: 1 | CU34: 2 | CV34: 2 | CW34: 3 | CX34: 1 | CY34: 2 | CZ34: 1 | DA34: 2 | DB34: 1 | DC34: 2 | DD34: 2 | DE34: 1 | DF34: 2 | DG34: 2 | DH34: 1 | DI34: 2 | DJ34: 2 | DK34: 2 | DL34: 買替 | DM34: 45943 | DN34: 無 | DO34: - | DP34: デスクトップ | DQ34: 標準性能 | DR34: 1 | DS34: 1 | DT34: 製造記録 | DU34: 2次 | DV34: B | DW34: C | DX34: 0.5 | DY34: 1
A35: 45757 | B35: 上辻耕太 | C35: mouse④ | D35: 技術製造部 | E35: 製造課 | F35: バルク・顆粒 | G35: 054 | H35: uetsugi | I35: × | J35: B | K35: 4 | L35: 4 | M35: 2 | N35: 1 | O35: 3 | P35: 3 | Q35: 3 | R35: 3 | S35: 1 | T35: 4 | U35: 4 | V35: 2 | W35: 2 | X35: 1 | Y35: 1 | Z35: 10238 | AA35: 0.010238 | AB35: 2 | AC35: 4 | AD35: 1 | AE35: 1 | AF35: 1 | AG35: 1 | AH35: 1 | AI35: 1 | AJ35: 1 | AK35: 1 | AL35: 1 | AM35: 1 | AN35: 1 | AO35: 3 | AP35: 1 | AQ35: 1 | AR35: 1 | AS35: 1 | AT35: 1 | AU35: 1 | AV35: 1 | AW35: 1 | AX35: - | AY35: 10.7 | AZ35: 10.7 | BA35: 8134 | BB35: 1356 | BC35: - | BD35: - | BE35: - | BF35: 10.710238 | BG35: 8134 | BH35: 1356 | BI35: - | BJ35: 2 | BK35: 3 | BL35: 1 | BM35: 2 | BN35: 2 | BO35: SSC-CF-5-1F-03 | BP35: コスメファクトリー | BQ35: 1F/バルク室 | BR35: - | BS35: - | BT35: - | BU35: - | BV35: 1 | BW35: ↓(ローカル側からコピペしてください。) | BX35: DESKTOP-E2UBCNM | BY35: Inter® Celeron® N4100 CPU @ 1.10GHz 1.10GHz | BZ35: 4.00GB(3.83GB使用可能) | CA35: 36BCAE6C-5095-4DA1-83E1-8CE32D22D812 | CB35: 00330-54055-59708-AAOEM | CC35: 64 ビット オペレーティング システム、x64 ベース プロセッサ | CD35: 10 タッチ ポイントでのペンとタッチのサポート | CE35: ↓(ローカル側からコピペしてください。) | CF35: Windows 11 Pro | CG35: 23H2 | CH35: 44902 | CI35: 22631.504 | CJ35: U104910839 | CK35: Windows 機能エクスペリエンスパック 1000.22700.1074.0 | CL35: 1 | CM35: 2 | CN35: 1 | CO35: - | CP35: 1 | CQ35: 3 | CR35: 1 | CS35: 1 | CT35: 1 | CU35: 1 | CV35: 3 | CW35: 3 | CX35: 1 | CY35: 3 | CZ35: 1 | DA35: 3 | DB35: 3 | DC35: 1 | DD35: 1 | DE35: 1 | DF35: 1 | DG35: 1 | DH35: 1 | DI35: 1 | DJ35: 1 | DK35: 1 | DL35: - | DM35: - | DN35: - | DO35: - | DP35: - | DQ35: - | DR35: - | DS35: - | DT35: - | DU35: - | DV35: - | DW35: - | DX35: - | DY35: -
A36: 45757 | B36: 外間裕貴人 | C36: mouse④ | D36: 技術製造部 | E36: 製造課 | F36: バルク・顆粒 | G36: 116 | H36: hokama | I36: × | J36: B | K36: 1 | L36: 1 | M36: 1 | N36: 1 | O36: 1 | P36: 1 | Q36: 3 | R36: 1 | S36: 1 | T36: 4 | U36: 3 | V36: 1 | W36: 2 | X36: 2 | Y36: 1 | Z36: 2552433 | AA36: 2.552433 | AB36: 4 | AC36: 3 | AD36: 1 | AE36: 2 | AF36: 1 | AG36: 1 | AH36: 1 | AI36: 1 | AJ36: 1 | AK36: 1 | AL36: 1 | AM36: 1 | AN36: 1 | AO36: 2 | AP36: 1 | AQ36: 1 | AR36: 1 | AS36: 1 | AT36: 1 | AU36: 1 | AV36: 1 | AW36: 1 | AX36: - | AY36: 3.71 | AZ36: 3.73 | BA36: 12036 | BB36: 1535 | BC36: - | BD36: - | BE36: - | BF36: 6.282433 | BG36: 12036 | BH36: 1535 | BI36: - | BJ36: 2 | BK36: 3 | BL36: 1 | BM36: 2 | BN36: 4 | BO36: SSC-CF-5-1F-03 | BP36: コスメファクトリー | BQ36: 1F/バルク室 | BR36: - | BS36: - | BT36: - | BU36: - | BV36: 1 | BW36: ↓(ローカル側からコピペしてください。) | BX36: DESKTOP-E2UBCNM | BY36: Inter® Celeron® N4100 CPU @ 1.10GHz 1.10GHz | BZ36: 4.00GB(3.83GB使用可能) | CA36: 36BCAE6C-5095-4DA1-83E1-8CE32D22D812 | CB36: 00330-54055-59708-AAOEM | CC36: 64 ビット オペレーティング システム、x64 ベース プロセッサ | CD36: 10 タッチ ポイントでのペンとタッチのサポート | CE36: ↓(ローカル側からコピペしてください。) | CF36: Windows 11 Pro | CG36: 23H2 | CH36: 44902 | CI36: 22631.504 | CJ36: U104910839 | CK36: Windows 機能エクスペリエンスパック 1000.22700.1074.0 | CL36: 1 | CM36: 1 | CN36: 1 | CO36: - | CP36: 2 | CQ36: 3 | CR36: 2 | CS36: 2 | CT36: 2 | CU36: 2 | CV36: 2 | CW36: 2 | CX36: 2 | CY36: 2 | CZ36: 2 | DA36: 2 | DB36: 2 | DC36: 2 | DD36: 2 | DE36: 2 | DF36: 2 | DG36: 2 | DH36: 2 | DI36: 2 | DJ36: 2 | DK36: 2 | DL36: - | DM36: - | DN36: - | DO36: - | DP36: - | DQ36: - | DR36: 1 | DS36: 1 | DT36: 製造記録 | DU36: 2次 | DV36: B | DW36: B | DX36: 0 | DY36: 1
A37: 45757 | B37: 松井敬視 | C37: mouse⑤ | D37: 技術製造部 | E37: 製造課 | F37: バルク・顆粒 | G37: 128 | H37: matsui | I37: × | J37: B | K37: 1 | L37: 1 | M37: 1 | N37: 1 | O37: 4 | P37: 1 | Q37: 4 | R37: 4 | S37: 1 | T37: 4 | U37: 2 | V37: 3 | W37: 2 | X37: 1 | Y37: 1 | Z37: 336553 | AA37: 0.336553 | AB37: 1 | AC37: 1 | AD37: 1 | AE37: 1 | AF37: 1 | AG37: 1 | AH37: 1 | AI37: 1 | AJ37: 1 | AK37: 1 | AL37: 1 | AM37: 1 | AN37: 1 | AO37: 1 | AP37: 1 | AQ37: 1 | AR37: 1 | AS37: 1 | AT37: 1 | AU37: 1 | AV37: 1 | AW37: 1 | AX37: - | AY37: 4.27e-05 | AZ37: 4.8e-05 | BA37: 5 | BB37: 0 | BC37: 0 | BD37: 0 | BE37: 0 | BF37: 0.336601 | BG37: 5 | BH37: 0 | BI37: - | BJ37: 2 | BK37: 3 | BL37: 1 | BM37: 2 | BN37: 3 | BO37: SSC-CF-5-1F-03 | BP37: コスメファクトリー | BQ37: 1F/バルク室 | BR37: - | BS37: - | BT37: - | BU37: - | BV37: 1 | BW37: ↓(ローカル側からコピペしてください。) | BX37: DESKTOP-C5JS0KA | BY37: Inter® Celeron® N4100 CPU @ 1.10GHz 1.10GHz | BZ37: 4.00GB(3.83GB使用可能) | CA37: C58AF61C-10BC-43E5-A1F6-9481EBDF2A8B | CB37: 00330-54055-59708-AAOEM | CC37: 64 ビット オペレーティング システム、x64 ベース プロセッサ | CD37: 10 タッチ ポイントでのペンとタッチのサポート | CE37: ↓(ローカル側からコピペしてください。) | CF37: Windows 10 Pro | CG37: 23H2 | CH37: 44917 | CI37: 22631.519 | CJ37: U104910837 | CK37: Windows 機能エクスペリエンスパック 1000.22700.1077.0 | CL37: 1 | CM37: 1 | CN37: 1 | CO37: - | CP37: 1 | CQ37: 3 | CR37: 1 | CS37: 1 | CT37: 1 | CU37: 2 | CV37: 2 | CW37: 2 | CX37: 1 | CY37: 2 | CZ37: 2 | DA37: 2 | DB37: 2 | DC37: 1 | DD37: 1 | DE37: 2 | DF37: 2 | DG37: 2 | DH37: 1 | DI37: 3 | DJ37: 2 | DK37: 2 | DL37: - | DM37: - | DN37: - | DO37: - | DP37: - | DQ37: - | DR37: 1 | DS37: 1 | DT37: 製造記録 | DU37: 2次 | DV37: B | DW37: B | DX37: 0 | DY37: 1
A38: 45755 | B38: 小田勇雄 | C38: - | D38: 技術製造部 | E38: 製造課 | F38: 充填包装 | G38: 021 | H38: oda-i | I38: ○ | J38: B | K38: 4 | L38: 3 | M38: 3 | N38: 4 | O38: 2 | P38: 2 | Q38: 2 | R38: 1 | S38: 4 | T38: 4 | U38: 3 | V38: 4 | W38: 3 | X38: 4 | Y38: 1 | Z38: 11753233 | AA38: 11.753233 | AB38: 1 | AC38: 1 | AD38: 1 | AE38: 1 | AF38: 1 | AG38: 1 | AH38: 1 | AI38: 1 | AJ38: 1 | AK38: 1 | AL38: 1 | AM38: 4 | AN38: 1 | AO38: 3 | AP38: 1 | AQ38: 1 | AR38: 1 | AS38: 1 | AT38: 1 | AU38: 1 | AV38: 1 | AW38: 1 | AX38: - | AY38: 17.2 | AZ38: 17.3 | BA38: 67197 | BB38: 3068 | BC38: 0.214 | BD38: 466 | BE38: 59 | BF38: 29.267233 | BG38: 67663 | BH38: 3127 | BI38: - | BJ38: 1 | BK38: 1 | BL38: 1 | BM38: 2 | BN38: 3 | BO38: SSC-CL-2-2F-01 | BP38: コスメラボラトリー | BQ38: 2F/事務所 | BR38: SSC-CF-2-2F-01 | BS38: SSC-CF-2-2F-03 | BT38: SSC-CL-2-2F-03 | BU38: - | BV38: 1 | BW38: ↓(ローカル側からコピペしてください。) | BX38: DESKTOP-GP448S6 | BY38: Intel(R) Core(TM) i3-6006U CPU @ 2.00GHz 2.00 GHz | BZ38: 4.00 GB | CA38: 14002981-0578-45F8-ABD6-83D4CF16AA90 | CB38: 00330-50746-19089-AAOEM | CC38: 64 ビット オペレーティング システム、x64 ベース プロセッサ | CD38: このディスプレイでは、ペン入力とタッチ入力は利用できません | CE38: ↓(ローカル側からコピペしてください。) | CF38: Windows 11 Pro | CG38: 21H2 | CH38: ‎2021/‎10/‎05 | CI38: 22000.254 | CJ38: YH038702H | CK38: Windows 機能エクスペリエンス パック 1000.22001.1000.0 | CL38: 2 | CM38: 1 | CN38: 1 | CO38: - | CP38: 1 | CQ38: 2 | CR38: 1 | CS38: 1 | CT38: 1 | CU38: 2 | CV38: 2 | CW38: 4 | CX38: 1 | CY38: 2 | CZ38: 1 | DA38: 2 | DB38: 1 | DC38: 1 | DD38: 1 | DE38: 1 | DF38: 2 | DG38: 2 | DH38: 2 | DI38: 2 | DJ38: 1 | DK38: 1 | DL38: 買替 | DN38: 無 | DO38: - | DP38: ノート | DQ38: 標準性能 | DR38: 1 | DS38: 1 | DT38: 製造記録 | DU38: 2次 | DV38: B | DW38: C | DX38: 0.5 | DY38: 1
A39: 45756 | B39: 東口智一 | C39: - | D39: 技術製造部 | E39: 製造課 | F39: 充填包装 | G39: 066 | H39: higashiguchi | I39: ○ | J39: B | K39: 4 | L39: 3 | M39: 3 | N39: 3 | O39: 3 | P39: 1 | Q39: 3 | R39: 1 | S39: 2 | T39: 4 | U39: 2 | V39: 2 | W39: 2 | X39: 2 | Y39: 1 | Z39: 8126481 | AA39: 8.126481 | AB39: 4 | AC39: 1 | AD39: 1 | AE39: 2 | AF39: 1 | AG39: 1 | AH39: 1 | AI39: 4 | AJ39: 1 | AK39: 1 | AL39: 1 | AM39: 4 | AN39: 1 | AO39: 1 | AP39: 1 | AQ39: 1 | AR39: 1 | AS39: 1 | AT39: 2 | AU39: 1 | AV39: 1 | AW39: 1 | AX39: - | AY39: 12.2 | AZ39: 12.2 | BA39: 21812 | BB39: 1873 | BC39: 0.0418 | BD39: 39 | BE39: 2 | BF39: 20.368281 | BG39: 21851 | BH39: 1875 | BI39: - | BJ39: 1 | BK39: 1 | BL39: 1 | BM39: 2 | BN39: 2 | BO39: SSC-CF-5-2F-03 | BP39: コスメファクトリー | BQ39: 2F/充填ライン南 | BR39: - | BS39: - | BT39: - | BU39: - | BV39: 1 | BW39: ↓(ローカル側からコピペしてください。) | BX39: DESKTOP-HCA34M3 | BY39: Intel(R) Core(TM) i5-4300M CPU @ 2.60GHz 2.59 GHz | BZ39: 8.00 GB (7.90 GB 使用可能) | CA39: 91B98C73-78E2-40D4-9B65-7738EB5A5311 | CB39: 00330-50421-18011-AAOEM | CC39: 64 ビット オペレーティング システム、x64 ベース プロセッサ | CD39: このディスプレイでは、ペン入力とタッチ入力は利用できません | CE39: ↓(ローカル側からコピペしてください。) | CF39: Windows 11 Pro | CG39: 22H2 | CH39: ‎2023/‎07/‎07 | CI39: 22621.432 | CJ39: R9-0MWT4617/02 | CK39: Windows Feature Experience Pack 1000.22700.1041.0 | CL39: 2 | CM39: 2 | CN39: 2 | CO39: - | CP39: 1 | CQ39: 2 | CR39: 1 | CS39: 1 | CT39: 1 | CU39: 3 | CV39: 2 | CW39: 4 | CX39: 1 | CY39: 2 | CZ39: 1 | DA39: 2 | DB39: 2 | DC39: 1 | DD39: 1 | DE39: 2 | DF39: 2 | DG39: 2 | DH39: 1 | DI39: 2 | DJ39: 2 | DK39: 2 | DL39: 買替 | DN39: 無 | DO39: - | DP39: ノート | DQ39: 標準性能 | DR39: 1 | DS39: 1 | DT39: 製造記録 | DU39: 2次 | DV39: B | DW39: C | DX39: 0.5 | DY39: 1
A40: 45756 | B40: 藤本洸平 | C40: LAVIE⑤ | D40: 技術製造部 | E40: 製造課 | F40: 充填包装 | G40: 091 | H40: fujimoto | I40: × | J40: B | K40: 4 | L40: 2 | M40: 3 | N40: 4 | O40: 3 | P40: 1 | Q40: 4 | R40: 4 | S40: 4 | T40: 4 | U40: 2 | V40: 4 | W40: 2 | X40: 1 | Y40: 1 | Z40: 5777177 | AA40: 5.777177 | AB40: 4 | AC40: 4 | AD40: 1 | AE40: 4 | AF40: 1 | AG40: 1 | AH40: 1 | AI40: 1 | AJ40: 1 | AK40: 1 | AL40: 1 | AM40: 3 | AN40: 1 | AO40: 3 | AP40: 1 | AQ40: 1 | AR40: 1 | AS40: 1 | AT40: 1 | AU40: 1 | AV40: 1 | AW40: 1 | AX40: - | AY40: 7.16 | AZ40: 7.19 | BA40: 14959 | BB40: 1468 | BC40: 0 | BD40: 0 | BE40: 0 | BF40: 12.967177 | BG40: 14959 | BH40: 1468 | BI40: - | BJ40: 2 | BK40: 3 | BL40: 1 | BM40: 2 | BN40: 3 | BO40: SSC-CF-2-2F-02 | BP40: コスメファクトリー | BQ40: 2F/充填ライン北 | BR40: - | BS40: - | BT40: - | BU40: - | BV40: 3 | BW40: ↓(ローカル側からコピペしてください。) | BX40: DESKTOP-53AITPN | BY40: Intel(R) Celeron(R) N4100 CPU @ 1.10GHz 1.10 GHz | BZ40: 4.00 GB (3.64 GB 使用可能) | CA40: EE72E688-3097-4CF6-A888-0B57A41A058E | CB40: 00330-53364-74161-AAOEM | CC40: 64 ビット オペレーティング システム、x64 ベース プロセッサ | CD40: 10 タッチ ポイントでのペンとタッチのサポート | CE40: ↓(ローカル側からコピペしてください。) | CF40: Windows 11 Pro | CG40: 24H2 | CH40: 2025/‎02/‎10 | CI40: 26100.348 | CJ40: PC-FM150PAL | CK40: Windows 機能エクスペリエンス パック 1000.26100.54.0 | CL40: 1 | CM40: 2 | CN40: 2 | CO40: - | CP40: 2 | CQ40: 4 | CR40: 2 | CS40: 2 | CT40: 2 | CU40: 3 | CV40: 3 | CW40: 4 | CX40: 2 | CY40: 2 | CZ40: 2 | DA40: 2 | DB40: 3 | DC40: 2 | DD40: 2 | DE40: 2 | DF40: 3 | DG40: 2 | DH40: 2 | DI40: 2 | DJ40: 2 | DK40: 2 | DL40: - | DM40: - | DN40: - | DO40: - | DP40: - | DQ40: - | DR40: 1 | DS40: 1 | DT40: 製造記録 | DU40: 2次 | DV40: B | DW40: B | DX40: 0 | DY40: 1
